Workbook
Name Database: #REF!
Name Database: #REF!
Name dxn: [1]dxnsjtempsheet!$A$1:$G$65536
Name fzxm: '[2]披露表(上市)'!$D$12:$D$23
Name fzxm_qt: '[3]披露表(国资)'!$C$48:$C$65
Name fzxm_xj: '[3]披露表(国资)'!$C$10:$C$27
Name fzxm_yc: '[3]披露表(国资)'!$C$29:$C$46
Name fzxmxj: '[4]披露表(上市)'!$C$11:$C$14
Name fzxmyh: '[4]披露表(上市)'!$C$16:$C$19
Name gzfzxm: '[5]披露表(国资)'!$C$10:$C$11
Name hkd: 1.0611
Name KMDM: #REF!
Name KMDM: #REF!
Name KMDM: #REF!
Name usd: 8.2773
Name 附注: #REF!
Name 附注: #REF!
Name 固定资产清单: #REF!
Name 固定资产清单: #REF!
Name 应付帐款: #REF!
Name 应付帐款: #REF!
Name 应付帐款: #REF!
Name 应收帐款: #REF!
Name 应收帐款: #REF!
Name 应收帐款: #REF!
Name Database: #REF!
Name KMDM: #REF!
Name 附注: #REF!
Name 固定资产清单: #REF!
Name 应付帐款: #REF!
Name 应收帐款: #REF!
Name Database: #REF!
Name KMDM: #REF!
Name 附注: #REF!
Name 固定资产清单: #REF!
Name 应付帐款: #REF!
Name 应收帐款: #REF!
Name Database: #REF!
Name KMDM: #REF!
Name 附注: #REF!
Name 固定资产清单: #REF!
Name 应付帐款: #REF!
Name 应收帐款: #REF!
Name Database: #REF!
Name KMDM: #REF!
Name 附注: #REF!
Name 固定资产清单: #REF!
Name 应付帐款: #REF!
Name 应收帐款: #REF!

Sheet 基本信息
B1: 公司名称 | C1: 简称 | E1: 股权结构图：
A2: 母公司 | B2: 飞而康快速制造科技有限责任公司 | C2: 飞而康快速
A3: 子公司1 | C3: 飞而康新材料
A4: 子公司2 | C4: 飞而康精铸
A5: 子公司3 | C5: 飞而康热等静压 | F5: 待更新
A6: 子公司4
A7: 子公司5
B9: 截止日 | C9: 会计年度
A11: 第一期 | B11: 44926 | C11: 2022年度
A12: 第二期 | B12: 45291 | C12: 2023年度
A13: 第三期 | B13: 45657 | C13: 2024年度
A14: 第四期 | B14: 45991 | C14: 2025年度
B15: 签名 | C15: 日期：
A16: 编制人：
A17: 复核人：

Sheet 利润表-新材料+快速
A1: 利 润 表-合并报表
C2: 会企02表 | D2: =(B5-B8)/B5 -> 0.68475341 | E2: =(C5-C8)/C5 -> 0.17882376 | K2: =(I5-I8)/I5 -> 0.13633661 | L2: =(J5-J8)/J5 -> 0.099941107 | Q2: =C5-C8 -> 23966730 | W2: =W3/W5 -> 0.70725114 | X2: =X3/X5 -> 0.16037483 | Z2: 9585464.7 | AA2: 70777394
A3: 单位名称：飞而康快速制造科技有限责任公司 | B3: =合并试算平衡表!B6 -> 45991 | C3: 单位：元 | F3: 注意修改！！！ | Q3: =Q2/C5 -> 0.17882376 | W3: =W5-W8 -> 11607351 | X3: =X5-X8 -> 19692046 | Z3: =W5-Z2 -> 6826458.7 | AA3: =X5-AA2 -> 52010240 | AC3: =AA5-AA8 -> 9056400.4 | AD3: 差异系精铸管理费嘎差
A4: 项 目 | B4: 合并口径本期金额 | C4: 合并口径本年累计金额 | E4: =(D5-E8)/D5 -> #DIV/0! | F4: 2410月金额 | G4: 2410月累计金额 | I4: 2306数据 | J4: 2306合计 | K4: 差异1 | L4: 差异2 | Q4: 精铸本月 | R4: 精铸累计 | S4: 热等静压本月 | T4: 热等静压累计 | U4: 合并抵消还原本月 | V4: 合并抵消还原累计 | W4: 快速+新材料本期金额 | X4: 快速+新材料本年累计金额
A5: 一、营业收入 | B5: =C5-G5 -> 17635913 | C5: =C6+C7 -> 1.340243e+08 | F5: 17470608 | G5: 1.1638839e+08 | I5: 14520603 | J5: 46494371 | K5: =B5-I5 -> 3115309.8 | L5: =C5-J5 -> 87529932 | M5: =K5/I5 -> 0.21454411 | N5: =L5/J5 -> 1.882592 | Q5: =精铸PL!B5 -> 757088.85 | R5: =精铸PL!C5 -> 6894779.8 | S5: =热等静压PL!B5 -> 1375041.3 | T5: =热等静压PL!C5 -> 18429412 | U5: =SUM(U6:U7) -> 908140.93 | V5: =SUM(V6:V7) -> 14087523 | W5: =B5-Q5-S5+U5 -> 16411923 | X5: =C5-R5-T5+V5 -> 1.2278763e+08 | Z5: =W5-新材料PL!D6-快速PL!C6 -> -1276342 | AA5: =X5-新材料PL!E6-快速PL!D6 -> -1.2233872e+08
A6: 其中：主营业务收入 | B6: =C6-G6 -> 18206795 | C6: =合并试算平衡表!K125 -> 1.3352726e+08 | F6: 17406946 | G6: 1.1532047e+08 | I6: 14326059 | J6: 45162004 | K6: =B6-I6 -> 3880735.7 | L6: =C6-J6 -> 88365258 | M6: =K6/I6 -> 0.27088647 | N6: =L6/J6 -> 1.9566284 | Q6: =精铸PL!B6 -> 757088.85 | R6: =精铸PL!C6 -> 6890832.9 | S6: =热等静压PL!B6 -> 1375041.3 | T6: =热等静压PL!C6 -> 18429412 | U6: =66814.16+717929.94 -> 784744.1 | V6: =252654.87+12342539.58 -> 12595194 | W6: =B6-Q6-S6+U6 -> 16859409 | X6: =C6-R6-T6+V6 -> 1.2080221e+08 | Z6: =W6-新材料PL!D7-快速PL!C7 -> -133883.45 | AA6: =X6-新材料PL!E7-快速PL!D7 -> -1.0035663e+08 | AC6: =93137171.52 -> 93137172
A7: 其他业务收入 | B7: =C7-G7 -> -570882.32 | C7: =合并试算平衡表!K126 -> 497041.45 | F7: 63662.36 | G7: 1067923.8 | I7: 194543.53 | J7: 1332367.7 | K7: =B7-I7 -> -765425.85 | L7: =C7-J7 -> -835326.27 | M7: =K7/I7 -> -3.9344709 | N7: =L7/J7 -> -0.62694875 | Q7: =精铸PL!B7 -> 0 | R7: =精铸PL!C7 -> 3946.9 | S7: =热等静压PL!B7 -> 0 | T7: =热等静压PL!C7 -> 0 | U7: 123396.83 | V7: 1492328.1 | W7: =B7-Q7-S7+U7 -> -447485.49 | X7: =C7-R7-T7+V7 -> 1985422.6 | Z7: =W7-新材料PL!D8-快速PL!C8 -> -1142458.5 | AA7: =X7-新材料PL!E8-快速PL!D8 -> -21982083 | AC7: =3909115.43-合并调整抵消分录!F224 -> 3909115.4
A8: 减：营业成本 | B8: =C8-G8 -> 5559661.3 | C8: =C9+C10 -> 1.1005757e+08 | F8: 15004809 | G8: 1.0449791e+08 | I8: 12540913 | J8: 41847672 | K8: =B8-I8 -> -6981251.6 | L8: =C8-J8 -> 68209901 | M8: =K8/I8 -> -0.5566781 | N8: =L8/J8 -> 1.6299569 | Q8: =精铸PL!B8 -> 765142.84 | R8: =精铸PL!C8 -> 5464056.9 | S8: =热等静压PL!B8 -> 876946.02 | T8: =热等静压PL!C8 -> 15352894 | U8: =U9+U10 -> 886999.42 | V8: =V9+V10 -> 13854966 | W8: =B8-Q8-S8+U8 -> 4804571.9 | X8: =C8-R8-T8+V8 -> 1.0309559e+08 | Z8: =W8-新材料PL!D9-快速PL!C9 -> -11959845 | AA8: =X8-新材料PL!E9-快速PL!D9 -> -1.3139512e+08
A9: 其中：主营业务成本 | B9: =C9-G9 -> 6384482.1 | C9: =合并试算平衡表!K128 -> 1.1005757e+08 | F9: 14981283 | G9: 1.0367309e+08 | I9: 12420465 | J9: 41161831 | K9: =B9-I9 -> -6035982.6 | L9: =C9-J9 -> 68895742 | M9: =K9/I9 -> -0.48597075 | N9: =L9/J9 -> 1.6737774 | Q9: =精铸PL!B9 -> 765142.84 | R9: =精铸PL!C9 -> 5464056.9 | S9: =热等静压PL!B9 -> 876946.02 | T9: =热等静压PL!C9 -> 15352894 | U9: =U6 -> 784744.1 | V9: =V6 -> 12595194 | W9: =B9-Q9-S9+U9 -> 5527137.4 | X9: =C9-R9-T9+V9 -> 1.0183582e+08 | Z9: =W9-新材料PL!D10-快速PL!C10 -> -10586565 | AA9: =X9-新材料PL!E10-快速PL!D10 -> -1.0918221e+08
A10: 其他业务成本 | B10: =C10-G10 -> -824820.83 | C10: =合并试算平衡表!K129 -> 0 | F10: 23525.8 | G10: 824820.83 | I10: 120448.22 | J10: 685841.17 | K10: =B10-I10 -> -945269.05 | L10: =C10-J10 -> -685841.17 | M10: =K10/I10 -> -7.8479288 | N10: =L10/J10 -> -1 | Q10: =精铸PL!B10 -> 0 | R10: =精铸PL!C10 -> 0 | S10: =热等静压PL!B10 -> 0 | T10: =热等静压PL!C10 -> 0 | U10: =U7-U13 -> 102255.32 | V10: =V7-V13 -> 1259771.5 | W10: =B10-Q10-S10+U10 -> -722565.51 | X10: =C10-R10-T10+V10 -> 1259771.5 | Z10: =W10-新材料PL!D11-快速PL!C11 -> -1373280.1 | AA10: =X10-新材料PL!E11-快速PL!D11 -> -22212905
A11: 营业税金及附加 | B11: =C11-G11 -> -997712.24 | C11: =合并试算平衡表!K130 -> 829444.38 | D11: =C11/$C$5 -> 0.006188761 | E11: =D5*0.007 -> 0 | F11: 71444.48 | G11: 1827156.6 | I11: 90103.84 | J11: 475596.62 | K11: =B11-I11 -> -1087816.1 | L11: =C11-J11 -> 353847.76 | M11: =K11/I11 -> -12.072916 | N11: =L11/J11 -> 0.74400815 | O11: 快速资产转移新材料4月份开票确认收入6227.38形成增值税 809.56 及附加税97.15万元 | Q11: =精铸PL!B11 -> 4572.03 | R11: =精铸PL!C11 -> 27595.05 | S11: =热等静压PL!B11 -> 1020.39 | T11: =热等静压PL!C11 -> 6811.17 | W11: =B11-Q11-S11+U11 -> -1003304.7 | X11: =C11-R11-T11+V11 -> 795038.16 | Z11: =W11-新材料PL!D12-快速PL!C12 -> -1061049.2 | AA11: =X11-新材料PL!E12-快速PL!D12 -> -1061049.2
A12: 销售费用 | B12: =C12-G12 -> -521103.68 | C12: =合并试算平衡表!K131 -> 8045698 | D12: =C12/$C$5 -> 0.060031634 | E12: =D12*$D$5 -> 0 | F12: 964070.03 | G12: 8566801.7 | I12: 938241.48 | J12: 4692976 | K12: =B12-I12 -> -1459345.2 | L12: =C12-J12 -> 3352722 | M12: =K12/I12 -> -1.5554046 | N12: =L12/J12 -> 0.71441277 | O12: 营业收入增长，销售费用略有增长相对合理 | Q12: =精铸PL!B12 -> 48065.29 | R12: =精铸PL!C12 -> 533425.91 | S12: =热等静压PL!B12 -> 117870.1 | T12: =热等静压PL!C12 -> 641148.73 | W12: =B12-Q12-S12+U12 -> -687039.07 | X12: =C12-R12-T12+V12 -> 6871123.3 | Z12: =W12-新材料PL!D13-快速PL!C13 -> -2731662.9 | AA12: =X12-新材料PL!E13-快速PL!D13 -> -2731662.9
A13: 管理费用 | B13: =C13-G13 -> -766556.38 | C13: =合并试算平衡表!K132 -> 8350965.1 | D13: =C13/$C$5 -> 0.062309334 | E13: =D13*$D$5 -> 0 | F13: 891664.76 | G13: 9117521.4 | I13: 941704.85 | J13: 4286617.3 | K13: =B13-I13 -> -1708261.2 | L13: =C13-J13 -> 4064347.8 | M13: =K13/I13 -> -1.8140092 | N13: =L13/J13 -> 0.94814803 | O13: 上年同期因审计调整，红冲当月费用26.20万元 | Q13: =精铸PL!B13 -> 66954.09 | R13: =精铸PL!C13 -> 635654.87 | S13: =热等静压PL!B13 -> 37604.38 | T13: =热等静压PL!C13 -> 446142.54 | U13: 21141.51 | V13: 232556.61 | W13: =B13-Q13-S13+U13 -> -849973.34 | X13: =C13-R13-T13+V13 -> 7501724.3 | Z13: =W13-新材料PL!D14-快速PL!C14 -> -1534749.7 | AA13: =X13-新材料PL!E14-快速PL!D14 -> -1534749.7
A14: 研发费用 | B14: =C14-G14 -> 942695.37 | C14: =合并试算平衡表!K133 -> 19920178 | D14: =C14/$C$5 -> 0.14863109 | E14: =D14*$D$5 -> 0 | F14: 2625421.1 | G14: 18977483 | I14: 1386872.1 | J14: 8292064.8 | K14: =B14-I14 -> -444176.74 | L14: =C14-J14 -> 11628113 | M14: =K14/I14 -> -0.32027231 | N14: =L14/J14 -> 1.4023182 | O14: 上年同期将1-3月部分误入3D生产成本的研发费用调整调回研发费用-直接投入 | Q14: =精铸PL!B14 -> 23475.81 | R14: =精铸PL!C14 -> 652802.07 | S14: =热等静压PL!B14 -> 166797.05 | T14: =热等静压PL!C14 -> 892711.12 | W14: =B14-Q14-S14+U14 -> 752422.51 | X14: =C14-R14-T14+V14 -> 18374665 | Z14: =W14-新材料PL!D15-快速PL!C15 -> -4055269 | AA14: =X14-新材料PL!E15-快速PL!D15 -> -4055269
A15: 财务费用 | B15: =C15-G15 -> -224415.61 | C15: =合并试算平衡表!K134 -> 4508765.3 | D15: =C15/$C$5 -> 0.033641401 | E15: =D15*$D$5 -> 0 | F15: 400727.74 | G15: 4733180.9 | I15: 523640.15 | J15: 2939834.1 | K15: =B15-I15 -> -748055.76 | L15: =C15-J15 -> 1568931.2 | M15: =K15/I15 -> -1.4285684 | N15: =L15/J15 -> 0.53368016 | O15: 跟产业集团借款3000万元，每月约增加15万财务费用 | Q15: =精铸PL!B15 -> 20294.88 | R15: =精铸PL!C15 -> 175284.93 | S15: =热等静压PL!B15 -> 416.99 | T15: =热等静压PL!C15 -> -2452.71 | U15: 0 | V15: 0 | W15: =B15-Q15-S15+U15 -> -245127.48 | X15: =C15-R15-T15+V15 -> 4335933.1 | Z15: =W15-新材料PL!D16-快速PL!C16 -> -659752.5 | AA15: =X15-新材料PL!E16-快速PL!D16 -> -659752.5
A16: 资产减值损失 | B16: =C16-G16 -> 0 | C16: =合并试算平衡表!K140 -> 0 | F16: 0 | G16: 0 | I16: 0 | J16: -7500 | K16: =B16-I16 -> 0 | L16: =C16-J16 -> 7500 | W16: =B16-Q16-S16+U16 -> 0 | X16: =C16-R16-T16+V16 -> 0
A17: 信用减值损失 | B17: =C17-G17 -> -579092.11 | C17: =合并试算平衡表!K139 -> -1780058.3 | F17: 0 | G17: -1200966.1 | K17: =B17-I17 -> -579092.11 | L17: =C17-J17 -> -1780058.3 | Q17: =-精铸PL!B17 -> 0 | R17: =精铸PL!C17 -> 45991.45 | S17: =-热等静压PL!B17 -> 0 | T17: =热等静压PL!C17 -> -139781.06 | W17: =B17-Q17-S17+U17 -> -579092.11 | X17: =C17-R17-T17+V17 -> -1686268.6 | Z17: =W17+新材料PL!D18+快速PL!C18 -> -579092.11 | AA17: =X17+新材料PL!E18+快速PL!D18 -> -2793445.2
A18: 加：公允价值变动收益（损失以"-"填列） | B18: =C18-G18 -> 0 | C18: 0 | F18: 0 | G18: 0 | K18: =B18-I18 -> 0 | L18: =C18-J18 -> 0 | W18: =B18-Q18-S18+U18 -> 0 | X18: =C18-R18-T18+V18 -> 0
A19: 投资收益（损失以"-"填列） | B19: =C19-G19 -> 713796.94 | C19: =合并试算平衡表!K136 -> 853056.55 | F19: 3.4924597e-10 | G19: 139259.61 | I19: 12833.33 | J19: 94275.86 | K19: =B19-I19 -> 700963.61 | L19: =C19-J19 -> 758780.69 | W19: =B19-Q19-S19+U19 -> 713796.94 | X19: =C19-R19-T19+V19 -> 853056.55 | AA19: 2411
A20: 其中：对联营企业和合营企业的投资收益 | B20: =C20-G20 -> 0 | C20: 0 | F20: 0 | G20: 0 | K20: =B20-I20 -> 0 | L20: =C20-J20 -> 0 | W20: =B20-Q20-S20+U20 -> 0 | X20: =C20-R20-T20+V20 -> 0 | Z20: 236635.29 | AA20: 新材料-热压背靠背收入
A21: 其他收益 | B21: =C21-G21 -> 622840.85 | C21: =合并试算平衡表!K135 -> 1305528.3 | F21: 165040 | G21: 682687.46 | I21: 0 | J21: 153443.41 | K21: =B21-I21 -> 622840.85 | L21: =C21-J21 -> 1152084.9 | Q21: =精铸PL!B21 -> 175000 | R21: =精铸PL!C21 -> 559647.46 | S21: =热等静压PL!B21 -> 0 | T21: =热等静压PL!C21 -> 0 | W21: =B21-Q21-S21+U21 -> 447840.85 | X21: =C21-R21-T21+V21 -> 745880.85 | Z21: =AB28+AB31+AB32 -> 14465224 | AA21: 3D
A22: 二、营业利润（亏损以"－"号填列） | B22: =C22-G22 -> 14400889 | C22: =C5-C8-C11-C12-C13-C14-C15+C16+C18+C19+C21+C17 -> -17309794 | F22: -2322488.7 | G22: -31710684 | I22: -1888039.3 | J22: -15785171 | K22: =B22-I22 -> 16288929 | L22: =C22-J22 -> -1524623.8 | Q22: =Q5-Q8-Q11-Q12-Q13-Q14-Q15+Q16+Q18+Q19+Q21+Q17 -> 3583.91 | R22: =R5-R8-R11-R12-R13-R14-R15+R16+R18+R19+R21+R17 -> 11598.91 | S22: =S5-S8-S11-S12-S13-S14-S15+S16+S18+S19+S21+S17 -> 174386.35 | T22: =T5-T8-T11-T12-T13-T14-T15+T16+T18+T19+T21+T17 -> 952375.44 | W22: =W5-W8-W11-W12-W13-W14-W15+W16+W18+W19+W21+W17 -> 14222919 | X22: =X5-X8-X11-X12-X13-X14-X15+X16+X18+X19+X21+X17 -> -18273769 | Z22: =SUM(Z20:Z21) -> 14701860 | AA22: 合计
A23: 加：营业外收入 | B23: =C23-G23 -> -119902.09 | C23: =合并试算平衡表!K143 -> 70120.03 | F23: 0 | G23: 190022.12 | I23: 250001.17 | J23: 2016411 | K23: =B23-I23 -> -369903.26 | L23: =C23-J23 -> -1946291 | Q23: =精铸PL!B23 -> 0 | R23: =精铸PL!C23 -> 3.03 | S23: =热等静压PL!B23 -> 0 | T23: =热等静压PL!C23 -> 1.73 | W23: =B23-Q23-S23+U23 -> -119902.09 | X23: =C23-R23-T23+V23 -> 70115.27 | Z23: =Z22-W6 -> -2157549.2 | AA23: check
A24: 减：营业外支出 | B24: =C24-G24 -> 15755.35 | C24: =合并试算平衡表!K145 -> 24203.21 | F24: 0 | G24: 8447.86 | I24: 15.66 | J24: 341.48 | K24: =B24-I24 -> 15739.69 | L24: =C24-J24 -> 23861.73 | Q24: =精铸PL!B24 -> 592.32 | R24: =精铸PL!C24 -> 3130.45 | S24: =热等静压PL!B24 -> 0 | T24: =热等静压PL!C24 -> 0 | W24: =B24-Q24-S24+U24 -> 15163.03 | X24: =C24-R24-T24+V24 -> 21072.76
A25: 其中：非流动资产处置损失 | B25: =C25-G25 -> 0 | C25: 0 | F25: 0 | G25: 0 | K25: =B25-I25 -> 0 | L25: =C25-J25 -> 0 | W25: 0 | X25: 0
A26: 三、利润总额（亏损总额以"－"号填列） | B26: =C26-G26 -> 14265232 | C26: =C22+C23-C24 -> -17263878 | F26: -2322488.7 | G26: -31529110 | I26: -1638053.8 | J26: -13769101 | K26: =B26-I26 -> 15903286 | L26: =C26-J26 -> -3494776.6 | Q26: =Q22+Q23-Q24 -> 2991.59 | R26: =R22+R23-R24 -> 8471.49 | S26: =S22+S23-S24 -> 174386.35 | T26: =T22+T23-T24 -> 952377.17 | W26: =W22+W23-W24 -> 14087854 | X26: =X22+X23-X24 -> -18224726
A27: 减：所得税费用 | B27: =C27-G27 -> 6470.17 | C27: =合并试算平衡表!K148 -> 45634.12 | F27: 0 | G27: 39163.95 | I27: 0 | J27: 11520.73 | K27: =B27-I27 -> 6470.17 | L27: =C27-J27 -> 34113.39 | Q27: =精铸PL!B27 -> 0 | R27: =精铸PL!C27 -> 0 | S27: =热等静压PL!B27 -> 8505.93 | T27: =热等静压PL!C27 -> 47669.88 | W27: =B27-Q27-S27+U27 -> -2035.76 | X27: =C27-R27-T27+V27 -> -2035.76 | AA27: 3D实际开票 | AB27: 14327638
A28: 四、净利润（净亏损以"－"号填列） | B28: =C28-G28 -> 14258762 | C28: =C26-C27 -> -17309512 | F28: -2322488.7 | G28: -31568274 | I28: -1638053.8 | J28: -13780622 | K28: =B28-I28 -> 15896816 | L28: =C28-J28 -> -3528890 | Q28: =Q26-Q27 -> 2991.59 | R28: =R26-R27 -> 8471.49 | S28: =S26-S27 -> 165880.42 | T28: =T26-T27 -> 904707.29 | W28: =W26-W27 -> 14089890 | X28: =X26-X27 -> -18222691 | AA28: 其中账面进收入 | AB28: 13946191
A29: 少数股东损益 | B29: =C29-G29 -> 42034.239 | C29: =合并试算平衡表!K151 -> 43251.883 | F29: 15808.25 | G29: 1217.6438 | I29: 123837 | J29: -122541.82 | K29: =B29-I29 -> -81802.764 | L29: =C29-J29 -> 165793.7 | AA29: 合同负债 | AB29: 381446.66
A30: 归属于母公司所有者的净利润 | B30: =C30-G30 -> 14216728 | C30: =合并试算平衡表!K150 -> -17352764 | F30: -2338296.9 | G30: -31569491 | I30: -1761890.8 | J30: -13658080 | K30: =B30-I30 -> 15978618 | L30: =C30-J30 -> -3694683.7 | AA30: 其余月份合同资产转收入
A31: 五、每股收益： | B31: 0 | C31: 0 | F31: 0 | G31: 0 | AA31: 快速 | AB31: 28141.6
A32: （一）基本每股收益 | AA32: 新材料 | AB32: 490891.59
A33: （二）稀释每股收益
Q34: =精铸PL!B28 -> 2991.59 | R34: =精铸PL!C28 -> 8471.49 | S34: =热等静压PL!B28 -> 165880.42 | T34: =热等静压PL!C28 -> 904707.29 | W34: =W28-B28+精铸PL!B28+热等静压PL!B28 -> -5.5297278e-09 | X34: =X28-C28+精铸PL!C28+热等静压PL!C28 -> -8.6147338e-09
P35: check | Q35: =Q28-Q34 -> 0 | R35: =R28-R34 -> 0 | S35: =S28-S34 -> -9.6042641e-10 | T35: =T28-T34 -> 0

Sheet 资产负债表-合并(原）
A1: 资产负债表-合并报表
G2: 会企01表
A3: 单位名称：飞而康快速制造科技有限责任公司 | E3: ='利润表-合并'!B3 -> 45991 | G3: 单位：元
A5: 资产 | B5: 年初余额 | C5: 期末余额 | E5: 负债及所有者权益（或股东权益） | F5: 年初余额 | G5: 期末余额
A6: 流动资产： | E6: 流动负债：
A7: 货币资金 | B7: 47919713 | C7: =合并试算平衡表!K9 -> 56972677 | D7: =(C7-B7)/B7 -> 0.18891941 | E7: 短期借款 | F7: 62800000 | G7: =合并试算平衡表!K64 -> 1.1655207e+08 | H7: =(F7-G7)/F7 -> -0.85592467
A8: 其中：银行存款 | B8: 40494291 | C8: =精铸BS!C7+新材料BS!D7+快速BS!D7+热等静压BS!C7 -> 21767935 | D8: =(C8-B8)/B8 -> -0.46244434 | E8: 交易性金融负债 | H8: =(F8-G8)/F8 -> #DIV/0!
A9: 其他货币资金 | B9: 7415709.8 | C9: =精铸BS!C8+新材料BS!D8+快速BS!D8+热等静压BS!C8 -> 504397.14 | D9: =(C9-B9)/B9 -> -0.93198262 | E9: 应付票据 | F9: 13567983 | G9: =合并试算平衡表!K70 -> 1128557.5 | H9: =(F9-G9)/F9 -> 0.91682202
A10: 交易性金融资产 | B10: 6000000 | C10: =合并试算平衡表!K12 -> 0 | D10: =(C10-B10)/B10 -> -1 | E10: 应付账款 | F10: 97313283 | G10: =合并试算平衡表!K71 -> 1.4933087e+08 | H10: =(F10-G10)/F10 -> -0.53453742
A11: 应收票据 | B11: 7578956.6 | C11: =合并试算平衡表!K14 -> 6766158.5 | D11: =(C11-B11)/B11 -> -0.10724406 | E11: 预收款项 | F11: 412768.62 | G11: =合并试算平衡表!K72 -> 3510493.9 | H11: =(F11-G11)/F11 -> -7.5047499
A12: 应收账款 | B12: 75509438 | C12: =合并试算平衡表!K15 -> 1.1533203e+08 | D12: =(C12-B12)/B12 -> 0.52738556 | E12: 合同负债 | F12: 0 | G12: =合并试算平衡表!K73 -> 5289418 | H12: =(F13-G13)/F13 -> 0.47642887
A13: 预付款项 | B13: 1306843.1 | C13: =合并试算平衡表!K17 -> 7259283.4 | D13: =(C13-B13)/B13 -> 4.554824 | E13: 应付职工薪酬 | F13: 6096722.6 | G13: =合并试算平衡表!K76 -> 3192067.9 | H13: =(F14-G14)/F14 -> 5.7735915
A14: 应收利息 | B14: 0 | C14: =合并试算平衡表!K21 -> 0 | D14: =(C14-B14)/B14 -> #DIV/0! | E14: 应交税费 | F14: -154621.2 | G14: =合并试算平衡表!K77 -> 738098.44 | H14: =(F15-G15)/F15 -> -1.9100214
A15: 应收股利 | B15: 0 | C15: =合并试算平衡表!K22 -> 0 | D15: =(C15-B15)/B15 -> #DIV/0! | E15: 应付利息 | F15: 156763.89 | G15: =合并试算平衡表!K78 -> 456186.27 | H15: =(F16-G16)/F16 -> #DIV/0!
A16: 其他应收款 | B16: 2584018.1 | C16: =合并试算平衡表!K23 -> 721163.11 | D16: =(C16-B16)/B16 -> -0.72091407 | E16: 应付股利 | F16: 0 | G16: =合并试算平衡表!K79 -> 0 | H16: =(F17-G17)/F17 -> -1.8438671
A17: 存货 | B17: 1.0119038e+08 | C17: =合并试算平衡表!K25 -> 1.1331129e+08 | D17: =(C17-B17)/B17 -> 0.11978326 | E17: 其他应付款 | F17: 1224220.3 | G17: =合并试算平衡表!K80 -> 3481519.8 | H17: =(F18-G18)/F18 -> 0.65286407
A18: 其中：库存材料 | B18: 36662265 | C18: =精铸BS!C17+新材料BS!D17+快速BS!D17+热等静压BS!C17 -> 34576849 | D18: =(C18-B18)/B18 -> -0.056881824 | E18: 一年内到期的非流动负债 | F18: 36447159 | G18: =合并试算平衡表!K86+合并试算平衡表!K87 -> 12652118 | H18: =(F32-G32)/F32 -> -15.878876 | L18: 合并报表 | N18: 精铸 | O18: 新材料 | P18: 快速准 | Q18: 快速
A19: 在产品及自制半成品 | B19: 21132635 | C19: =精铸BS!C18+新材料BS!D18+快速BS!D18+热等静压BS!C18 -> 21228692 | D19: =(C19-B19)/B19 -> 0.0045454678 | H19: =(F20-G20)/F20 -> #DIV/0! | K19: =(C19-B19)/0.75 -> 128076.95 | L19: =K19/10000 -> 12.807695 | M19: 在产品产值 | N19: =(精铸BS!C18-精铸BS!B18)/0.75/10000 -> 549.15123 | O19: =(新材料BS!D18-新材料BS!C18)/0.75/10000 -> 348.42395 | P19: =Q19+R19 -> -884.76749 | Q19: =(快速BS!D18-快速BS!C18)/0.75/10000 -> -1045.6513 | R19: =L19-N19-O19-Q19 -> 160.8838
A20: 产成品（库存商品） | B20: 41755341 | C20: =精铸BS!C19+新材料BS!D19+快速BS!D19+热等静压BS!C19 -> 44092937 | D20: =(C20-B20)/B20 -> 0.055983157 | F20: 0 | G20: 0 | H20: =(F21-G21)/F21 -> #DIV/0! | K20: =(C20-B20)/0.75+'利润表-合并'!C5 -> 1.371411e+08 | L20: =K20/10000 -> 13714.11 | M20: 产成品产值 | N20: =((精铸BS!C19-精铸BS!B19)/0.75+精铸PL!C5)/10000 -> 192.74859 | O20: =((新材料BS!D19-新材料BS!C19)/0.75+新材料PL!E6)/10000 -> 16099.64 | P20: =Q20+R20 -> -2578.2785 | Q20: =((快速BS!D19-快速BS!C19)/0.75+快速PL!D6)/10000 -> 9242.9093 | R20: =L20-N20-O20-Q20 -> -11821.188
A21: 周转材料 | B21: 1640134.3 | C21: =精铸BS!C20+新材料BS!D20+快速BS!D20+热等静压BS!C20 -> 1114684.8 | D21: =(C21-B21)/B21 -> -0.3203698 | F21: 0 | G21: 0 | H21: =(F22-G22)/F22 -> #DIV/0! | K21: =K19+K20 -> 1.3726917e+08 | L21: =L19+L20 -> 13726.917 | M21: 总产值 | N21: =N19+N20 -> 741.89983 | O21: =O19+O20 -> 16448.064 | P21: =Q21+R21 -> -3463.046 | Q21: =Q19+Q20 -> 8197.258 | R21: =L21-N21-O21-Q21 -> -11660.304
A22: 待摊费用 | D22: =(C22-B22)/B22 -> #DIV/0! | F22: 0 | G22: 0 | H22: =(F23-G23)/F23 -> #DIV/0!
A23: 合同资产 | F23: 0 | G23: 0
A24: 一年内到期的非流动资产 | B24: 0 | C24: =合并试算平衡表!K28 -> 0 | D24: =(C24-B24)/B24 -> #DIV/0! | H24: =(F25-G25)/F25 -> -0.36016516
A25: 其他流动资产 | B25: 477319.67 | C25: =合并试算平衡表!K29 -> 3625070.3 | D25: =(C25-B25)/B25 -> 6.5946383 | E25: 流动负债合计 | F25: 2.1786428e+08 | G25: =SUM(G7:G23) -> 2.963314e+08 | H25: =(F26-G26)/F26 -> #DIV/0! | I25: =G25/10000 -> 29633.14
A26: 流动资产合计 | B26: 2.4256666e+08 | C26: =C7+C10+C11+C12+C13+C16+C17+C22+C25 -> 3.0398767e+08 | D26: =(C26-B26)/B26 -> 0.25321288 | E26: 非流动负债： | F26: 0 | G26: 0 | H26: =(F27-G27)/F27 -> 0.0258 | K26: =K19/1.13+K20 -> 1.3725444e+08 | L26: =K26/10000 -> 13725.444 | M26: 工业销售产值 | N26: =((精铸BS!C18-精铸BS!B18+精铸BS!C19-精铸BS!B19)+精铸PL!C5)/10000 -> 728.79436 | O26: =((新材料BS!C18-新材料BS!B18+新材料BS!C19-新材料BS!B19)+新材料PL!C6)/10000 -> 730.52332 | P26: =Q26+R26 -> #VALUE! | Q26: =((快速BS!C18-快速BS!B18+快速BS!C19-快速BS!B19)+快速PL!C5)/10000 -> #VALUE! | R26: =L26-N26-O26-Q26 -> #VALUE!
A27: 非流动资产： | B27: 0 | C27: 0 | D27: =(C27-B27)/B27 -> #DIV/0! | E27: 长期借款 | F27: 50000000 | G27: =合并试算平衡表!K90 -> 48710000 | H27: =(F28-G28)/F28 -> #DIV/0!
A28: 可供出售金融资产 | B28: 0 | C28: =合并试算平衡表!K33 -> 0 | D28: =(C28-B28)/B28 -> #DIV/0! | E28: 应付债券 | F28: 0 | G28: =合并试算平衡表!K91 -> 0 | H28: =(F29-G29)/F29 -> 1
A29: 持有至到期投资 | B29: 0 | C29: =合并试算平衡表!K34 -> 0 | D29: =(C29-B29)/B29 -> #DIV/0! | E29: 长期应付款 | F29: 2497172.2 | G29: =合并试算平衡表!K94 -> 0 | H29: =(F30-G30)/F30 -> #DIV/0!
A30: 长期应收款 | B30: 28650 | C30: =合并试算平衡表!K35 -> 0 | D30: =(C30-B30)/B30 -> -1 | E30: 专项应付款 | F30: 0 | G30: 0 | H30: =(F31-G31)/F31 -> #DIV/0!
A31: 长期股权投资 | B31: 0 | C31: =合并试算平衡表!K36 -> 0 | D31: =(C31-B31)/B31 -> #DIV/0! | E31: 预计负债 | H31: =(F33-G33)/F33 -> #DIV/0!
A32: 投资性房地产 | B32: 0 | C32: =合并试算平衡表!K39 -> 0 | D32: =(C32-B32)/B32 -> #DIV/0! | E32: 递延收益 | F32: 2010252.9 | G32: =合并试算平衡表!K98 -> 33930809 | H32: =(F34-G34)/F34 -> #DIV/0!
A33: 固定资产原价 | B33: 3.2774819e+08 | C33: =合并试算平衡表!K40 -> 3.6376163e+08 | D33: =(C33-B33)/B33 -> 0.10988142 | E33: 递延所得税负债 | F33: 0 | G33: =合并试算平衡表!K99 -> 0 | H33: =(F35-G35)/F35 -> -0.51613855 | K33: =C33-B33 -> 36013437 | L33: =ROUND(K33/10000,2) -> 3601.34 | M33: 固定资产当年增加
A34: 减：累计折旧 | B34: 1.1518926e+08 | C34: =合并试算平衡表!K41 -> 1.6850946e+08 | D34: =(C34-B34)/B34 -> 0.46289213 | E34: 其他非流动负债 | F34: 0 | G34: =合并试算平衡表!K100 -> 0 | H34: =(F36-G36)/F36 -> -0.39137879 | K34: =C34-B34 -> 53320202 | L34: =ROUND(K34/10000,2) -> 5332.02 | M34: 当年累计折旧
A35: 固定资产净值 | B35: 2.1255893e+08 | C35: =C33-C34 -> 1.9525217e+08 | D35: =(C35-B35)/B35 -> -0.081421021 | E35: 非流动负债合计 | F35: 54507425 | G35: =SUM(G27:G34) -> 82640809 | H35: =(F37-G37)/F37 -> #DIV/0!
A36: 在建工程 | B36: 16725442 | C36: =合并试算平衡表!K45 -> 42663260 | D36: =(C36-B36)/B36 -> 1.5508002 | E36: 负债合计 | F36: 2.723717e+08 | G36: =G25+G35 -> 3.7897221e+08 | H36: =(F38-G38)/F38 -> -0.009973253
A37: 工程物资 | B37: 0 | C37: =合并试算平衡表!K46 -> 0 | D37: =(C37-B37)/B37 -> #DIV/0! | E37: 所有者权益（或股东权益）： | F37: 0 | G37: 0 | H37: =(F39-G39)/F39 -> -0.11786555
A38: 固定资产清理 | B38: 0 | C38: =合并试算平衡表!K47 -> 0 | D38: =(C38-B38)/B38 -> #DIV/0! | E38: 实收资本（或股本） | F38: 260216000 | G38: =合并试算平衡表!K104 -> 262811200 | H38: =(F40-G40)/F40 -> #DIV/0!
A39: 生产性生物资产 | B39: 0 | C39: =合并试算平衡表!K48 -> 0 | D39: =(C39-B39)/B39 -> #DIV/0! | E39: 资本公积 | F39: 1.0524534e+08 | G39: =合并试算平衡表!K108 -> 1.1765014e+08 | H39: =(F41-G41)/F41 -> #DIV/0!
A40: 油气资产 | B40: 0 | C40: =合并试算平衡表!K49 -> 0 | D40: =(C40-B40)/B40 -> #DIV/0! | E40: 减：库存股 | H40: =(F42-G42)/F42 -> -0.43249189
A41: 无形资产 | B41: 12866865 | C41: =合并试算平衡表!K50 -> 13011878 | D41: =(C41-B41)/B41 -> 0.011270254 | E41: 盈余公积 | F41: 0 | G41: =合并试算平衡表!K112 -> 0 | H41: =(F43-G43)/F43 -> 0.19048863
A42: 开发支出 | B42: 0 | C42: =合并试算平衡表!K51 -> 0 | D42: =(C42-B42)/B42 -> #DIV/0! | E42: 未分配利润 | F42: -1.3582484e+08 | G42: =合并试算平衡表!K114 -> -1.9456799e+08 | H42: =(F44-G44)/F44 -> -0.023112165 | I42: =G42-F42-'利润表-合并'!C30 -> -41390380
A43: 商誉 | B43: 6070777.8 | C43: =合并试算平衡表!K52 -> 4043375.5 | D43: =(C43-B43)/B43 -> -0.33396088 | E43: 归属母公司所有者权益 | F43: 2.296365e+08 | G43: =G38+G39+G42 -> 1.8589336e+08 | H43: =(F45-G45)/F45 -> 0.18876199
A44: 长期待摊费用 | B44: 4569310 | C44: =合并试算平衡表!K53 -> 3260115 | D44: =(C44-B44)/B44 -> -0.28651921 | E44: 少数股东权益 | F44: 1871390.3 | G44: =F44+'利润表-合并'!C29 -> 1914642.2 | H44: =(#REF!-#REF!)/#REF! -> #REF!
A45: 递延所得税资产 | B45: 19251 | C45: =合并试算平衡表!K54 -> 10042.63 | D45: =(C45-B45)/B45 -> -0.47833203 | E45: 所有者权益（或股东权益）合计 | F45: 2.3150789e+08 | G45: =G43+G44 -> 1.87808e+08 | H45: =(F46-G46)/F46 -> #DIV/0!
A46: 其他非流动资产 | B46: 8473703.2 | C46: =合并试算平衡表!K55 -> 0 | D46: =(C46-B46)/B46 -> -1 | F46: 0 | G46: 0 | H46: =(F47-G47)/F47 -> #DIV/0!
A47: 非流动资产合计 | B47: 2.6131293e+08 | C47: =C35+C36+C41+C43+C44+C45+C46+C31+C37+C30 -> 2.5824084e+08 | D47: =(C47-B47)/B47 -> -0.011756378 | F47: 0 | G47: 0 | H47: =(#REF!-#REF!)/#REF! -> #REF!
A48: 资产总计 | B48: 5.038796e+08 | C48: =C47+C26 -> 5.6222851e+08 | D48: =(C48-B48)/B48 -> 0.11579931 | E48: 负债和所有者权益（或股东权益）总计 | F48: 5.038796e+08 | G48: =G45+G36 -> 5.6678021e+08 | H48: =(F48-G48)/F48 -> -0.12483263
I49: =I42/0.7778 -> -53214682
F51: =B48-F48 -> 0 | G51: =G48-C48 -> 4551706.7
B53: =B48-F48 -> 0
F55: =F36/B48 -> 0.54054918 | G55: =(G36)/(C48) -> 0.67405371
K65: 营业收入 | L65: ='利润表-合并'!C5 -> 1.340243e+08
K66: 净利润 | L66: ='利润表-合并'!C28 -> -17309512
K67: 资产负债率 | L67: =M43 -> 0

Sheet BS-合并
A1: 资产负债表-合并
F2: 会企01表
A3: 制表单位:飞而康快速制造科技有限责任公司 | C3: 报表期间： | D3: =基本信息!B14 -> 45991 | E3: 单位: | F3: 人民币元
A7: 资产 | B7: 年初余额 | C7: 期末余额 | D7: 负债及所有者权益 | E7: 年初余额 | F7: 期末余额
A8: 流动资产： | D8: 流动负债：
A9: 货币资金 | B9: 49753272 | C9: =合并试算平衡表!K9 -> 56972677 | D9: 短期借款 | E9: 1.0278669e+08 | F9: =合并试算平衡表!K64 -> 1.1655207e+08
A10: 其中：银行存款 | B10: 49750882 | C10: =精铸BS新!C10+新材料BS新!C6+快速BS新!C10+热等静压BS新!C7 -> 56240462 | D10: 交易性金融负债 | E10: 0 | F10: =合并试算平衡表!K67 -> 0
A11: 其他货币资金 | B11: 2389.71 | C11: =精铸BS新!C11+新材料BS新!C7+快速BS新!C11+热等静压BS新!C8 -> 732215.19 | D11: 应付票据 | E11: 0 | F11: =合并试算平衡表!K70 -> 1128557.5
A12: 交易性金融资产 | B12: 0 | C12: =合并试算平衡表!K12 -> 0 | D12: 应付账款 | E12: 1.1834943e+08 | F12: =合并试算平衡表!K71 -> 1.4933087e+08
A13: 应收票据 | B13: 29226386 | C13: =合并试算平衡表!K14 -> 6766158.5 | D13: 预收账款 | E13: 0 | F13: =合并试算平衡表!K72 -> 3510493.9
A14: 应收账款 | B14: 86579419 | C14: =合并试算平衡表!K15 -> 1.1533203e+08 | D14: 合同负债 | E14: 9067703.6 | F14: =合并试算平衡表!K73 -> 5289418
A15: 应收款项融资 | B15: 1603892.3 | C15: =合并试算平衡表!K16 -> 0 | D15: 应付职工薪酬 | E15: 7566027.5 | F15: =合并试算平衡表!K76 -> 3192067.9
A16: 预付款项 | B16: 4883049.8 | C16: =合并试算平衡表!K17 -> 7259283.4 | D16: 应交税费 | E16: 3095811.7 | F16: =合并试算平衡表!K77 -> 738098.44
A17: 应收利息 | B17: 0 | C17: =合并试算平衡表!K21 -> 0 | D17: 应付利息 | E17: 0 | F17: =合并试算平衡表!K78 -> 456186.27
A18: 应收股利 | B18: 0 | C18: =合并试算平衡表!K22 -> 0 | D18: 应付股利 | E18: 0 | F18: =合并试算平衡表!K79 -> 0
A19: 其他应收款 | B19: 938609.95 | C19: =合并试算平衡表!K23 -> 721163.11 | D19: 其他应付款 | E19: 1627343.6 | F19: =合并试算平衡表!K80 -> 3481519.8
A20: 存货 | B20: 89565843 | C20: =合并试算平衡表!K25 -> 1.1331129e+08 | D20: 一年内到期的非流动负债 | E20: 35008704 | F20: =合并试算平衡表!K86 -> 8372322.7
A21: 其中:库存材料 | B21: 34587133 | C21: =快速BS新!C21+新材料BS新!C17+热等静压BS新!C18+精铸BS新!C21-合并调整抵消分录!F196-合并调整抵消分录!F177 -> 34837507 | D21: 其他流动负债 | E21: 22779924 | F21: =合并试算平衡表!K87 -> 4279795.6
A22: 在产品及自制半成品 | B22: 20928300 | C22: =快速BS新!C22+新材料BS新!C18+热等静压BS新!C19+精铸BS新!C22 -> 31121988 | H22: =(C22-B22)/0.75/10000 -> 1359.1583 | I22: 在产品产值
A23: 产成品(库存商品) | B23: 33022501 | C23: =快速BS新!C23+新材料BS新!C19+热等静压BS新!C20+精铸BS新!C23 -> 46329411 | H23: =((C23-B23)/0.75+'PL-合并'!D9)/10000 -> 15176.685 | I23: 产成品产值
A24: 周转材料 | B24: 1027908.9 | C24: =快速BS新!C24+新材料BS新!C20+热等静压BS新!C21+精铸BS新!C24 -> 1022383.5 | H24: =H22+H23 -> 16535.843 | I24: 总产值
A25: 待摊费用 | B25: 0 | C25: 0 | D25: 流动负债合计 | E25: =SUM(E9:E24) -> 3.0028163e+08 | F25: =SUM(F9:F24) -> 2.963314e+08 | H25: =H22/1.13+H23 -> 16379.48 | I25: 工业销售产值
A26: 合同资产 | B26: 5174733.3 | C26: =合并试算平衡表!K26 -> 1426653 | D26: 非流动负债： | E26: ——
A27: 一年内到期的非流动资产 | B27: 0 | C27: =合并试算平衡表!K28 -> 0 | D27: 长期借款 | E27: 23800000 | F27: =合并试算平衡表!K90 -> 48710000
A28: 其他流动资产 | B28: 1383995.4 | C28: =合并试算平衡表!K29 -> 3625070.3 | D28: 应付债券 | E28: 0 | F28: =合并试算平衡表!K91 -> 0
A29: 流动资产合计 | B29: =SUM(B9:B28)-B10-B11-B21-B22-B23-B24 -> 2.691092e+08 | C29: =SUM(C9:C28)-C10-C11-C21-C22-C23-C24 -> 3.0541432e+08 | D29: 长期应付款 | E29: 0 | F29: =合并试算平衡表!K94 -> 0
D30: 专项应付款 | E30: 0 | F30: =合并试算平衡表!K96 -> 0
D31: 预计负债 | E31: 0 | F31: =合并试算平衡表!K97 -> 0
D32: 递延收益 | E32: 6958008.6 | F32: =合并试算平衡表!K98 -> 33930809
A33: 非流动资产： | D33: 递延所得税负债 | E33: 0 | F33: =合并试算平衡表!K99 -> 0
A34: 可供出售金融资产 | B34: 0 | C34: =合并试算平衡表!K33 -> 0 | D34: 其他非流动负债 | E34: 0 | F34: =合并试算平衡表!K100 -> 0
A35: 持有至到期投资 | B35: 0 | C35: =合并试算平衡表!K34 -> 0 | D35: 非流动负债合计 | E35: =SUM(E27:E34) -> 30758009 | F35: =SUM(F27:F34) -> 82640809
A36: 长期应收款 | B36: 0 | C36: =合并试算平衡表!K35 -> 0 | D36: 负债合计 | E36: =E35+E25 -> 3.3103964e+08 | F36: =F35+F25 -> 3.7897221e+08
A37: 长期股权投资 | B37: 0 | C37: =合并试算平衡表!K36 -> 0
A38: 其他非流动金融资产 | B38: 17507066 | C38: =合并试算平衡表!K38 -> 3000000
A39: 投资性房地产 | B39: 0 | C39: =合并试算平衡表!K39 -> 0 | D39: 所有者权益（或股东权益）： | E39: ——
A40: 固定资产 | B40: 3.4408716e+08 | C40: =合并试算平衡表!K40 -> 3.6376163e+08 | D40: 实收资本（或股本） | E40: 260216000 | F40: =合并试算平衡表!K104 -> 262811200 | H40: =(C40-B40)/10000 -> 1967.4474 | I40: 固定资产当年增加
A41: 减:累计折旧 | B41: 1.4300318e+08 | C41: =合并试算平衡表!K41 -> 1.6850946e+08 | D41: 资本公积 | E41: 1.0524534e+08 | F41: =合并试算平衡表!K108 -> 1.1765014e+08 | H41: =(C41-B41)/10000 -> 2550.6277 | I41: 当年累计折旧
A42: 固定资产净值 | B42: 2.0108397e+08 | C42: =C40-C41 -> 1.9525217e+08 | D42: 减：库存股 | E42: 0 | F42: =合并试算平衡表!K109 -> 0
A43: 在建工程 | B43: 11313317 | C43: =合并试算平衡表!K45 -> 42663260 | D43: 盈余公积 | E43: 0 | F43: =合并试算平衡表!K112 -> 0
A44: 固定资产清理 | B44: 0 | C44: =合并试算平衡表!K47 -> 0 | D44: 未分配利润 | E44: -1.7721522e+08 | F44: =合并试算平衡表!K114 -> -1.9456799e+08 | G44: =F44-E44-'PL-合并'!D38 -> -5.9604645e-08
A45: 生产性生物资产 | B45: 0 | C45: =合并试算平衡表!K48 -> 0 | D45: 归属母公司所有者权益 | E45: =E40+E41+E44+E43 -> 1.8824612e+08 | F45: =F40+F41+F44+F43 -> 1.8589336e+08
A46: 油气资产 | B46: 0 | C46: =合并试算平衡表!K49 -> 0 | D46: 少数股东权益 | E46: 1746336.6 | F46: =合并试算平衡表!K116 -> 1789588.5
A47: 无形资产 | B47: 13123470 | C47: =合并试算平衡表!K50 -> 13011878 | D47: 所有者权益（或股东权益）合计 | E47: =E45+E46 -> 1.8999246e+08 | F47: =F45+F46 -> 1.8768295e+08
A48: 开发支出 | B48: 0 | C48: =合并试算平衡表!K51 -> 0
A49: 商誉 | B49: 4043375.5 | C49: =合并试算平衡表!K52 -> 4043375.5 | I49: -112634.02
A50: 长期待摊费用 | B50: 4841651.7 | C50: =合并试算平衡表!K53 -> 3260115 | I50: =I49/0.2222 -> -506903.78
A51: 递延所得税资产 | B51: 10042.63 | C51: =合并试算平衡表!K54 -> 10042.63
A52: 其他非流动资产 | B52: 0 | C52: =合并试算平衡表!K55 -> 0 | I52: 506853.6
A53: 非流动资产合计 | B53: =SUM(B34:B52)-B40-B41 -> 2.5192289e+08 | C53: =SUM(C34:C52)-C40-C41 -> 2.6124084e+08 | I53: =I52*(400/1800) -> 112634.13
A54: 资产总计 | B54: =B53+B29 -> 5.210321e+08 | C54: =C53+C29 -> 5.6665516e+08 | D54: 负债和所有者权益（或股东权益）总计 | E54: =E47+E36 -> 5.210321e+08 | F54: =F47+F36 -> 5.6665516e+08 | I54: =I49+I53 -> 0.11333333
E55: =B54-E54 -> 0 | F55: =C54-F54 -> 0.0032681227
C57: =C49-B49 -> 0 | D57: 资产负债率 | E57: =E36/B54 -> 0.63535364 | F57: =F36/C54 -> 0.66878807

Sheet 利润表-合并
A1: 利 润 表-合并报表
C2: 会企02表 | D2: =(B5-B8)/B5 -> 0.68475341 | E2: =(C5-C8)/C5 -> 0.17882376 | K2: =(I5-I8)/I5 -> 0.13633661 | L2: =(J5-J8)/J5 -> 0.099941107
A3: 单位名称：飞而康快速制造科技有限责任公司 | B3: =合并试算平衡表!B6 -> 45991 | C3: 单位：元 | F3: 注意修改！！！
A4: 项 目 | B4: 本期金额 | C4: 本年累计金额 | E4: =(D5-E8)/D5 -> #DIV/0! | F4: 2410月金额 | G4: 2410月累计金额 | I4: 2306数据 | J4: 2306合计 | K4: 差异1 | L4: 差异2
A5: 一、营业收入 | B5: =C5-G5 -> 17635913 | C5: =C6+C7 -> 1.340243e+08 | F5: 17470608 | G5: 1.1638839e+08 | I5: 14520603 | J5: 46494371 | K5: =B5-I5 -> 3115309.8 | L5: =C5-J5 -> 87529932 | M5: =K5/I5 -> 0.21454411 | N5: =L5/J5 -> 1.882592
A6: 其中：主营业务收入 | B6: =C6-G6 -> 18206795 | C6: =合并试算平衡表!K125 -> 1.3352726e+08 | F6: 17406946 | G6: 1.1532047e+08 | I6: 14326059 | J6: 45162004 | K6: =B6-I6 -> 3880735.7 | L6: =C6-J6 -> 88365258 | M6: =K6/I6 -> 0.27088647 | N6: =L6/J6 -> 1.9566284
A7: 其他业务收入 | B7: =C7-G7 -> -570882.32 | C7: =合并试算平衡表!K126 -> 497041.45 | F7: 63662.36 | G7: 1067923.8 | I7: 194543.53 | J7: 1332367.7 | K7: =B7-I7 -> -765425.85 | L7: =C7-J7 -> -835326.27 | M7: =K7/I7 -> -3.9344709 | N7: =L7/J7 -> -0.62694875
A8: 减：营业成本 | B8: =C8-G8 -> 5559661.3 | C8: =C9+C10 -> 1.1005757e+08 | F8: 15004809 | G8: 1.0449791e+08 | I8: 12540913 | J8: 41847672 | K8: =B8-I8 -> -6981251.6 | L8: =C8-J8 -> 68209901 | M8: =K8/I8 -> -0.5566781 | N8: =L8/J8 -> 1.6299569
A9: 其中：主营业务成本 | B9: =C9-G9 -> 6384482.1 | C9: =合并试算平衡表!K128 -> 1.1005757e+08 | F9: 14981283 | G9: 1.0367309e+08 | I9: 12420465 | J9: 41161831 | K9: =B9-I9 -> -6035982.6 | L9: =C9-J9 -> 68895742 | M9: =K9/I9 -> -0.48597075 | N9: =L9/J9 -> 1.6737774
A10: 其他业务成本 | B10: =C10-G10 -> -824820.83 | C10: =合并试算平衡表!K129 -> 0 | F10: 23525.8 | G10: 824820.83 | I10: 120448.22 | J10: 685841.17 | K10: =B10-I10 -> -945269.05 | L10: =C10-J10 -> -685841.17 | M10: =K10/I10 -> -7.8479288 | N10: =L10/J10 -> -1
A11: 营业税金及附加 | B11: =C11-G11 -> -997712.24 | C11: =合并试算平衡表!K130 -> 829444.38 | D11: =C11/$C$5 -> 0.006188761 | E11: =D5*0.007 -> 0 | F11: 71444.48 | G11: 1827156.6 | I11: 90103.84 | J11: 475596.62 | K11: =B11-I11 -> -1087816.1 | L11: =C11-J11 -> 353847.76 | M11: =K11/I11 -> -12.072916 | N11: =L11/J11 -> 0.74400815 | O11: 快速资产转移新材料4月份开票确认收入6227.38形成增值税 809.56 及附加税97.15万元
A12: 销售费用 | B12: =C12-G12 -> -521103.68 | C12: =合并试算平衡表!K131 -> 8045698 | D12: =C12/$C$5 -> 0.060031634 | E12: =D12*$D$5 -> 0 | F12: 964070.03 | G12: 8566801.7 | I12: 938241.48 | J12: 4692976 | K12: =B12-I12 -> -1459345.2 | L12: =C12-J12 -> 3352722 | M12: =K12/I12 -> -1.5554046 | N12: =L12/J12 -> 0.71441277 | O12: 营业收入增长，销售费用略有增长相对合理
A13: 管理费用 | B13: =C13-G13 -> -766556.38 | C13: =合并试算平衡表!K132 -> 8350965.1 | D13: =C13/$C$5 -> 0.062309334 | E13: =D13*$D$5 -> 0 | F13: 891664.76 | G13: 9117521.4 | I13: 941704.85 | J13: 4286617.3 | K13: =B13-I13 -> -1708261.2 | L13: =C13-J13 -> 4064347.8 | M13: =K13/I13 -> -1.8140092 | N13: =L13/J13 -> 0.94814803 | O13: 上年同期因审计调整，红冲当月费用26.20万元
A14: 研发费用 | B14: =C14-G14 -> 942695.37 | C14: =合并试算平衡表!K133 -> 19920178 | D14: =C14/$C$5 -> 0.14863109 | E14: =D14*$D$5 -> 0 | F14: 2625421.1 | G14: 18977483 | I14: 1386872.1 | J14: 8292064.8 | K14: =B14-I14 -> -444176.74 | L14: =C14-J14 -> 11628113 | M14: =K14/I14 -> -0.32027231 | N14: =L14/J14 -> 1.4023182 | O14: 上年同期将1-3月部分误入3D生产成本的研发费用调整调回研发费用-直接投入
A15: 财务费用 | B15: =C15-G15 -> -224415.61 | C15: =合并试算平衡表!K134 -> 4508765.3 | D15: =C15/$C$5 -> 0.033641401 | E15: =D15*$D$5 -> 0 | F15: 400727.74 | G15: 4733180.9 | I15: 523640.15 | J15: 2939834.1 | K15: =B15-I15 -> -748055.76 | L15: =C15-J15 -> 1568931.2 | M15: =K15/I15 -> -1.4285684 | N15: =L15/J15 -> 0.53368016 | O15: 跟产业集团借款3000万元，每月约增加15万财务费用
A16: 资产减值损失 | B16: =C16-G16 -> 0 | C16: =合并试算平衡表!K140 -> 0 | D16: 11月修改取数逻辑 | F16: 0 | G16: 0 | I16: 0 | J16: -7500 | K16: =B16-I16 -> 0 | L16: =C16-J16 -> 7500
A17: 信用减值损失 | B17: =C17-G17 -> -579092.11 | C17: =合并试算平衡表!K139 -> -1780058.3 | D17: 11月修改取数逻辑 | F17: 0 | G17: -1200966.1 | K17: =B17-I17 -> -579092.11 | L17: =C17-J17 -> -1780058.3
A18: 加：公允价值变动收益（损失以"-"填列） | B18: =C18-G18 -> 0 | C18: 0 | F18: 0 | G18: 0 | K18: =B18-I18 -> 0 | L18: =C18-J18 -> 0
A19: 投资收益（损失以"-"填列） | B19: =C19-G19 -> 713796.94 | C19: =合并试算平衡表!K136 -> 853056.55 | F19: 3.4924597e-10 | G19: 139259.61 | I19: 12833.33 | J19: 94275.86 | K19: =B19-I19 -> 700963.61 | L19: =C19-J19 -> 758780.69
A20: 其中：对联营企业和合营企业的投资收益 | B20: =C20-G20 -> 0 | C20: 0 | F20: 0 | G20: 0 | K20: =B20-I20 -> 0 | L20: =C20-J20 -> 0
A21: 其他收益 | B21: =C21-G21 -> 622840.85 | C21: =合并试算平衡表!K135 -> 1305528.3 | F21: 165040 | G21: 682687.46 | I21: 0 | J21: 153443.41 | K21: =B21-I21 -> 622840.85 | L21: =C21-J21 -> 1152084.9
A22: 二、营业利润（亏损以"－"号填列） | B22: =C22-G22 -> 14400889 | C22: =C5-C8-C11-C12-C13-C14-C15+C16+C18+C19+C21+C17 -> -17309794 | D22: 11月修改取数公式 | F22: -2322488.7 | G22: -31710684 | I22: -1888039.3 | J22: -15785171 | K22: =B22-I22 -> 16288929 | L22: =C22-J22 -> -1524623.8
A23: 加：营业外收入 | B23: =C23-G23 -> -119902.09 | C23: =合并试算平衡表!K143 -> 70120.03 | F23: 0 | G23: 190022.12 | I23: 250001.17 | J23: 2016411 | K23: =B23-I23 -> -369903.26 | L23: =C23-J23 -> -1946291
A24: 减：营业外支出 | B24: =C24-G24 -> 15755.35 | C24: =合并试算平衡表!K145 -> 24203.21 | F24: 0 | G24: 8447.86 | I24: 15.66 | J24: 341.48 | K24: =B24-I24 -> 15739.69 | L24: =C24-J24 -> 23861.73
A25: 其中：非流动资产处置损失 | B25: =C25-G25 -> 0 | C25: 0 | F25: 0 | G25: 0 | K25: =B25-I25 -> 0 | L25: =C25-J25 -> 0
A26: 三、利润总额（亏损总额以"－"号填列） | B26: =C26-G26 -> 14265232 | C26: =C22+C23-C24 -> -17263878 | F26: -2322488.7 | G26: -31529110 | I26: -1638053.8 | J26: -13769101 | K26: =B26-I26 -> 15903286 | L26: =C26-J26 -> -3494776.6
A27: 减：所得税费用 | B27: =C27-G27 -> 6470.17 | C27: =合并试算平衡表!K148 -> 45634.12 | F27: 0 | G27: 39163.95 | I27: 0 | J27: 11520.73 | K27: =B27-I27 -> 6470.17 | L27: =C27-J27 -> 34113.39
A28: 四、净利润（净亏损以"－"号填列） | B28: =C28-G28 -> 14258762 | C28: =C26-C27 -> -17309512 | F28: -2322488.7 | G28: -31568274 | I28: -1638053.8 | J28: -13780622 | K28: =B28-I28 -> 15896816 | L28: =C28-J28 -> -3528890
A29: 少数股东损益 | B29: =C29-G29 -> 42034.239 | C29: =合并试算平衡表!K151 -> 43251.883 | F29: 15808.25 | G29: 1217.6438 | I29: 123837 | J29: -122541.82 | K29: =B29-I29 -> -81802.764 | L29: =C29-J29 -> 165793.7
A30: 归属于母公司所有者的净利润 | B30: =C30-G30 -> 14216728 | C30: =合并试算平衡表!K150 -> -17352764 | F30: -2338296.9 | G30: -31569491 | I30: -1761890.8 | J30: -13658080 | K30: =B30-I30 -> 15978618 | L30: =C30-J30 -> -3694683.7
A31: 五、每股收益： | B31: 0 | C31: 0 | F31: 0 | G31: 0
A32: （一）基本每股收益
A33: （二）稀释每股收益
D40: =B14/B5 -> 0.053453167 | E40: =C14/C5 -> 0.14863109

Sheet PL-合并
A1: 利润表-合并
D2: 会企02表
A3: 制表单位:飞而康快速制造科技有限责任公司 | B3: 报表期间: | C3: =基本信息!B14 -> 45991 | D3: 单位：人民币元 | G3: =C9-C12 -> 676410.62 | H3: =D9-D12 -> 23966730
A6: 账簿:快速主账簿 | C6: =(C9-C12)/C9 -> 0.040977553 | D6: =(D9-D12)/D9 -> 0.17882376 | G6: =(G9-G12)/G9 -> 0.028482909 | H6: =(H9-H12)/H9 -> 0.19818606 | I6: =(C10-C13)/C10 -> 0.038459216 | J6: =(D10-D13)/D10 -> 0.17576702
G7: 注意修改！！！
A8: 项目 | B8: 行次 | C8: 本期金额 | D8: 本年累计金额 | G8: 2510月金额 | H8: 2510月累计金额 | M8: 合并 | N8: 3D
A9: 一、营业收入 | B9: 1 | C9: =D9-H9 -> 16506857 | D9: =D10+D11 -> 1.340243e+08 | G9: 11456714 | H9: 1.1751745e+08 | L9: 累计收入 | M9: =D9/10000 -> 13402.43 | N9: ='PL-3D板块'!R9/10000 -> 9547.7146
A10: 其中：主营业务收入 | B10: 2 | C10: =D10-H10 -> 16463625 | D10: =合并试算平衡表!K125 -> 1.3352726e+08 | G10: 11391609 | H10: 1.1706364e+08 | L10: 净利润 | M10: =D36/10000 -> -1730.9512 | N10: ='PL-3D板块'!R36/10000 -> -3260.4715
A11: 其他业务收入 | B11: 3 | C11: =D11-H11 -> 43232.51 | D11: =合并试算平衡表!K126 -> 497041.45 | G11: 65104.29 | H11: 453808.94
A12: 减：营业成本 | B12: 4 | C12: =D12-H12 -> 15830447 | D12: =D13+D14 -> 1.1005757e+08 | G12: 11130393 | H12: 94227126 | J12: =C18/C9 -> 0.26141189 | K12: =D18/D9 -> 0.14863109
A13: 其中：主营业务成本 | B13: 5 | C13: =D13-H13 -> 15830447 | D13: =合并试算平衡表!K128 -> 1.1005757e+08 | G13: 11130393 | H13: 94227126
A14: 其他业务成本 | B14: 6 | C14: =D14-H14 -> 0 | D14: =合并试算平衡表!K129 -> 0 | G14: 0 | H14: 0
A15: 税金及附加 | B15: 7 | C15: =D15-H15 -> 82112.72 | D15: =合并试算平衡表!K130 -> 829444.38 | G15: 69676.53 | H15: 747331.66
A16: 销售费用 | B16: 8 | C16: =D16-H16 -> 822770.64 | D16: =合并试算平衡表!K131 -> 8045698 | G16: 649038.84 | H16: 7222927.3
A17: 管理费用 | B17: 9 | C17: =D17-H17 -> 1193327.4 | D17: =合并试算平衡表!K132 -> 8350965.1 | G17: 828962.78 | H17: 7157637.6
A18: 研发费用 | B18: 10 | C18: =D18-H18 -> 4315088.8 | D18: =合并试算平衡表!K133 -> 19920178 | G18: 1995821 | H18: 15605089
A19: 财务费用 | B19: 11 | C19: =D19-H19 -> 468077.9 | D19: =合并试算平衡表!K134 -> 4508765.3 | G19: 414734.8 | H19: 4040687.4
A20: 其中：利息费用 | B20: 12 | C20: =D20-H20 -> 458409.52 | D20: =精铸PL新!D20+新材料PL新!D16+快速PL新!D20+热等静压PL新!D16 -> 4534024.2 | G20: 409021.01 | H20: 4075614.6
A21: 利息收入 | B21: 13 | C21: =D21-H21 -> -232.59 | D21: =精铸PL新!D21+新材料PL新!D17+快速PL新!D21+热等静压PL新!D17 -> -85075.68 | G21: 0 | H21: -84843.09
A22: 加：其他收益 | B22: 14 | C22: =D22-H22 -> 250000 | D22: =合并试算平衡表!K135 -> 1305528.3 | G22: 0 | H22: 1055528.3
A23: 投资收益（损失以“-”号填列） | B23: 15 | C23: =D23-H23 -> 0 | D23: =合并试算平衡表!K136 -> 853056.55 | G23: 0 | H23: 853056.55
A24: 其中：对联营企业和合营企业的投资收益 | B24: 16 | C24: =D24-H24 -> 0 | G24: 0
A25: 以摊余成本计量的金融资产终止确认收益（损失以“-”号填列） | B25: 17 | C25: =D25-H25 -> 0 | G25: 0
A26: 净敞口套期收益（损失以“-”号填列） | B26: 18 | C26: =D26-H26 -> 0 | G26: 0
A27: 公允价值变动收益（损失以“-”填列） | B27: 19 | C27: =D27-H27 -> 0 | D27: =合并试算平衡表!K138 -> 0 | G27: 0 | H27: 0
A28: 信用减值损失（损失以“-”填列） | B28: 20 | C28: =D28-H28 -> 0 | D28: =合并试算平衡表!K139 -> -1780058.3 | G28: 0 | H28: -1780058.3 | I28: =C28/10000 -> 0
A29: 资产减值损失（损失以“-”填列） | B29: 21 | C29: =D29-H29 -> 0 | D29: =合并试算平衡表!K140 -> 0 | G29: 0 | H29: 0
A30: 资产处置收益（损失以“-”填列） | B30: 22 | C30: =D30-H30 -> 0 | D30: =合并试算平衡表!K141 -> 0 | G30: 0 | H30: 0
A31: 二、营业利润（亏损以“－”号填列） | B31: 23 | C31: =C9-C12-C15-C16-C17-C18-C19+C22+C23+C27+C28+C29+C30 -> -5954966.8 | D31: =D9-D12-D15-D16-D17-D18-D19+D22+D23+D27+D28+D29+D30 -> -17309794 | G31: -3631913.4 | H31: -11354828
A32: 加：营业外收入 | B32: 24 | C32: =D32-H32 -> 0 | D32: =合并试算平衡表!K143 -> 70120.03 | G32: 70000 | H32: 70120.03
A33: 减：营业外支出 | B33: 25 | C33: =D33-H33 -> 0 | D33: =合并试算平衡表!K145 -> 24203.21 | G33: 0.01 | H33: 24203.21
A34: 三、利润总额（亏损以“－”号填列） | B34: 26 | C34: =C31+C32-C33 -> -5954966.8 | D34: =D31+D32-D33 -> -17263878 | G34: -3561913.4 | H34: -11308911
A35: 减：所得税费用 | B35: 27 | C35: =D35-H35 -> 20876.67 | D35: =合并试算平衡表!K148 -> 45634.12 | G35: 0 | H35: 24757.45
A36: 四、净利润（净亏损以“－”号填列） | B36: 28 | C36: =C34-C35 -> -5975843.5 | D36: =D34-D35 -> -17309512 | G36: -3561913.4 | H36: -11333668
A37: 少数股东损益 | B37: 29 | C37: =D37-H37 -> 72653.383 | D37: =合并试算平衡表!K151 -> 43251.883 | G37: 35159.516 | H37: -29401.5
A38: 归属于母公司所有者的净利润 | B38: 30 | C38: =D38-H38 -> -6048496.9 | D38: =合并试算平衡表!K150 -> -17352764 | G38: -3597072.9 | H38: -11304267
A39: 五、其他综合收益的税后净额 | B39: 31
A40: （一）不能重分类进损益的其他综合收益 | B40: 32
A41: 1、重新计量设定受益计划变动额 | B41: 33
A42: 2、权益法下不能转损益的其他综合收益 | B42: 34
A43: 3、其他权益工具投资公允价值变动 | B43: 35
A44: 4、企业自身信用风险公允价值变动 | B44: 36
A45: （二）将重分类进损益的其他综合收益 | B45: 37
A46: 1、权益法下可转损益的其他综合收益 | B46: 38
A47: 2、其他债权投资公允价值变动 | B47: 39
A48: 3、金融资产重分类计入其他综合收益的金额 | B48: 40
A49: 4、其他债权投资信用减值准备 | B49: 41
A50: 5、现金流量套期储备 | B50: 42
... A55: （二）稀释每股收益 | B55: 47
A57: 补充资料：
A58: 1、出售、处置部门或被投资单位所得收益 | B58: 1
A59: 2、自然灾害发生的损失 | B59: 2
A60: 3、会计政策变更增加（或减少）利润总额 | B60: 3
A61: 4、会计估计变更增加（或减少）利润总额 | B61: 4
A62: 5、债务重组损失 | B62: 5
A63: 6、其他 | B63: 6

Sheet 资产负债表-合并 (2)
A1: 资产负债表-合并报表
G2: 会企01表
A3: 单位名称：飞而康快速制造科技有限责任公司 | E3: ='利润表-合并'!B3 -> 45991 | G3: 单位：元
A5: 资产 | B5: 年初余额 | C5: 期末余额 | E5: 负债及所有者权益（或股东权益） | F5: 年初余额 | G5: 期末余额
A6: 流动资产： | E6: 流动负债：
A7: 货币资金 | B7: 53038385 | C7: =合并试算平衡表!K9 -> 56972677 | D7: =(C7-B7)/B7 -> 0.074178214 | E7: 短期借款 | F7: 62878115 | G7: =合并试算平衡表!K64 -> 1.1655207e+08 | H7: =(F7-G7)/F7 -> -0.853619
A8: 其中：银行存款 | B8: 40494241 | C8: =精铸BS!C7+新材料BS!D7+快速BS!D7+热等静压BS!C7 -> 21767935 | D8: =(C8-B8)/B8 -> -0.46244367 | E8: 交易性金融负债 | H8: =(F8-G8)/F8 -> #DIV/0!
A9: 其他货币资金 | B9: 12544099 | C9: =精铸BS!C8+新材料BS!D8+快速BS!D8+热等静压BS!C8 -> 504397.14 | D9: =(C9-B9)/B9 -> -0.95979009 | E9: 应付票据 | F9: 13567983 | G9: =合并试算平衡表!K70 -> 1128557.5 | H9: =(F9-G9)/F9 -> 0.91682202
A10: 交易性金融资产 | B10: 1000000 | C10: =合并试算平衡表!K12 -> 0 | D10: =(C10-B10)/B10 -> -1 | E10: 应付账款 | F10: 96923783 | G10: =合并试算平衡表!K71 -> 1.4933087e+08 | H10: =(F10-G10)/F10 -> -0.54070414
A11: 应收票据 | B11: =19238095.92+5358921.48 -> 24597017 | C11: =合并试算平衡表!K14 -> 6766158.5 | D11: =(C11-B11)/B11 -> -0.72491955 | E11: 预收款项 | G11: =合并试算平衡表!K72 -> 3510493.9 | H11: =(F11-G11)/F11 -> #DIV/0!
A12: 应收账款 | B12: 73111333 | C12: =合并试算平衡表!K15 -> 1.1533203e+08 | D12: =(C12-B12)/B12 -> 0.57748491 | E12: 合同负债 | F12: 1253516.7 | G12: =合并试算平衡表!K73 -> 5289418 | H12: =(F13-G13)/F13 -> 0.25977706
A13: 预付款项 | B13: 2052438.6 | C13: =合并试算平衡表!K17 -> 7259283.4 | D13: =(C13-B13)/B13 -> 2.5369065 | E13: 应付职工薪酬 | F13: 4312306.1 | G13: =合并试算平衡表!K76 -> 3192067.9 | H13: =(F14-G14)/F14 -> -0.4984176
A14: 应收利息 | C14: =合并试算平衡表!K21 -> 0 | D14: =(C14-B14)/B14 -> #DIV/0! | E14: 应交税费 | F14: 492585.27 | G14: =合并试算平衡表!K77 -> 738098.44 | H14: =(F15-G15)/F15 -> #DIV/0!
A15: 应收股利 | C15: =合并试算平衡表!K22 -> 0 | D15: =(C15-B15)/B15 -> #DIV/0! | E15: 应付利息 | G15: =合并试算平衡表!K78 -> 456186.27 | H15: =(F16-G16)/F16 -> #DIV/0! | J15: =C17-C18-C19-C20-C21 -> 12320014
A16: 其他应收款 | B16: 2579303.7 | C16: =合并试算平衡表!K23 -> 721163.11 | D16: =(C16-B16)/B16 -> -0.72040396 | E16: 应付股利 | F16: 0 | G16: =合并试算平衡表!K79 -> 0 | H16: =(F17-G17)/F17 -> -1.8724236
A17: 存货 | B17: 95998497 | C17: =合并试算平衡表!K25 -> 1.1331129e+08 | D17: =(C17-B17)/B17 -> 0.1803444 | E17: 其他应付款 | F17: 1212049.6 | G17: =合并试算平衡表!K80 -> 3481519.8 | H17: =(F18-G18)/F18 -> 0.7711703
A18: 其中：库存材料 | B18: =41437340.57-3089719.68 -> 38347621 | C18: =精铸BS!C17+新材料BS!D17+快速BS!D17+热等静压BS!C17-合并调整抵消分录!F196-合并调整抵消分录!F177 -> 34554960 | D18: =(C18-B18)/B18 -> -0.098902105 | E18: 一年内到期的非流动负债 | F18: 36587571 | G18: =合并试算平衡表!K86 -> 8372322.7 | H18: =(F32-G32)/F32 -> -5.2281142 | I18: 17500000 | J18: 2410长期借款 | L18: 合并报表 | N18: 精铸 | O18: 新材料 | P18: 快速准 | Q18: 快速
A19: 在产品及自制半成品 | B19: 16077130 | C19: =精铸BS!C18+新材料BS!D18+快速BS!D18+热等静压BS!C18 -> 21228692 | D19: =(C19-B19)/B19 -> 0.32042801 | E19: 其他流动负债 | F19: 17887902 | G19: =合并试算平衡表!K87 -> 4279795.6 | H19: =(F20-G20)/F20 -> #DIV/0! | I19: 32500000 | J19: 一年内到期长期借款 | K19: =(C19-B19)/0.75 -> 6868750.3 | L19: =K19/10000 -> 686.87503 | M19: 在产品产值 | N19: =(精铸BS!C18-精铸BS!B18)/0.75/10000 -> 549.15123 | O19: =(新材料BS!D18-新材料BS!C18)/0.75/10000 -> 348.42395 | P19: =Q19+R19 -> -210.70015 | Q19: =(快速BS!D18-快速BS!C18)/0.75/10000 -> -1045.6513 | R19: =L19-N19-O19-Q19 -> 834.95113
A20: 产成品（库存商品） | B20: =12629783.6+32755178.75-3811216.38 -> 41573746 | C20: =精铸BS!C19+新材料BS!D19+快速BS!D19+热等静压BS!C19 -> 44092937 | D20: =(C20-B20)/B20 -> 0.060595709 | G20: 0 | H20: =(F21-G21)/F21 -> #DIV/0! | I20: =G18-I19 -> -24127677 | J20: 一年内到期长期应付 | K20: =(C20-B20)/0.75+'利润表-合并'!C5 -> 1.3738322e+08 | L20: =K20/10000 -> 13738.322 | M20: 产成品产值 | N20: =((精铸BS!C19-精铸BS!B19)/0.75+精铸PL!C5)/10000 -> 192.74859 | O20: =((新材料BS!D19-新材料BS!C19)/0.75+新材料PL!E6)/10000 -> 16099.64 | P20: =Q20+R20 -> -2554.0658 | Q20: =((快速BS!D19-快速BS!C19)/0.75+快速PL!D6)/10000 -> 9242.9093 | R20: =L20-N20-O20-Q20 -> -11796.975
A21: 周转材料 | B21: 0 | C21: =精铸BS!C20+新材料BS!D20+快速BS!D20+热等静压BS!C20 -> 1114684.8 | D21: =(C21-B21)/B21 -> #DIV/0! | G21: 0 | H21: =(F22-G22)/F22 -> #DIV/0! | K21: =K19+K20 -> 1.4425197e+08 | L21: =L19+L20 -> 14425.197 | M21: 总产值 | N21: =N19+N20 -> 741.89983 | O21: =O19+O20 -> 16448.064 | P21: =Q21+R21 -> -2764.766 | Q21: =Q19+Q20 -> 8197.258 | R21: =L21-N21-O21-Q21 -> -10962.024
A22: 待摊费用 | D22: =(C22-B22)/B22 -> #DIV/0! | F22: 0 | G22: 0 | H22: =(F23-G23)/F23 -> #DIV/0!
A23: 合同资产 | B23: 2362972 | C23: =合并试算平衡表!K26 -> 1426653 | F23: 0 | G23: 0
A24: 一年内到期的非流动资产 | C24: =合并试算平衡表!K28 -> 0 | D24: =(C24-B24)/B24 -> #DIV/0! | H24: =(F25-G25)/F25 -> -0.26036356
A25: 其他流动资产 | B25: 27074.08 | C25: =合并试算平衡表!K29 -> 3625070.3 | D25: =(C25-B25)/B25 -> 132.89449 | E25: 流动负债合计 | F25: =SUM(F7:F23) -> 2.3511581e+08 | G25: =SUM(G7:G23) -> 2.963314e+08 | H25: =(F26-G26)/F26 -> #DIV/0! | I25: =G25/10000 -> 29633.14
A26: 流动资产合计 | B26: =B7+B10+B11+B12+B13+B16+B17+B22+B25+B23 -> 2.5476702e+08 | C26: =C7+C10+C11+C12+C13+C16+C17+C22+C25+C23 -> 3.0541432e+08 | D26: =(C26-B26)/B26 -> 0.19879849 | E26: 非流动负债： | F26: 0 | G26: 0 | H26: =(F27-G27)/F27 -> 0.0258 | K26: =K19/1.13+K20 -> 1.4346176e+08 | L26: =K26/10000 -> 14346.176 | M26: 工业销售产值 | N26: =((精铸BS!C18-精铸BS!B18+精铸BS!C19-精铸BS!B19)+精铸PL!C5)/10000 -> 728.79436 | O26: =((新材料BS!C18-新材料BS!B18+新材料BS!C19-新材料BS!B19)+新材料PL!C6)/10000 -> 730.52332 | P26: =Q26+R26 -> #VALUE! | Q26: =((快速BS!C18-快速BS!B18+快速BS!C19-快速BS!B19)+快速PL!C5)/10000 -> #VALUE! | R26: =L26-N26-O26-Q26 -> #VALUE!
A27: 非流动资产： | B27: 0 | C27: 0 | D27: =(C27-B27)/B27 -> #DIV/0! | E27: 长期借款 | F27: 50000000 | G27: =合并试算平衡表!K90 -> 48710000 | H27: =(F28-G28)/F28 -> #DIV/0!
A28: 可供出售金融资产 | C28: =合并试算平衡表!K33 -> 0 | D28: =(C28-B28)/B28 -> #DIV/0! | E28: 应付债券 | G28: =合并试算平衡表!K91 -> 0 | H28: =(F29-G29)/F29 -> 1
A29: 持有至到期投资 | C29: =合并试算平衡表!K34 -> 0 | D29: =(C29-B29)/B29 -> #DIV/0! | E29: 长期应付款 | F29: 2447726.5 | G29: =合并试算平衡表!K94 -> 0 | H29: =(F30-G30)/F30 -> #DIV/0!
A30: 长期应收款 | B30: 22650 | C30: =合并试算平衡表!K35 -> 0 | D30: =(C30-B30)/B30 -> -1 | E30: 专项应付款 | G30: 0 | H30: =(F31-G31)/F31 -> #DIV/0!
A31: 长期股权投资 | C31: =合并试算平衡表!K36 -> 0 | D31: =(C31-B31)/B31 -> #DIV/0! | E31: 预计负债 | H31: =(F33-G33)/F33 -> #DIV/0!
A32: 投资性房地产 | C32: =合并试算平衡表!K39 -> 0 | D32: =(C32-B32)/B32 -> #DIV/0! | E32: 递延收益 | F32: 5448006.8 | G32: =合并试算平衡表!K98 -> 33930809 | H32: =(F34-G34)/F34 -> #DIV/0!
A33: 固定资产原价 | B33: 3.2728959e+08 | C33: =合并试算平衡表!K40 -> 3.6376163e+08 | D33: =(C33-B33)/B33 -> 0.11143661 | E33: 递延所得税负债 | F33: 0 | G33: =合并试算平衡表!K99 -> 0 | H33: =(F35-G35)/F35 -> -0.42740758 | K33: =C33-B33 -> 36472042 | L33: =ROUND(K33/10000,2) -> 3647.2 | M33: 固定资产当年增加
A34: 减：累计折旧 | B34: 1.1518926e+08 | C34: =合并试算平衡表!K41 -> 1.6850946e+08 | D34: =(C34-B34)/B34 -> 0.46289213 | E34: 其他非流动负债 | F34: 0 | G34: =合并试算平衡表!K100 -> 0 | H34: =(F36-G36)/F36 -> -0.29336955 | K34: =C34-B34 -> 53320202 | L34: =ROUND(K34/10000,2) -> 5332.02 | M34: 当年累计折旧
A35: 固定资产净值 | B35: 2.1210033e+08 | C35: =C33-C34 -> 1.9525217e+08 | D35: =(C35-B35)/B35 -> -0.079434861 | E35: 非流动负债合计 | F35: =SUM(F27:F34) -> 57895733 | G35: =SUM(G27:G34) -> 82640809 | H35: =(F37-G37)/F37 -> #DIV/0! | J35: 存货跌价
A36: 在建工程 | B36: 16311725 | C36: =合并试算平衡表!K45 -> 42663260 | D36: =(C36-B36)/B36 -> 1.6154965 | E36: 负债合计 | F36: =F25+F35 -> 2.9301155e+08 | G36: =G25+G35 -> 3.7897221e+08 | H36: =(F38-G38)/F38 -> -0.009973253
A37: 工程物资 | C37: =合并试算平衡表!K46 -> 0 | D37: =(C37-B37)/B37 -> #DIV/0! | E37: 所有者权益（或股东权益）： | F37: 0 | G37: 0 | H37: =(F39-G39)/F39 -> -0.11786555 | K37: 13447321
A38: 固定资产清理 | C38: =合并试算平衡表!K47 -> 0 | D38: =(C38-B38)/B38 -> #DIV/0! | E38: 实收资本（或股本） | F38: 260216000 | G38: =合并试算平衡表!K104 -> 262811200 | H38: =(F40-G40)/F40 -> #DIV/0!
A39: 生产性生物资产 | C39: =合并试算平衡表!K48 -> 0 | D39: =(C39-B39)/B39 -> #DIV/0! | E39: 资本公积 | F39: 1.0524534e+08 | G39: =合并试算平衡表!K108 -> 1.1765014e+08 | H39: =(F41-G41)/F41 -> #DIV/0!
A40: 油气资产 | C40: =合并试算平衡表!K49 -> 0 | D40: =(C40-B40)/B40 -> #DIV/0! | E40: 减：库存股 | H40: =(F42-G42)/F42 -> -0.36391111
A41: 无形资产 | B41: 12866865 | C41: =合并试算平衡表!K50 -> 13011878 | D41: =(C41-B41)/B41 -> 0.011270254 | E41: 盈余公积 | F41: 0 | G41: =合并试算平衡表!K112 -> 0 | H41: =(F43-G43)/F43 -> 0.16567503
A42: 开发支出 | C42: =合并试算平衡表!K51 -> 0 | D42: =(C42-B42)/B42 -> #DIV/0! | E42: 未分配利润 | F42: -1.4265445e+08 | G42: =合并试算平衡表!K114 -> -1.9456799e+08 | H42: =(F44-G44)/F44 -> 0.037322881 | I42: =G42-F42-'利润表-合并'!C30 -> -34560775
A43: 商誉 | B43: 4811701.9 | C43: =合并试算平衡表!K52 -> 4043375.5 | D43: =(C43-B43)/B43 -> -0.15967872 | E43: 归属母公司所有者权益 | F43: =SUM(F38:F42) -> 2.228069e+08 | G43: =G38+G39+G42 -> 1.8589336e+08 | H43: =(F45-G45)/F45 -> 0.16461299
A44: 长期待摊费用 | B44: 4561500.8 | C44: =合并试算平衡表!K53 -> 3260115 | D44: =(C44-B44)/B44 -> -0.28529773 | E44: 少数股东权益 | F44: 1858970.7 | G44: =合并试算平衡表!K116 -> 1789588.5 | H44: =(#REF!-#REF!)/#REF! -> #REF! | I44: =G44-F44 -> -69382.14
A45: 递延所得税资产 | B45: 102931.58 | C45: =合并试算平衡表!K54 -> 10042.63 | D45: =(C45-B45)/B45 -> -0.90243393 | E45: 所有者权益（或股东权益）合计 | F45: =F43+F44 -> 2.2466587e+08 | G45: =G43+G44 -> 1.8768295e+08 | H45: =(F46-G46)/F46 -> #DIV/0!
A46: 其他非流动资产 | B46: =11281777.56+850913.16 -> 12132691 | C46: =合并试算平衡表!K55 -> 0 | D46: =(C46-B46)/B46 -> -1 | F46: 0 | G46: 0 | H46: =(F47-G47)/F47 -> #DIV/0!
A47: 非流动资产合计 | B47: =B35+B36+B41+B43+B44+B45+B46+B31+B37+B30 -> 2.6291039e+08 | C47: =C35+C36+C41+C43+C44+C45+C46+C31+C37+C30 -> 2.5824084e+08 | D47: =(C47-B47)/B47 -> -0.017761011 | F47: 0 | G47: 0 | H47: =(#REF!-#REF!)/#REF! -> #REF!
A48: 资产总计 | B48: =B47+B26 -> 5.1767741e+08 | C48: =C47+C26 -> 5.6365516e+08 | D48: =(C48-B48)/B48 -> 0.088815435 | E48: 负债和所有者权益（或股东权益）总计 | F48: =F45+F36 -> 5.1767741e+08 | G48: =G45+G36 -> 5.6665516e+08 | H48: =(F48-G48)/F48 -> -0.09461055
C51: =C48/1000 -> 563655.16 | F51: =B48-F48 -> 0 | G51: =G48-C48 -> 3000000 | J51: =I42/0.7778 -> -44434013
F55: =F36/B48 -> 0.56601184 | G55: =(G36)/(C48) -> 0.67234763
C58: =C48+G59+G60-G61 -> 8.2365516e+08
C59: =G36+G59-G61 -> 3.3897221e+08 | G59: 10000000 | I59: 新进借款
C60: =C59/C58 -> 0.41154627 | G60: 300000000 | I60: 融资
G61: 50000000 | I61: 还项目贷
K65: 营业收入 | L65: ='利润表-合并'!C5 -> 1.340243e+08
K66: 净利润 | L66: ='利润表-合并'!C28 -> -17309512
K67: 资产负债率 | L67: =M43 -> 0

Sheet CF-合并
C1: 合并现金流量表
G2: 财会年企03表
A3: 单位:飞而康快速制造科技有限责任公司 | E3: =基本信息!B14 -> 45991 | G3: 金额单位：元
A4: 项 目 | B4: 行次 | C4: 本期金额 | D4: 本年累计 | E4: 项 目 | F4: 行次 | G4: 本期金额 | H4: 本年累计
A5: 一、经营活动产生的现金流量： | B5: 1 | C5: — | D5: — | E5: 处置固定资产、无形资产和其他长期资产所收回的现金净额 | F5: 30 | G5: 0 | H5: 0
A6: 销售商品、提供劳务收到的现金 | B6: 2 | C6: 10324670 | D6: 92773879 | E6: 处置子公司及其他营业单位收回的现金净额 | F6: 31 | G6: 0 | H6: 0
A7: 客户存款和同业存放款项净增加额 | B7: 3 | C7: 0 | D7: 0 | E7: 收到其他与投资活动有关的现金 | F7: 32 | G7: 0 | H7: 0
A8: 向中央银行借款净增加额 | B8: 4 | C8: 0 | D8: 0 | E8: 投资活动现金流入小计 | F8: 33 | G8: 0 | H8: 15360122
A9: 向其他金融机构拆入资金净增加额 | B9: 5 | C9: 0 | D9: 0 | E9: 购建固定资产、无形资产和其他长期资产所支付的现金 | F9: 34 | G9: 353274.28 | H9: 46108059
A10: 收到原保险合同保费取得的现金 | B10: 6 | C10: 0 | D10: 0 | E10: 投资支付的现金 | F10: 35 | G10: 0 | H10: 0
A11: 收到再保险业务现金净额 | B11: 7 | C11: 0 | D11: 0 | E11: 质押贷款净增加额 | F11: 36 | G11: 0 | H11: 0
A12: 保户储金及投资款净增加额 | B12: 8 | C12: 0 | D12: 0 | E12: 取得子公司及其他营业单位支付的现金净额 | F12: 37 | G12: 0 | H12: 0
A13: 处置交易性金融资产净增加额 | B13: 9 | C13: 0 | D13: 0 | E13: 支付其他与投资活动有关的现金 | F13: 38 | G13: 0 | H13: 0
A14: 收取利息、手续费及佣金的现金 | B14: 10 | C14: 0 | D14: 0 | E14: 投资活动现金流出小计 | F14: 39 | G14: 353274.28 | H14: 46108059
A15: 拆入资金净增加额 | B15: 11 | C15: 0 | D15: 0 | E15: 投资活动产生的现金流量净额 | F15: 40 | G15: -353274.28 | H15: -30747936
A16: 回购业务资金净增加额 | B16: 12 | C16: 0 | D16: 0 | E16: 三、筹资活动产生的现金流量： | F16: 41 | G16: 0 | H16: 0
A17: 收到的税费返还 | B17: 13 | C17: 0 | D17: 20027.64 | E17: 吸收投资收到的现金 | F17: 42 | G17: 0 | H17: 15000000
... A32: 收回投资收到的现金 | B32: 28 | C32: 0 | D32: 5206506.8 | E32: 六、期末现金及现金等价物余额 | F32: 57 | G32: 56240462 | H32: 56240462
A33: 取得投资收益收到的现金 | B33: 29 | C33: 0 | D33: 10153615 | H33: —
F35: 现金 | G35: 0
F36: 银行存款 | G36: ='BS-合并'!C10 -> 56240462
G37: =G35+G36-G32 -> 0

Sheet PL-3D板块
A1: 利润表-3D板块合并
D2: 会企02表
A3: 制表单位:飞而康快速制造科技有限责任公司 | B3: 报表期间: | C3: =基本信息!B14 -> 45991 | D3: 单位：人民币元
I4: =I10+Q10 -> 14483982 | J4: =I4-I5 -> -145517.08
I5: =I13+Q13 -> 14629499 | J5: =J4/I4 -> -0.010046759
A6: 账簿:快速主账簿 | I6: =(I9-I12)/I9 -> 0.82048805 | J6: =(J9-J12)/J9 -> 0.67156733 | K6: =(K9-K12)/K9 -> 0.29170846 | L6: =(L9-L12)/L9 -> 0.29636069 | M6: =(M9-M12)/M9 -> 0.23706395 | N6: =(N9-N12)/N9 -> 0.14129516 | Q6: =(Q9-Q12)/Q9 -> -0.14251784 | R6: =(R9-R12)/R9 -> 0.052130885
G7: 注意修改！！！ | Q7: =(Q10-Q13)/Q10 -> -0.14762921 | R7: =(R10-R13)/R10 -> 0.045573767
A8: 项目 | B8: 行次 | C8: 合并口径本期金额 | D8: 合并口径本年累计金额 | G8: ='PL-合并'!G8 -> 2510月金额 | H8: ='PL-合并'!H8 -> 2510月累计金额 | I8: 压块本月 | J8: 压块累计 | K8: 精铸本月 | L8: 精铸累计 | M8: 热等静压本月 | N8: 热等静压累计 | O8: 合并抵消还原本月 | P8: 合并抵消还原累计 | Q8: 快速+新材料本期金额 | R8: 快速+新材料本年累计金额 | V8: 2511
A9: 一、营业收入 | B9: 1 | C9: ='PL-合并'!C9 -> 16506857 | D9: ='PL-合并'!D9 -> 1.340243e+08 | G9: ='PL-合并'!G9 -> 11456714 | H9: ='PL-合并'!H9 -> 1.1751745e+08 | I9: =I10+I11 -> 2058368.1 | J9: =J10+J11 -> 20993026 | K9: =精铸PL新!C9 -> 1781043.7 | L9: =精铸PL新!D9 -> 7351863.7 | M9: =热等静压PL新!C5 -> 1093163.5 | N9: =热等静压PL新!D5 -> 20619623 | O9: =SUM(O10:O11) -> 993625.22 | P9: =SUM(P10:P11) -> 10417355 | Q9: =C9-K9-M9+O9-I9 -> 12567907 | R9: =D9-L9-N9+P9-J9 -> 95477146 | U9: 32808.32 | V9: 新材料-精铸背靠背收入
A10: 其中：主营业务收入 | B10: 2 | C10: ='PL-合并'!C10 -> 16463625 | D10: ='PL-合并'!D10 -> 1.3352726e+08 | G10: ='PL-合并'!G10 -> 11391609 | H10: ='PL-合并'!H10 -> 1.1706364e+08 | I10: 2058368.1 | J10: =10131427.43+1765210.62+1467695.58+1287249.56+1492267.26+1404913.27+1385893.81+2058368.14 -> 20993026 | K10: =精铸PL新!C10 -> 1781043.7 | L10: =精铸PL新!D10 -> 7349891.4 | M10: =热等静压PL新!C6 -> 1093163.5 | N10: =热等静压PL新!D6 -> 20418559 | O10: =32808.32+861756.23 -> 894564.55 | P10: =465301.04+8400223.07 -> 8865524.1 | Q10: =C10-K10-M10+O10-I10 -> 12425614 | R10: =D10-L10-N10+P10-J10 -> 93631310 | U10: 629897.81 | V10: 新材料-热压背靠背收入
A11: 其他业务收入 | B11: 3 | C11: ='PL-合并'!C11 -> 43232.51 | D11: ='PL-合并'!D11 -> 497041.45 | G11: ='PL-合并'!G11 -> 65104.29 | H11: ='PL-合并'!H11 -> 453808.94 | K11: =精铸PL新!C11 -> 0 | L11: =精铸PL新!D11 -> 1972.3 | M11: =热等静压PL新!C7 -> 0 | N11: =热等静压PL新!D7 -> 201064.85 | O11: 99060.67 | P11: =1350766.46+201064.85 -> 1551831.3 | Q11: =C11-K11-M11+O11 -> 142293.18 | R11: =D11-L11-N11+P11 -> 1845835.6 | U11: 13821276 | V11: 3D
A12: 减：营业成本 | B12: 4 | C12: ='PL-合并'!C12 -> 15830447 | D12: ='PL-合并'!D12 -> 1.1005757e+08 | G12: ='PL-合并'!G12 -> 11130393 | H12: ='PL-合并'!H12 -> 94227126 | I12: =I13+I14 -> 369501.68 | J12: =J13+J14 -> 6894795.4 | K12: =精铸PL新!C12 -> 1261498.2 | L12: =精铸PL新!D12 -> 5173060.3 | M12: =热等静压PL新!C8 -> 834013.87 | N12: =热等静压PL新!D8 -> 17706170 | O12: =O13+O14 -> 993625.22 | P12: =P13+P14 -> 10216291 | Q12: =C12-K12-M12+O12-I12 -> 14359058 | R12: =D12-L12-N12+P12-J12 -> 90499838 | U12: =SUM(U9:U11) -> 14483982 | V12: 合计
A13: 其中：主营业务成本 | B13: 5 | C13: ='PL-合并'!C13 -> 15830447 | D13: ='PL-合并'!D13 -> 1.1005757e+08 | G13: ='PL-合并'!G13 -> 11130393 | H13: ='PL-合并'!H13 -> 94227126 | I13: 369501.68 | J13: =1712108.95+1669124.73+1487436.38+284945.34+269605.24+225598.04+342447.42+253230.26+280797.4+369501.68 -> 6894795.4 | K13: =精铸PL新!C13 -> 1261498.2 | L13: =精铸PL新!D13 -> 5173060.3 | M13: =热等静压PL新!C9 -> 834013.87 | N13: =热等静压PL新!D9 -> 17491063 | O13: =O10 -> 894564.55 | P13: =P10 -> 8865524.1 | Q13: =C13-K13-M13+O13-I13 -> 14259998 | R13: =D13-L13-N13+P13-J13 -> 89364179 | U13: =U12-Q10-I10 -> -1.4202669e-08 | V13: check
A14: 其他业务成本 | B14: 6 | C14: ='PL-合并'!C14 -> 0 | D14: ='PL-合并'!D14 -> 0 | G14: ='PL-合并'!G14 -> 0 | H14: ='PL-合并'!H14 -> 0 | K14: =精铸PL新!C14 -> 0 | L14: =精铸PL新!D14 -> 0 | M14: =热等静压PL新!C10 -> 0 | N14: =热等静压PL新!D10 -> 215107.4 | O14: =O11-O16 -> 99060.67 | P14: =P11-P16 -> 1350766.5 | Q14: =C14-K14-M14+O14 -> 99060.67 | R14: =D14-L14-N14+P14 -> 1135659.1
A15: 税金及附加 | B15: 7 | C15: ='PL-合并'!C15 -> 82112.72 | D15: ='PL-合并'!D15 -> 829444.38 | G15: ='PL-合并'!G15 -> 69676.53 | H15: ='PL-合并'!H15 -> 747331.66 | K15: =精铸PL新!C15 -> 0 | L15: =精铸PL新!D15 -> 26359.78 | M15: =热等静压PL新!C11 -> 584.09 | N15: =热等静压PL新!D11 -> 7209.21 | Q15: =C15-K15-M15+O15 -> 81528.63 | R15: =D15-L15-N15+P15 -> 795875.39
A16: 销售费用 | B16: 8 | C16: ='PL-合并'!C16 -> 822770.64 | D16: ='PL-合并'!D16 -> 8045698 | G16: ='PL-合并'!G16 -> 649038.84 | H16: ='PL-合并'!H16 -> 7222927.3 | K16: =精铸PL新!C16 -> 65057.34 | L16: =精铸PL新!D16 -> 580641.56 | M16: =热等静压PL新!C12 -> 49638.71 | N16: =热等静压PL新!D12 -> 556431.11 | O16: 0 | P16: 201064.85 | Q16: =C16-K16-M16+O16 -> 708074.59 | R16: =D16-L16-N16+P16 -> 7109690.2
A17: 管理费用 | B17: 9 | C17: ='PL-合并'!C17 -> 1193327.4 | D17: ='PL-合并'!D17 -> 8350965.1 | G17: ='PL-合并'!G17 -> 828962.78 | H17: ='PL-合并'!H17 -> 7157637.6 | K17: =精铸PL新!C17 -> 1663.13 | L17: =精铸PL新!D17 -> 100618.84 | M17: =热等静压PL新!C13 -> 17274.27 | N17: =热等静压PL新!D13 -> 237860.86 | Q17: =C17-K17-M17+O17 -> 1174390 | R17: =D17-L17-N17+P17 -> 8012485.4
A18: 研发费用 | B18: 10 | C18: ='PL-合并'!C18 -> 4315088.8 | D18: ='PL-合并'!D18 -> 19920178 | G18: ='PL-合并'!G18 -> 1995821 | H18: ='PL-合并'!H18 -> 15605089 | K18: =精铸PL新!C18 -> 98901.62 | L18: =精铸PL新!D18 -> 1123957.1 | M18: =热等静压PL新!C14 -> 93227.55 | N18: =热等静压PL新!D14 -> 894023.38 | Q18: =C18-K18-M18+O18 -> 4122959.6 | R18: =D18-L18-N18+P18 -> 17902198
A19: 财务费用 | B19: 11 | C19: ='PL-合并'!C19 -> 468077.9 | D19: ='PL-合并'!D19 -> 4508765.3 | G19: ='PL-合并'!G19 -> 414734.8 | H19: ='PL-合并'!H19 -> 4040687.4 | K19: =精铸PL新!C19 -> 26950.51 | L19: =精铸PL新!D19 -> 185821.21 | M19: =热等静压PL新!C15 -> 270.22 | N19: =热等静压PL新!D15 -> 1051.76 | O19: 0 | P19: 0 | Q19: =C19-K19-M19+O19 -> 440857.17 | R19: =D19-L19-N19+P19 -> 4321892.3
A20: 其中：利息费用 | B20: 12 | C20: ='PL-合并'!C20 -> 458409.52 | D20: ='PL-合并'!D20 -> 4534024.2 | G20: ='PL-合并'!G20 -> 409021.01 | H20: ='PL-合并'!H20 -> 4075614.6 | K20: =精铸PL新!C20 -> 17172.28 | L20: =精铸PL新!D20 -> 193063.36 | M20: =热等静压PL新!C16 -> 0 | N20: =热等静压PL新!D16 -> 0 | Q20: =C20-K20-M20+O20 -> 441237.24 | R20: =D20-L20-N20+P20 -> 4340960.8
A21: 利息收入 | B21: 13 | C21: ='PL-合并'!C21 -> -232.59 | D21: ='PL-合并'!D21 -> -85075.68 | G21: ='PL-合并'!G21 -> 0 | H21: ='PL-合并'!H21 -> -84843.09 | K21: =精铸PL新!C21 -> -72.12 | L21: =精铸PL新!D21 -> -1409.16 | M21: =热等静压PL新!C17 -> 0 | N21: =热等静压PL新!D17 -> -1211.72 | Q21: =C21-K21-M21+O21 -> -160.47 | R21: =D21-L21-N21+P21 -> -82454.8
A22: 加：其他收益 | B22: 14 | C22: ='PL-合并'!C22 -> 250000 | D22: ='PL-合并'!D22 -> 1305528.3 | G22: ='PL-合并'!G22 -> 0 | H22: ='PL-合并'!H22 -> 1055528.3 | K22: =精铸PL新!C22 -> 0 | L22: =精铸PL新!D22 -> 34962.89 | M22: =热等静压PL新!C18 -> 0 | N22: =热等静压PL新!D18 -> 1843.34 | Q22: =C22-K22-M22+O22 -> 250000 | R22: =D22-L22-N22+P22 -> 1268722.1
A23: 投资收益（损失以“-”号填列） | B23: 15 | C23: ='PL-合并'!C23 -> 0 | D23: ='PL-合并'!D23 -> 853056.55 | G23: ='PL-合并'!G23 -> 0 | H23: ='PL-合并'!H23 -> 853056.55 | K23: =精铸PL新!C23 -> 0 | L23: =精铸PL新!D23 -> 0 | M23: =热等静压PL新!C19 -> 0 | N23: =热等静压PL新!D19 -> 0 | Q23: =C23-K23-M23+O23 -> 0 | R23: =D23-L23-N23+P23 -> 853056.55
A24: 其中：对联营企业和合营企业的投资收益 | B24: 16 | C24: ='PL-合并'!C24 -> 0 | D24: ='PL-合并'!D24 -> 0 | G24: ='PL-合并'!G24 -> 0 | H24: ='PL-合并'!H24 -> 0 | K24: =精铸PL新!C24 -> 0 | L24: =精铸PL新!D24 -> 0 | M24: =热等静压PL新!C20 -> 0 | N24: =热等静压PL新!D20 -> 0 | Q24: =C24-K24-M24+O24 -> 0 | R24: =D24-L24-N24+P24 -> 0
A25: 以摊余成本计量的金融资产终止确认收益（损失以“-”号填列） | B25: 17 | C25: ='PL-合并'!C25 -> 0 | D25: ='PL-合并'!D25 -> 0 | G25: ='PL-合并'!G25 -> 0 | H25: ='PL-合并'!H25 -> 0 | K25: =精铸PL新!C25 -> 0 | L25: =精铸PL新!D25 -> 0 | M25: =热等静压PL新!C21 -> 0 | N25: =热等静压PL新!D21 -> 0 | Q25: =C25-K25-M25+O25 -> 0 | R25: =D25-L25-N25+P25 -> 0
A26: 净敞口套期收益（损失以“-”号填列） | B26: 18 | C26: ='PL-合并'!C26 -> 0 | D26: ='PL-合并'!D26 -> 0 | G26: ='PL-合并'!G26 -> 0 | H26: ='PL-合并'!H26 -> 0 | K26: =精铸PL新!C26 -> 0 | L26: =精铸PL新!D26 -> 0 | M26: =热等静压PL新!C22 -> 0 | N26: =热等静压PL新!D22 -> 0 | Q26: =C26-K26-M26+O26 -> 0 | R26: =D26-L26-N26+P26 -> 0
A27: 公允价值变动收益（损失以“-”填列） | B27: 19 | C27: ='PL-合并'!C27 -> 0 | D27: ='PL-合并'!D27 -> 0 | G27: ='PL-合并'!G27 -> 0 | H27: ='PL-合并'!H27 -> 0 | K27: =精铸PL新!C27 -> 0 | L27: =精铸PL新!D27 -> 0 | M27: =热等静压PL新!C23 -> 0 | N27: =热等静压PL新!D23 -> 0 | Q27: =C27-K27-M27+O27 -> 0 | R27: =D27-L27-N27+P27 -> 0
A28: 信用减值损失（损失以“-”填列） | B28: 20 | C28: ='PL-合并'!C28 -> 0 | D28: ='PL-合并'!D28 -> -1780058.3 | G28: ='PL-合并'!G28 -> 0 | H28: ='PL-合并'!H28 -> -1780058.3 | K28: =精铸PL新!C28 -> 0 | L28: =精铸PL新!D28 -> 0 | M28: =热等静压PL新!C24 -> 0 | N28: =热等静压PL新!D24 -> -170766.3 | Q28: =C28-K28-M28+O28 -> 0 | R28: =D28-L28-N28+P28 -> -1609292
A29: 资产减值损失（损失以“-”填列） | B29: 21 | C29: ='PL-合并'!C29 -> 0 | D29: ='PL-合并'!D29 -> 0 | G29: ='PL-合并'!G29 -> 0 | H29: ='PL-合并'!H29 -> 0 | K29: =精铸PL新!C29 -> 0 | L29: =精铸PL新!D29 -> 0 | M29: =热等静压PL新!C25 -> 0 | N29: =热等静压PL新!D25 -> 0 | Q29: =C29-K29-M29+O29 -> 0 | R29: =D29-L29-N29+P29 -> 0
A30: 资产处置收益（损失以“-”填列） | B30: 22 | C30: ='PL-合并'!C30 -> 0 | D30: ='PL-合并'!D30 -> 0 | G30: ='PL-合并'!G30 -> 0 | H30: ='PL-合并'!H30 -> 0 | K30: =精铸PL新!C30 -> 0 | L30: =精铸PL新!D30 -> 0 | M30: =热等静压PL新!C26 -> 0 | N30: =热等静压PL新!D26 -> 0 | Q30: =C30-K30-M30+O30 -> 0 | R30: =D30-L30-N30+P30 -> 0
A31: 二、营业利润（亏损以“－”号填列） | B31: 23 | C31: ='PL-合并'!C31 -> -5954966.8 | D31: ='PL-合并'!D31 -> -17309794 | G31: ='PL-合并'!G31 -> -3631913.4 | H31: ='PL-合并'!H31 -> -11354828 | I31: =I9-I12 -> 1688866.5 | J31: =J9-J12 -> 14098230 | K31: =K9-K12-K15-K16-K17-K18-K19+K22+K23+K27+K28+K29+K30 -> 326972.92 | L31: =L9-L12-L15-L16-L17-L18-L19+L22+L23+L27+L28+L29+L30 -> 196367.74 | M31: =M9-M12-M15-M16-M17-M18-M19+M22+M23+M27+M28+M29+M30 -> 98154.83 | N31: =N9-N12-N15-N16-N17-N18-N19+N22+N23+N27+N28+N29+N30 -> 1047953.8 | Q31: =C31-K31-M31+O31-I31 -> -8068961.1 | R31: =D31-L31-N31+P31-J31 -> -32652346
A32: 加：营业外收入 | B32: 24 | C32: ='PL-合并'!C32 -> 0 | D32: ='PL-合并'!D32 -> 70120.03 | G32: ='PL-合并'!G32 -> 70000 | H32: ='PL-合并'!H32 -> 70120.03 | K32: =精铸PL新!C32 -> 0 | L32: =精铸PL新!D32 -> 0 | M32: =热等静压PL新!C28 -> 0 | N32: =热等静压PL新!D28 -> 0 | Q32: =C32-K32-M32+O32 -> 0 | R32: =D32-L32-N32+P32 -> 70120.03
A33: 减：营业外支出 | B33: 25 | C33: ='PL-合并'!C33 -> 0 | D33: ='PL-合并'!D33 -> 24203.21 | G33: ='PL-合并'!G33 -> 0.01 | H33: ='PL-合并'!H33 -> 24203.21 | K33: =精铸PL新!C33 -> 0 | L33: =精铸PL新!D33 -> 1714.8 | M33: =热等静压PL新!C29 -> 0 | N33: =热等静压PL新!D29 -> 0 | Q33: =C33-K33-M33+O33 -> 0 | R33: =D33-L33-N33+P33 -> 22488.41
A34: 三、利润总额（亏损以“－”号填列） | B34: 26 | C34: ='PL-合并'!C34 -> -5954966.8 | D34: ='PL-合并'!D34 -> -17263878 | G34: ='PL-合并'!G34 -> -3561913.4 | H34: ='PL-合并'!H34 -> -11308911 | I34: =I31+I32-I33 -> 1688866.5 | J34: =J31+J32-J33 -> 14098230 | K34: =K31+K32-K33 -> 326972.92 | L34: =L31+L32-L33 -> 194652.94 | M34: =M31+M32-M33 -> 98154.83 | N34: =N31+N32-N33 -> 1047953.8 | Q34: =C34-K34-M34+O34-I34 -> -8068961.1 | R34: =D34-L34-N34+P34-J34 -> -32604715
A35: 减：所得税费用 | B35: 27 | C35: ='PL-合并'!C35 -> 20876.67 | D35: ='PL-合并'!D35 -> 45634.12 | G35: ='PL-合并'!G35 -> 0 | H35: ='PL-合并'!H35 -> 24757.45 | K35: =精铸PL新!C35 -> 0 | L35: =精铸PL新!D35 -> 0 | M35: =热等静压PL新!C31 -> 20876.67 | N35: =热等静压PL新!D31 -> 45634.12 | Q35: =C35-K35-M35+O35 -> 0 | R35: =D35-L35-N35+P35 -> 0
A36: 四、净利润（净亏损以“－”号填列） | B36: 28 | C36: ='PL-合并'!C36 -> -5975843.5 | D36: ='PL-合并'!D36 -> -17309512 | G36: ='PL-合并'!G36 -> -3561913.4 | H36: ='PL-合并'!H36 -> -11333668 | I36: =I34-I35 -> 1688866.5 | J36: =J34-J35 -> 14098230 | K36: =K34-K35 -> 326972.92 | L36: =L34-L35 -> 194652.94 | M36: =M34-M35 -> 77278.16 | N36: =N34-N35 -> 1002319.6 | Q36: =C36-K36-M36+O36-I36 -> -8068961.1 | R36: =D36-L36-N36+P36-J36 -> -32604715
A37: 少数股东损益 | B37: 29 | C37: ='PL-合并'!C37 -> 72653.383 | D37: ='PL-合并'!D37 -> 43251.883 | G37: ='PL-合并'!G37 -> 35159.516 | H37: ='PL-合并'!H37 -> -29401.5 | K37: =精铸PL新!C37 -> 0 | L37: =精铸PL新!D37 -> 0 | M37: =热等静压PL新!C33 -> 0 | N37: =热等静压PL新!D33 -> 0
A38: 归属于母公司所有者的净利润 | B38: 30 | C38: ='PL-合并'!C38 -> -6048496.9 | D38: ='PL-合并'!D38 -> -17352764 | G38: ='PL-合并'!G38 -> -3597072.9 | H38: ='PL-合并'!H38 -> -11304267 | K38: =精铸PL新!C38 -> 0 | L38: =精铸PL新!D38 -> 0 | M38: =热等静压PL新!C34 -> 0 | N38: =热等静压PL新!D34 -> 0
A39: 五、其他综合收益的税后净额 | B39: 31
A40: （一）不能重分类进损益的其他综合收益 | B40: 32
A41: 1、重新计量设定受益计划变动额 | B41: 33
A42: 2、权益法下不能转损益的其他综合收益 | B42: 34
A43: 3、其他权益工具投资公允价值变动 | B43: 35
A44: 4、企业自身信用风险公允价值变动 | B44: 36
A45: （二）将重分类进损益的其他综合收益 | B45: 37
A46: 1、权益法下可转损益的其他综合收益 | B46: 38
A47: 2、其他债权投资公允价值变动 | B47: 39
A48: 3、金融资产重分类计入其他综合收益的金额 | B48: 40
A49: 4、其他债权投资信用减值准备 | B49: 41
A50: 5、现金流量套期储备 | B50: 42
... A55: （二）稀释每股收益 | B55: 47
A57: 补充资料：
A58: 1、出售、处置部门或被投资单位所得收益 | B58: 1
A59: 2、自然灾害发生的损失 | B59: 2
A60: 3、会计政策变更增加（或减少）利润总额 | B60: 3
A61: 4、会计估计变更增加（或减少）利润总额 | B61: 4
A62: 5、债务重组损失 | B62: 5
A63: 6、其他 | B63: 6
I66: =I36 -> 1688866.5 | J66: =J36 -> 14098230 | K66: =精铸PL新!C36 -> 326972.92 | L66: =精铸PL新!D36 -> 194652.94 | M66: =热等静压PL新!C32 -> 77278.16 | N66: =热等静压PL新!D32 -> 1002319.6
J67: check | K67: =K66-K36 -> 0 | L67: =L66-L36 -> -2.910383e-10 | M67: =M66-M36 -> 1.9645086e-09 | N67: =N66-N36 -> 0 | Q67: =Q36-C36+K66+M66+I66 -> 1.8626451e-09 | R67: =R36-D36+L66+N66+J66 -> 0

Sheet 资产负债表-M
A1: 资产负债表
A3: 编制单位：飞而康快速制造科技有限责任公司 | C3: =基本信息!B14 -> 45991 | D3: 金额单位：人民币元
A4: 资 产 | B4: 附注 | C4: =C3 -> 45991 | D4: 45657
A7: 流动资产：
A8: 货币资金 | C8: ='BS-合并'!C9 -> 56972677 | D8: ='BS-合并'!B9 -> 49753272
A9: 以公允价值计量且其变动计入当期损益的金融资产
A10: 交易性金融资产 | C10: ='BS-合并'!C12 -> 0 | D10: 0
A11: 衍生金融资产
A12: 应收票据 | C12: ='BS-合并'!C13 -> 6766158.5 | D12: ='BS-合并'!B13 -> 29226386
A13: 应收账款 | C13: ='BS-合并'!C14 -> 1.1533203e+08 | D13: ='BS-合并'!B14 -> 86579419
A14: 应收款项融资 | C14: ='BS-合并'!C15 -> 0 | D14: ='BS-合并'!B15 -> 1603892.3
A15: 预付款项 | C15: ='BS-合并'!C16 -> 7259283.4 | D15: ='BS-合并'!B16 -> 4883049.8
A16: 其他应收款 | C16: ='BS-合并'!C17+'BS-合并'!C18+'BS-合并'!C19 -> 721163.11 | D16: ='BS-合并'!B19 -> 938609.95
A17: 存货 | C17: ='BS-合并'!C20 -> 1.1331129e+08 | D17: ='BS-合并'!B20 -> 89565843
A18: 合同资产 | C18: ='资产负债表-合并 (2)'!C23 -> 1426653 | D18: ='BS-合并'!B26 -> 5174733.3
A19: 持有待售资产
A20: 一年内到期的非流动资产 | C20: ='BS-合并'!C27 -> 0
A21: 其他流动资产 | C21: ='BS-合并'!C28 -> 3625070.3 | D21: ='BS-合并'!B28 -> 1383995.4
A25: 流动资产合计 | C25: =SUM(C8:C24) -> 3.0541432e+08 | D25: =SUM(D8:D24) -> 2.691092e+08 | F25: =C25-'BS-合并'!C29 -> 0 | H25: =D25-'BS-合并'!B29 -> 0
A26: 非流动资产：
A27: 债权投资
A28: 可供出售金融资产
A29: 其他债权投资
A30: 持有至到期投资
A31: 长期应收款 | C31: ='BS-合并'!C36 -> 0 | D31: 0
A32: 长期股权投资 | C32: ='BS-合并'!C37 -> 0 | D32: 0
A33: 其他权益工具投资
A34: 其他非流动金融资产 | C34: ='BS-合并'!C38 -> 3000000 | D34: ='BS-合并'!B38 -> 17507066
A35: 投资性房地产
A36: 固定资产 | C36: ='BS-合并'!C42 -> 1.9525217e+08 | D36: ='BS-合并'!B42 -> 2.0108397e+08
A37: 在建工程 | C37: ='BS-合并'!C43 -> 42663260 | D37: ='BS-合并'!B43 -> 11313317
A38: 生产性生物资产
A39: 油气资产
A40: 使用权资产
A41: 无形资产 | C41: ='BS-合并'!C47 -> 13011878 | D41: ='BS-合并'!B47 -> 13123470
A42: 开发支出
A43: 商誉 | C43: ='BS-合并'!C49 -> 4043375.5 | D43: ='BS-合并'!B49 -> 4043375.5
A44: 长期待摊费用 | C44: ='BS-合并'!C50 -> 3260115 | D44: ='BS-合并'!B50 -> 4841651.7
A45: 递延所得税资产 | C45: ='BS-合并'!C51 -> 10042.63 | D45: ='BS-合并'!B51 -> 10042.63
A46: 其他非流动资产 | C46: ='BS-合并'!C52 -> 0 | D46: 0
A50: 非流动资产合计 | C50: =SUM(C27:C49) -> 2.6124084e+08 | D50: =SUM(D27:D49) -> 2.5192289e+08 | F50: =C50-'BS-合并'!C53 -> 0 | H50: =D50-'BS-合并'!B53 -> 0
A52: 资产总计 | C52: =C50+C25 -> 5.6665516e+08 | D52: =D50+D25 -> 5.210321e+08 | F52: =C52-'BS-合并'!C54 -> 0 | H52: =D52-'BS-合并'!B54 -> 0
A54: 资产负债表（续）
A56: =A3 -> 编制单位：飞而康快速制造科技有限责任公司 | D56: 金额单位：人民币元
A57: 负债和所有者权益（或股东权益） | B57: 附注 | C57: =C4 -> 45991 | D57: 45657
A60: 流动负债：
A61: 短期借款 | C61: ='BS-合并'!F9 -> 1.1655207e+08 | D61: ='BS-合并'!E9 -> 1.0278669e+08
A62: 以公允价值计量且其变动计入当期损益的金融负债
A63: 交易性金融负债
A64: 衍生金融负债
A65: 应付票据 | C65: ='BS-合并'!F11 -> 1128557.5 | D65: 0
A66: 应付账款 | C66: ='BS-合并'!F12 -> 1.4933087e+08 | D66: ='BS-合并'!E12 -> 1.1834943e+08
A67: 预收款项 | C67: ='BS-合并'!F13 -> 3510493.9 | D67: ='BS-合并'!E13 -> 0
A68: 合同负债 | C68: ='BS-合并'!F14 -> 5289418 | D68: ='BS-合并'!E14 -> 9067703.6
A69: 应付职工薪酬 | C69: ='BS-合并'!F15 -> 3192067.9 | D69: ='BS-合并'!E15 -> 7566027.5
A70: 应交税费 | C70: ='BS-合并'!F16 -> 738098.44 | D70: ='BS-合并'!E16 -> 3095811.7
A71: 其他应付款 | C71: ='BS-合并'!F17+'BS-合并'!F18+'BS-合并'!F19 -> 3937706.1 | D71: ='BS-合并'!E19 -> 1627343.6
A72: 持有待售负债
A73: 一年内到期的非流动负债 | C73: ='BS-合并'!F20 -> 8372322.7 | D73: ='BS-合并'!E20 -> 35008704
A74: 其他流动负债 | C74: ='BS-合并'!F21 -> 4279795.6 | D74: ='BS-合并'!E21 -> 22779924
A76: 流动负债合计 | C76: =SUM(C61:C75) -> 2.963314e+08 | D76: =SUM(D61:D75) -> 3.0028163e+08 | F76: =C76-'BS-合并'!F25 -> 0 | H76: =D76-'BS-合并'!E25 -> 0
A77: 非流动负债：
A78: 长期借款 | C78: ='BS-合并'!F27 -> 48710000 | D78: ='BS-合并'!E27 -> 23800000
A79: 应付债券
A80: 其中：优先股
A81: 永续债
A82: 租赁负债
A83: 长期应付款 | C83: ='BS-合并'!F29 -> 0 | D83: 0
A84: 长期应付职工薪酬
A85: 预计负债
A86: 递延收益 | C86: ='BS-合并'!F32 -> 33930809 | D86: ='BS-合并'!E32 -> 6958008.6
A87: 递延所得税负债
A88: 其他非流动负债
A90: 非流动负债合计 | C90: =SUM(C78:C89)-C80-C81 -> 82640809 | D90: =SUM(D78:D89)-D80-D81 -> 30758009 | F90: =D90-'BS-合并'!E35 -> 0 | H90: =C90-'BS-合并'!F35 -> 0
A91: 负债合计 | C91: =C90+C76 -> 3.7897221e+08 | D91: =D90+D76 -> 3.3103964e+08 | F91: =C91-'BS-合并'!F36 -> 0 | H91: =D91-'BS-合并'!E36 -> 0
A92: 所有者权益：
A93: 实收资本（或股本) | C93: ='BS-合并'!F40 -> 262811200 | D93: 260216000
A94: 其他权益工具
A95: 其中:优先股
A96: 永续债
A97: 资本公积 | C97: ='BS-合并'!F41 -> 1.1765014e+08 | D97: 1.0524534e+08
A98: 减：库存股
A99: 其他综合收益
A100: 专项储备
A101: 盈余公积
A102: 未分配利润 | C102: ='BS-合并'!F44 -> -1.9456799e+08 | D102: ='BS-合并'!E44 -> -1.7721522e+08 | F102: =C102-'BS-合并'!F44 -> 0 | H102: =D102-'BS-合并'!E44 -> 0
A103: 归属于母公司所有者权益合计 | C103: =C93+C97+C102 -> 1.8589336e+08 | D103: =D93+D97+D102 -> 1.8824612e+08 | F103: =C103-'BS-合并'!F45 -> 0 | H103: =D103-'BS-合并'!E45 -> 0
A104: 少数股东权益 | C104: ='BS-合并'!F46 -> 1789588.5 | D104: ='BS-合并'!E46 -> 1746336.6 | F104: =C104-'BS-合并'!F46 -> 0 | H104: =D104-'BS-合并'!E46 -> 0
A105: 所有者权益合计 | C105: =C103+C104 -> 1.8768295e+08 | D105: =D103+D104 -> 1.8999246e+08 | F105: =C105-'BS-合并'!F47 -> 0 | H105: =D105-'BS-合并'!E47 -> 0
A106: 负债和所有者权益总计 | C106: =C105+C91 -> 5.6665516e+08 | D106: =D105+D91 -> 5.210321e+08 | F106: =C106-'BS-合并'!F54 -> 0 | H106: =D106-'BS-合并'!E54 -> 0
C109: =C106-C52 -> -0.003267765 | D109: =D106-D52 -> 0

Sheet 利润表-M
A1: 利润表
A3: ='资产负债表-M'!A3 -> 编制单位：飞而康快速制造科技有限责任公司 | C3: ='资产负债表-M'!C3 -> 45991 | D3: 金额单位：人民币元
A4: 项 目 | B4: 附注 | C4: 本期 | D4: 本年累计
A6: 一、营业收入 | C6: ='PL-合并'!C9 -> 16506857 | D6: ='PL-合并'!D9 -> 1.340243e+08
A7: 减：营业成本 | C7: ='PL-合并'!C12 -> 15830447 | D7: ='PL-合并'!D12 -> 1.1005757e+08
A8: 税金及附加 | C8: ='PL-合并'!C15 -> 82112.72 | D8: ='PL-合并'!D15 -> 829444.38
A9: 销售费用 | C9: ='PL-合并'!C16 -> 822770.64 | D9: ='PL-合并'!D16 -> 8045698
A10: 管理费用 | C10: ='PL-合并'!C17 -> 1193327.4 | D10: ='PL-合并'!D17 -> 8350965.1
A11: 研发费用 | C11: ='PL-合并'!C18 -> 4315088.8 | D11: ='PL-合并'!D18 -> 19920178
A12: 财务费用 | C12: ='PL-合并'!C19 -> 468077.9 | D12: ='PL-合并'!D19 -> 4508765.3
A13: 其中：利息费用 | C13: ='PL-合并'!C20 -> 458409.52 | D13: ='PL-合并'!D20 -> 4534024.2 | F13: 注意修改
A14: 利息收入 | C14: ='PL-合并'!C21 -> -232.59 | D14: ='PL-合并'!D21 -> -85075.68 | F14: 注意修改
A15: 加: 其他收益 | C15: ='PL-合并'!C22 -> 250000 | D15: ='PL-合并'!D22 -> 1305528.3
A16: 投资收益(损失以"－"填列) | C16: ='PL-合并'!C23 -> 0 | D16: ='PL-合并'!D23 -> 853056.55
A17: 其中：对联营企业和合营企业的投资收益 | C17: 0 | D17: 0
A18: 以摊余成本计量的金融资产终止确认收益(损失以"－"号填列） | C18: 0 | D18: 0
A19: 净敞口套期收益（损失以"－"号填列） | C19: 0 | D19: 0
A20: 公允价值变动收益(损失以"－"填列) | C20: ='PL-合并'!C27 -> 0 | D20: ='PL-合并'!D27 -> 0
A21: 信用减值损失(损失以“-”号填列) | C21: ='PL-合并'!C28 -> 0 | D21: ='PL-合并'!D28 -> -1780058.3
A22: 资产减值损失(损失以"－"填列) | C22: ='PL-合并'!C29 -> 0 | D22: ='PL-合并'!D29 -> 0
A23: 资产处置收益（损失以"-"填列） | C23: ='PL-合并'!C30 -> 0 | D23: ='PL-合并'!D30 -> 0 | F23: 注意修改
A24: 二、营业利润(亏损以"－"填列) | C24: =C6-C7-C8-C9-C10-C11-C12+C15+C16+C21+C22+C20 -> -5954966.8 | D24: =D6-D7-D8-D9-D10-D11-D12+D15+D16+D21+D22+D20 -> -17309794 | G24: =C24-'PL-合并'!C31 -> 0 | H24: =D24-'PL-合并'!D31 -> 0
A25: 加：营业外收入 | C25: ='PL-合并'!C32 -> 0 | D25: ='PL-合并'!D32 -> 70120.03 | G25: =C25-'PL-合并'!C32 -> 0 | H25: =D25-'PL-合并'!D32 -> 0
A26: 减：营业外支出 | C26: ='PL-合并'!C33 -> 0 | D26: ='PL-合并'!D33 -> 24203.21 | G26: =C26-'PL-合并'!C33 -> 0 | H26: =D26-'PL-合并'!D33 -> 0
A27: 三、利润总额(亏损以"－"填列) | C27: =C24+C25-C26 -> -5954966.8 | D27: =D24+D25-D26 -> -17263878 | G27: =C27-'PL-合并'!C34 -> 0 | H27: =D27-'PL-合并'!D34 -> 0
A28: 减：所得税费用 | C28: ='PL-合并'!C35 -> 20876.67 | D28: ='PL-合并'!D35 -> 45634.12 | G28: =C28-'PL-合并'!C35 -> 0 | H28: =D28-'PL-合并'!D35 -> 0
A29: 四、净利润(净亏损以"－"填列) | C29: =C27-C28 -> -5975843.5 | D29: =D27-D28 -> -17309512 | G29: =C29-'PL-合并'!C36 -> 0 | H29: =D29-'PL-合并'!D36 -> 0
A30: （一）按经营持续性分类
A31: 1.持续经营净利润（净亏损以"-"号填列）
A32: 2.终止经营净利润（净亏损以"-"号填列）
A33: （二）按所有权归属分类
A34: 1.归属于母公司所有者的净利润（净亏损以"-"号填列） | C34: ='PL-合并'!C38 -> -6048496.9 | D34: ='PL-合并'!D38 -> -17352764
A35: 2.少数股东损益（净亏损以"-"号填列） | C35: ='PL-合并'!C37 -> 72653.383 | D35: ='PL-合并'!D37 -> 43251.883
A36: 五、其他综合收益的税后净额
A37: 归属于母公司所有者的其他综合收益税后净额
A38: （一）不能重分类进损益的其他综合收益
A39: 1.重新计量设定受益计划变动额
A40: 2.权益法下不能转损益的其他综合收益
A41: 3.其他权益工具投资公允价值变动
A42: 4.企业自身信用风险公允价值变动
A43: （二）将重分类进损益的其他综合收益
A44: 1.权益法下可转损益的其他综合收益
A45: 2.可供出售金融资产公允价值变动损益
A46: 3.持有至到期投资重分类为可供出售金融资产损益
A47: 4.现金流量套期损益的有效部分
... A60: (二)、稀释每股收益

Sheet 现流表-M
A1: 现金流量表
A3: ='利润表-M'!A3 -> 编制单位：飞而康快速制造科技有限责任公司 | C3: ='利润表-M'!C3 -> 45991 | D3: 金额单位：人民币元
A4: 项 目 | B4: 附注 | C4: 本期 | D4: 本年累计
A5: 一、经营活动产生的现金流量：
A6: 销售商品、提供劳务收到的现金 | C6: ='CF-合并'!C6 -> 10324670 | D6: ='CF-合并'!D6 -> 92773879
A7: 收到的税费返还 | C7: ='CF-合并'!C17 -> 0 | D7: ='CF-合并'!D17 -> 20027.64
A8: 收到的其他与经营活动有关的现金 | C8: ='CF-合并'!C7+'CF-合并'!C8+'CF-合并'!C9+'CF-合并'!C10+'CF-合并'!C11+'CF-合并'!C12+'CF-合并'!C13+'CF-合并'!C14+'CF-合并'!C15+'CF-合并'!C16+'CF-合并'!C18 -> 2549154 | D8: ='CF-合并'!D7+'CF-合并'!D8+'CF-合并'!D9+'CF-合并'!D10+'CF-合并'!D11+'CF-合并'!D12+'CF-合并'!D13+'CF-合并'!D14+'CF-合并'!D15+'CF-合并'!D16+'CF-合并'!D18 -> 31348776
A9: 经营活动现金流入小计 | C9: =SUM(C6:C8) -> 12873824 | D9: =SUM(D6:D8) -> 1.2414268e+08
A10: 购买商品、接受劳务支付的现金 | C10: ='CF-合并'!C20 -> 7211064.5 | D10: ='CF-合并'!D20 -> 43903813
A11: 支付给职工以及为职工支付的现金 | C11: ='CF-合并'!C26 -> 3926466.5 | D11: ='CF-合并'!D26 -> 42990091
A12: 支付的各项税费 | C12: ='CF-合并'!C27 -> 488013.24 | D12: ='CF-合并'!D27 -> 4797507.6
A13: 支付的其他与经营活动有关的现金 | C13: ='CF-合并'!C21+'CF-合并'!C22+'CF-合并'!C23+'CF-合并'!C24+'CF-合并'!C25+'CF-合并'!C28 -> 666933.4 | D13: ='CF-合并'!D21+'CF-合并'!D22+'CF-合并'!D23+'CF-合并'!D24+'CF-合并'!D25+'CF-合并'!D28 -> 8057898
A14: 经营活动现金流出小计 | C14: =SUM(C10:C13) -> 12292478 | D14: =SUM(D10:D13) -> 99749309
A15: 经营活动产生的现金流量净额 | C15: =C9-C14 -> 581346.15 | D15: =D9-D14 -> 24393373
A16: 二、投资活动产生的现金流量：
A17: 收回投资收到的现金 | C17: ='CF-合并'!C32 -> 0 | D17: ='CF-合并'!D32 -> 5206506.8
A18: 取得投资收益收到的现金 | C18: ='CF-合并'!C33 -> 0 | D18: ='CF-合并'!D33 -> 10153615
A19: 处置固定资产、无形资产和其他长期资产收回的现金净额 | C19: ='CF-合并'!G5 -> 0 | D19: ='CF-合并'!H5 -> 0
A20: 处置子公司及其他营业单位收到的现金净额 | C20: ='CF-合并'!G6 -> 0 | D20: ='CF-合并'!H6 -> 0
A21: 收到的其他与投资活动有关的现金 | C21: ='CF-合并'!G7 -> 0 | D21: ='CF-合并'!H7 -> 0
A22: 投资活动现金流入小计 | C22: =C17+C18 -> 0 | D22: =D17+D18 -> 15360122
A23: 购建固定资产、无形资产和其他长期资产支付的现金 | C23: ='CF-合并'!G9 -> 353274.28 | D23: ='CF-合并'!H9 -> 46108059
A24: 投资支付的现金 | C24: ='CF-合并'!G10 -> 0 | D24: ='CF-合并'!H10 -> 0
A25: 取得子公司及其他营业单位支付的现金净额 | C25: ='CF-合并'!G12 -> 0 | D25: ='CF-合并'!H12 -> 0
A26: 支付的其他与投资活动有关的现金 | C26: ='CF-合并'!G11+'CF-合并'!G13 -> 0 | D26: ='CF-合并'!H11+'CF-合并'!H13 -> 0
A27: 投资活动现金流出小计 | C27: =C23+C24 -> 353274.28 | D27: =D23+D24 -> 46108059
A28: 投资活动产生的现金流量净额 | C28: =C22-C27 -> -353274.28 | D28: =D22-D27 -> -30747936
A29: 三、筹资活动产生的现金流量：
A30: 吸收投资收到的现金 | C30: ='CF-合并'!G17 -> 0 | D30: ='CF-合并'!H17 -> 15000000
A31: 其中：子公司吸收少数股东投资收到的现金 | C31: ='CF-合并'!G18 -> 0 | D31: ='CF-合并'!H18 -> 0
A32: 取得借款收到的现金 | C32: ='CF-合并'!G19 -> 3307738.8 | D32: ='CF-合并'!H19 -> 1.7717207e+08
A33: 发行债券收到的现金 | C33: ='CF-合并'!G20 -> 0 | D33: ='CF-合并'!H20 -> 0
A34: 收到的其他与筹资活动有关的现金 | C34: ='CF-合并'!G21 -> 0 | D34: ='CF-合并'!H21 -> 0
A35: 筹资活动现金流入小计 | C35: =C32+C34 -> 3307738.8 | D35: =D32+D34+D30 -> 1.9217207e+08
A36: 偿还债务支付的现金 | C36: ='CF-合并'!G23 -> 3000000 | D36: ='CF-合并'!H23 -> 168000000
A37: 分配股利、利润或偿付利息支付的现金 | C37: ='CF-合并'!G24 -> 199578.3 | D37: ='CF-合并'!H24 -> 4177815.1
A38: 其中：子公司支付给少数股东的股利、利润 | C38: ='CF-合并'!G25 -> 0 | D38: ='CF-合并'!H25 -> 0
A39: 支付的其他与筹资活动有关的现金 | C39: ='CF-合并'!G26 -> 922726.25 | D39: ='CF-合并'!H26 -> 7150111.2
A40: 筹资活动现金流出小计 | C40: =C36+C37+C39 -> 4122304.5 | D40: =D36+D37+D39 -> 1.7932793e+08
A41: 筹资活动产生的现金流量净额 | C41: =C35-C40 -> -814565.78 | D41: =D35-D40 -> 12844143
A42: 四、汇率变动对现金及现金等价物的影响 | C42: ='CF-合并'!G29 -> 0 | D42: ='CF-合并'!H29 -> 0
A43: 五、现金及现金等价物净增加额 | C43: =C15+C28+C41+C42 -> -586493.91 | D43: =D15+D28+D41+D42 -> 6489579.9
A44: 加：期初现金及现金等价物余额 | C44: ='CF-合并'!G31 -> 56826956 | D44: ='CF-合并'!H31 -> 49750882
A45: 六、期末现金及现金等价物余额 | C45: =C43+C44 -> 56240462 | D45: =D43+D44 -> 56240462

Sheet 合并试算平衡表
A1: 资产=负债+所有者权益 | B1: =ROUND(B57-B118,4) -> 0 | C1: =ROUND(C57-C118,4) -> 0 | D1: =ROUND(D57-D118,4) -> 0 | E1: =ROUND(E57-E118,4) -> 0 | F1: =ROUND(F57-F118,4) -> 0 | G1: =ROUND(G57-G118,4) -> 0 | H1: =ROUND(H57-H118,4) -> 0 | I1: =IF(B1=0,"","资产≠负债+权益，差额为"&FIXED(B1)) | J1: =IF(K1=0,"","资产≠负债+权益，差额为"&FIXED(K1)) -> 资产≠负债+权益，差额为0.00 | K1: =ROUND(K57-K118,4) -> 0.0033 | L1: =ROUND(L57-L118,4) -> 0 | M1: =ROUND(M57-M118,4) -> 0 | N1: =ROUND(N57-N118,4) -> 0 | O1: =ROUND(O57-O118,4) -> 0 | P1: =ROUND(P57-P118,4) -> 0 | Q1: =ROUND(Q57-Q118,4) -> 0 | R1: =ROUND(R57-R118,4) -> 0 | S1: =IF(L1=0,"","资产≠负债+权益，差额为"&FIXED(L1)) | T1: =IF(U1=0,"","资产≠负债+权益，差额为"&FIXED(U1)) -> 资产≠负债+权益，差额为0.00 | U1: =ROUND(U57-U118,4) -> 0.0022 | V1: =ROUND(V57-V118,4) -> 0 | W1: =ROUND(W57-W118,4) -> 0 | X1: =ROUND(X57-X118,4) -> 0 | Y1: =ROUND(Y57-Y118,4) -> 0 | Z1: =ROUND(Z57-Z118,4) -> 0 | AA1: =ROUND(AA57-AA118,4) -> 0 | AB1: =ROUND(AB57-AB118,4) -> 0 | AC1: =IF(V1=0,"","资产≠负债+权益，差额为"&FIXED(V1)) | AD1: =IF(AE1=0,"","资产≠负债+权益，差额为"&FIXED(AE1)) -> 资产≠负债+权益，差额为-4,793,116.37 | AE1: =ROUND(AE57-AE118,4) -> -4793116.4 | AF1: =ROUND(AF57-AF118,4) -> 0 | AG1: =ROUND(AG57-AG118,4) -> 0 | AH1: =ROUND(AH57-AH118,4) -> 0 | AI1: =ROUND(AI57-AI118,4) -> 0 | AJ1: =ROUND(AJ57-AJ118,4) -> 0 | AK1: =ROUND(AK57-AK118,4) -> 0 | AL1: =ROUND(AL57-AL118,4) -> 0 | AM1: =IF(AF1=0,"","资产≠负债+权益，差额为"&FIXED(AF1)) | AN1: =IF(AO1=0,"","资产≠负债+权益，差额为"&FIXED(AO1)) | AO1: =ROUND(AO57-AO118,4) -> 0 | AP1: =ROUND(AP57-AP118,4) -> 0 | AQ1: =ROUND(AQ57-AQ118,4) -> 0 | AR1: =ROUND(AR57-AR118,4) -> 0 | AS1: =IF(AL1=0,"","资产≠负债+权益，差额为"&FIXED(AL1)) | AT1: =IF(AU1=0,"","资产≠负债+权益，差额为"&FIXED(AU1)) | AU1: =ROUND(AU57-AU118,4) -> 0
A2: 资产负债表未分配利润=利润分配表未分配利润 | B2: =ROUND(B114-B165,4) -> 0 | C2: =ROUND(C114-C165,4) -> 0 | D2: =ROUND(D114-D165,4) -> 0 | E2: =ROUND(E114-E165,4) -> 0 | F2: =ROUND(F114-F165,4) -> 0 | G2: =ROUND(G114-G165,4) -> 0 | H2: =ROUND(H114-H165,4) -> 0 | I2: =IF(B2=0,"","未分配利润不平，差额为"&FIXED(B2)) | J2: =IF(K2=0,"","未分配利润不平，差额为"&FIXED(K2)) | K2: =ROUND(K114-K165,4) -> 0 | L2: =ROUND(L114-L165,4) -> 164488.8 | M2: =ROUND(M114-M165,4) -> 363548.72 | N2: =ROUND(N114-N165,4) -> 509004.78 | O2: =ROUND(O114-O165,4) -> 66729.37 | P2: =ROUND(P114-P165,4) -> 0 | Q2: =ROUND(Q114-Q165,4) -> 0 | R2: =ROUND(R114-R165,4) -> 1103771.7 | S2: =IF(L2=0,"","未分配利润不平，差额为"&FIXED(L2)) -> 未分配利润不平，差额为164,488.80 | T2: =IF(U2=0,"","未分配利润不平，差额为"&FIXED(U2)) | U2: =ROUND(U114-U165,4) -> 0 | V2: =ROUND(V114-V165,4) -> 88076507 | W2: =ROUND(W114-W165,4) -> 935730.76 | X2: =ROUND(X114-X165,4) -> 5166127.4 | Y2: =ROUND(Y114-Y165,4) -> 0 | Z2: =ROUND(Z114-Z165,4) -> 0 | AA2: =ROUND(AA114-AA165,4) -> 0 | AB2: =ROUND(AB114-AB165,4) -> 94178365 | AC2: =IF(V2=0,"","未分配利润不平，差额为"&FIXED(V2)) -> 未分配利润不平，差额为88,076,506.86 | AD2: =IF(AE2=0,"","未分配利润不平，差额为"&FIXED(AE2)) -> 未分配利润不平，差额为96,131,632.33 | AE2: =ROUND(AE114-AE165,4) -> 96131632 | AF2: =ROUND(AF114-AF165,4) -> 0 | AG2: =ROUND(AG114-AG165,4) -> 0 | AH2: =ROUND(AH114-AH165,4) -> 0 | AI2: =ROUND(AI114-AI165,4) -> 0 | AJ2: =ROUND(AJ114-AJ165,4) -> 0 | AK2: =ROUND(AK114-AK165,4) -> 0 | AL2: =ROUND(AL114-AL165,4) -> 0 | AM2: =IF(AF2=0,"","未分配利润不平，差额为"&FIXED(AF2)) | AN2: =IF(AO2=0,"","未分配利润不平，差额为"&FIXED(AO2)) | AO2: =ROUND(AO114-AO165,4) -> 0 | AP2: =ROUND(AP114-AP165,4) -> 0 | AQ2: =ROUND(AQ114-AQ165,4) -> 0 | AR2: =ROUND(AR114-AR165,4) -> 0 | AS2: =IF(AL2=0,"","未分配利润不平，差额为"&FIXED(AL2)) | AT2: =IF(AU2=0,"","未分配利润不平，差额为"&FIXED(AU2)) | AU2: =ROUND(AU114-AU165,4) -> 0
A3: 本年年初未分配利润=上年年末未分配利润 | B3: =ROUND(B152-L165,4) -> 0 | C3: =ROUND(C152-M165,4) -> 0 | D3: =ROUND(D152-N165,4) -> 0 | E3: =ROUND(E152-O165,4) -> 0 | F3: =ROUND(F152-P165,4) -> 0 | G3: =ROUND(G152-Q165,4) -> 0 | H3: =ROUND(H152-R165,4) -> 0 | I3: =IF(B3=0,"","未分配利润不衔接，差额为"&FIXED(B3)) | J3: =IF(K3=0,"","未分配利润不衔接，差额为"&FIXED(K3)) -> 未分配利润不衔接，差额为-1,370,059.75 | K3: =ROUND(K152-U165,4) -> -1370059.7 | L3: =ROUND(L152-V165,4) -> 0 | M3: =ROUND(M152-W165,4) -> 0 | N3: =ROUND(N152-X165,4) -> 0 | O3: =ROUND(O152-Y165,4) -> 0 | P3: =ROUND(P152-Z165,4) -> 0 | Q3: =ROUND(Q152-AA165,4) -> 0 | R3: =ROUND(R152-AB165,4) -> 0 | S3: =IF(L3=0,"","未分配利润不衔接，差额为"&FIXED(L3)) | T3: =IF(U3=0,"","未分配利润不衔接，差额为"&FIXED(U3)) -> 未分配利润不衔接，差额为171,212.16 | U3: =ROUND(U152-AE165,4) -> 171212.16 | V3: =ROUND(V152-AF165,4) -> -1.0384719e+08 | W3: =ROUND(W152-AG165,4) -> 1401823.7 | X3: =ROUND(X152-AH165,4) -> -8727987.7 | Y3: =ROUND(Y152-AI165,4) -> 0 | Z3: =ROUND(Z152-AJ165,4) -> 0 | AA3: =ROUND(AA152-AK165,4) -> 0 | AB3: =ROUND(AB152-AL165,4) -> -1.1117335e+08 | AC3: =IF(V3=0,"","未分配利润不衔接，差额为"&FIXED(V3)) -> 未分配利润不衔接，差额为-103,847,191.06 | AD3: =IF(AE3=0,"","未分配利润不衔接，差额为"&FIXED(AE3)) -> 未分配利润不衔接，差额为-103,885,574.52 | AE3: =ROUND(AE152-AO165,4) -> -1.0388557e+08 | AS3: =ROUND(AS152-#REF!,4) -> #REF! | AT3: =ROUND(AT152-#REF!,4) -> #REF! | AU3: =ROUND(AU152-#REF!,4) -> #REF!
A4: 合并试算平衡表-资产表
A5: ="编制单位："&基本信息!B2 -> 编制单位：飞而康快速制造科技有限责任公司 | C5: =B1/2 -> 0 | S5: =R40+S40-T40-U40 -> 0 | AO5: 金额：人民币元 | AU5: 金额：人民币元
A6: 项目 | B6: =基本信息!B14 -> 45991 | I6: 合并调整抵消 | K6: =B6 -> 45991 | L6: =基本信息!B13 -> 45657 | S6: 合并调整抵消 | U6: =L6 -> 45657 | V6: =基本信息!B12 -> 45291 | AC6: 合并调整抵消 | AE6: =V6 -> 45291 | AF6: =基本信息!B10 -> 0 | AM6: 合并调整抵消 | AO6: =AF6 -> 0 | AP6: 41639 | AS6: 合并调整抵消 | AU6: =AP6 -> 41639
B7: 母公司 | C7: =基本信息!C3 -> 飞而康新材料 | D7: =基本信息!C4 -> 飞而康精铸 | E7: =基本信息!C5 -> 飞而康热等静压 | F7: =基本信息!C6 -> 0 | G7: =基本信息!C7 -> 0 | H7: 汇总数 | I7: 借 方 | J7: 贷 方 | K7: 合并审定数 | L7: 母公司 | M7: =基本信息!C3 -> 飞而康新材料 | N7: =基本信息!C4 -> 飞而康精铸 | O7: =基本信息!C5 -> 飞而康热等静压 | P7: =基本信息!C6 -> 0 | Q7: =基本信息!C7 -> 0 | R7: 汇总数 | S7: 借 方 | T7: 贷 方 | U7: 合并审定数 | V7: =L7 -> 母公司 | W7: =M7 -> 飞而康新材料 | X7: =N7 -> 飞而康精铸 | Y7: =O7 -> 飞而康热等静压 | Z7: =P7 -> 0 | AA7: =Q7 -> 0 | AB7: =R7 -> 汇总数 | AC7: 借 方 | AD7: 贷 方 | AE7: 合并审定数 | AF7: =L7 -> 母公司 | AG7: =M7 -> 飞而康新材料 | AH7: =N7 -> 飞而康精铸 | AI7: =O7 -> 飞而康热等静压 | AJ7: =P7 -> 0 | AK7: =Q7 -> 0 | AL7: =R7 -> 汇总数 | AM7: 借 方 | AN7: 贷 方 | AO7: 合并审定数 | AP7: =V7 -> 母公司 | AQ7: =W7 -> 飞而康新材料 | AR7: =AB7 -> 汇总数 | AS7: 借 方 | AT7: 贷 方 | AU7: 合并审定数
A8: 流动资产
A9: 货币资金 | B9: =VLOOKUP(A9,快速BS新!A$6:C$212,3,0) -> 40351321 | C9: =VLOOKUP(A9,新材料BS新!$A$4:$D$191,3,0) -> 11647742 | D9: =VLOOKUP(A9,精铸BS新!$A$6:$C$86,3,0) -> 1306279.9 | E9: =VLOOKUP(A9,热等静压BS新!$A$6:$C$86,3,0) -> 3667334.2 | H9: =SUM(B9:G9) -> 56972677 | I9: =合并调整抵消分录!E3 -> 0 | J9: =合并调整抵消分录!F3 -> 0 | K9: =H9+I9-J9 -> 56972677 | L9: 24245573 | M9: 21849512 | N9: 1463763.7 | O9: 2194423 | R9: =SUM(L9:Q9) -> 49753272 | S9: 0 | T9: 0 | U9: =R9+S9-T9 -> 49753272 | V9: 17491300 | W9: 2796242.7 | X9: 863555.57 | Z9: =[6]TB子公司4!M10 -> 0 | AA9: =[6]TB子公司5!M10 -> 0 | AB9: =SUM(V9:AA9) -> 21151098 | AC9: =合并调整抵消分录!N3 -> 0 | AD9: =合并调整抵消分录!O3 -> 0 | AE9: =AB9+AC9-AD9 -> 21151098 | AL9: =SUM(AF9:AK9) -> 0 | AM9: =合并调整抵消分录!Q3 -> 0 | AN9: =合并调整抵消分录!R3 -> 0 | AO9: =AL9+AM9-AN9 -> 0 | AR9: =SUM(AP9:AQ9) -> 0 | AS9: =合并调整抵消分录!T3 -> 0 | AT9: =合并调整抵消分录!U3 -> 0 | AU9: =AR9+AS9-AT9 -> 0 | AV9: =VLOOKUP(A9,合并资产负债表!$A$6:$C$87,3,0) -> #N/A | AW9: =K9-AV9 -> #N/A
A10: △结算备付金 | H10: =SUM(B10:G10) -> 0 | I10: =合并调整抵消分录!E4 -> 0 | J10: =合并调整抵消分录!F4 -> 0 | K10: =H10+I10-J10 -> 0 | R10: =SUM(L10:Q10) -> 0 | S10: 0 | T10: 0 | U10: =R10+S10-T10 -> 0 | V10: 0 | W10: 0 | X10: 0 | Z10: =[6]TB子公司4!M11 -> 0 | AA10: =[6]TB子公司5!M11 -> 0 | AB10: =SUM(V10:AA10) -> 0 | AC10: =合并调整抵消分录!N4 -> 0 | AD10: =合并调整抵消分录!O4 -> 0 | AE10: =AB10+AC10-AD10 -> 0 | AL10: =SUM(AF10:AK10) -> 0 | AM10: =合并调整抵消分录!Q4 -> 0 | AN10: =合并调整抵消分录!R4 -> 0 | AO10: =AL10+AM10-AN10 -> 0 | AR10: =SUM(AP10:AQ10) -> 0 | AS10: =合并调整抵消分录!T4 -> 0 | AT10: =合并调整抵消分录!U4 -> 0 | AU10: =AR10+AS10-AT10 -> 0 | AW10: =K10-AV10 -> 0
A11: △拆出资金 | H11: =SUM(B11:G11) -> 0 | I11: =合并调整抵消分录!E5 -> 0 | J11: =合并调整抵消分录!F5 -> 0 | K11: =H11+I11-J11 -> 0 | R11: =SUM(L11:Q11) -> 0 | S11: 0 | T11: 0 | U11: =R11+S11-T11 -> 0 | V11: 0 | W11: 0 | X11: 0 | Z11: =[6]TB子公司4!M12 -> 0 | AA11: =[6]TB子公司5!M12 -> 0 | AB11: =SUM(V11:AA11) -> 0 | AC11: =合并调整抵消分录!N5 -> 0 | AD11: =合并调整抵消分录!O5 -> 0 | AE11: =AB11+AC11-AD11 -> 0 | AL11: =SUM(AF11:AK11) -> 0 | AM11: =合并调整抵消分录!Q5 -> 0 | AN11: =合并调整抵消分录!R5 -> 0 | AO11: =AL11+AM11-AN11 -> 0 | AR11: =SUM(AP11:AQ11) -> 0 | AS11: =合并调整抵消分录!T5 -> 0 | AT11: =合并调整抵消分录!U5 -> 0 | AU11: =AR11+AS11-AT11 -> 0 | AW11: =K11-AV11 -> 0
A12: 交易性金融资产 | B12: =VLOOKUP(A12,快速BS新!A$6:C$212,3,0) -> 0 | C12: =VLOOKUP(A12,新材料BS新!$A$4:$D$191,3,0) -> 0 | D12: =VLOOKUP(A12,精铸BS新!$A$6:$C$86,3,0) -> 0 | E12: =VLOOKUP(A12,热等静压BS新!$A$6:$C$86,3,0) -> 0 | H12: =SUM(B12:G12) -> 0 | I12: =合并调整抵消分录!E6 -> 0 | J12: =合并调整抵消分录!F6 -> 0 | K12: =H12+I12-J12 -> 0 | L12: 0 | M12: 0 | N12: 0 | O12: 0 | R12: =SUM(L12:Q12) -> 0 | S12: 0 | T12: 0 | U12: =R12+S12-T12 -> 0 | V12: 0 | W12: 0 | X12: 0 | Z12: =[6]TB子公司4!M13 -> 0 | AA12: =[6]TB子公司5!M13 -> 0 | AB12: =SUM(V12:AA12) -> 0 | AC12: =合并调整抵消分录!N6 -> 0 | AD12: =合并调整抵消分录!O6 -> 0 | AE12: =AB12+AC12-AD12 -> 0 | AL12: =SUM(AF12:AK12) -> 0 | AM12: =合并调整抵消分录!Q6 -> 0 | AN12: =合并调整抵消分录!R6 -> 0 | AO12: =AL12+AM12-AN12 -> 0 | AR12: =SUM(AP12:AQ12) -> 0 | AS12: =合并调整抵消分录!T6 -> 0 | AT12: =合并调整抵消分录!U6 -> 0 | AU12: =AR12+AS12-AT12 -> 0 | AW12: =K12-AV12 -> 0
A13: 衍生金融资产 | H13: =SUM(B13:G13) -> 0 | I13: =合并调整抵消分录!E7 -> 0 | J13: =合并调整抵消分录!F7 -> 0 | K13: =H13+I13-J13 -> 0 | R13: =SUM(L13:Q13) -> 0 | S13: 0 | T13: 0 | U13: =R13+S13-T13 -> 0 | V13: 0 | W13: 0 | X13: 0 | Z13: =[6]TB子公司4!M14 -> 0 | AA13: =[6]TB子公司5!M14 -> 0 | AB13: =SUM(V13:AA13) -> 0 | AC13: =合并调整抵消分录!N7 -> 0 | AD13: =合并调整抵消分录!O7 -> 0 | AE13: =AB13+AC13-AD13 -> 0 | AL13: =SUM(AF13:AK13) -> 0 | AM13: =合并调整抵消分录!Q7 -> 0 | AN13: =合并调整抵消分录!R7 -> 0 | AO13: =AL13+AM13-AN13 -> 0 | AR13: =SUM(AP13:AQ13) -> 0 | AS13: =合并调整抵消分录!T7 -> 0 | AT13: =合并调整抵消分录!U7 -> 0 | AU13: =AR13+AS13-AT13 -> 0 | AW13: =K13-AV13 -> 0
A14: 应收票据 | B14: =VLOOKUP(A14,快速BS新!A$6:C$212,3,0) -> 1944969.9 | C14: =VLOOKUP(A14,新材料BS新!$A$4:$D$191,3,0) -> 3771405.6 | D14: =VLOOKUP(A14,精铸BS新!$A$6:$C$86,3,0) -> 508150.86 | E14: =VLOOKUP(A14,热等静压BS新!$A$6:$C$86,3,0) -> 541632.16 | H14: =SUM(B14:G14) -> 6766158.5 | I14: =合并调整抵消分录!E8 -> 0 | J14: =合并调整抵消分录!F8 -> 0 | K14: =H14+I14-J14 -> 6766158.5 | L14: -353554.12 | M14: 4565261.8 | N14: 1675222.9 | O14: 2746888.1 | R14: =SUM(L14:Q14) -> 8633818.7 | S14: 0 | T14: 0 | U14: =R14+S14-T14 -> 8633818.7 | V14: 475714.56 | W14: 12000 | X14: 100000 | Z14: =[6]TB子公司4!M15 -> 0 | AA14: =[6]TB子公司5!M15 -> 0 | AB14: =SUM(V14:AA14) -> 587714.56 | AC14: =合并调整抵消分录!N8 -> 0 | AD14: =合并调整抵消分录!O8 -> 0 | AE14: =AB14+AC14-AD14 -> 587714.56 | AL14: =SUM(AF14:AK14) -> 0 | AM14: =合并调整抵消分录!Q8 -> 0 | AN14: =合并调整抵消分录!R8 -> 0 | AO14: =AL14+AM14-AN14 -> 0 | AR14: =SUM(AP14:AQ14) -> 0 | AS14: =合并调整抵消分录!T8 -> 0 | AT14: =合并调整抵消分录!U8 -> 0 | AU14: =AR14+AS14-AT14 -> 0 | AV14: =VLOOKUP(A14,合并资产负债表!$A$6:$C$87,3,0) -> #N/A | AW14: =K14-AV14 -> #N/A
A15: 应收账款 | B15: =VLOOKUP(A15,快速BS新!A$6:C$212,3,0) -> 49191612 | C15: =VLOOKUP(A15,新材料BS新!$A$4:$D$191,3,0) -> 1.30096e+08 | D15: =VLOOKUP(A15,精铸BS新!$A$6:$C$86,3,0) -> 8564840.5 | E15: =VLOOKUP(A15,热等静压BS新!$A$6:$C$86,3,0) -> 11202090 | H15: =SUM(B15:G15) -> 1.9905455e+08 | I15: =合并调整抵消分录!E9 -> 0 | J15: =合并调整抵消分录!F9 -> 83722523 | K15: =H15+I15-J15 -> 1.1533203e+08 | L15: 52412192 | M15: 88207509 | N15: 8982104.4 | O15: 7005011.8 | R15: =SUM(L15:Q15) -> 1.5660682e+08 | S15: 0 | T15: 63078609 | U15: =R15+S15-T15 -> 93528208 | V15: 69604890 | W15: 5944026.2 | X15: 7616729.4 | Z15: =[6]TB子公司4!M16 -> 0 | AA15: =[6]TB子公司5!M16 -> 0 | AB15: =SUM(V15:AA15) -> 83165646 | AC15: =合并调整抵消分录!N9 -> 0 | AD15: =合并调整抵消分录!O9 -> 4469405.8 | AE15: =AB15+AC15-AD15 -> 78696240 | AL15: =SUM(AF15:AK15) -> 0 | AM15: =合并调整抵消分录!Q9 -> 0 | AN15: =合并调整抵消分录!R9 -> 0 | AO15: =AL15+AM15-AN15 -> 0 | AR15: =SUM(AP15:AQ15) -> 0 | AS15: =合并调整抵消分录!T9 -> 0 | AT15: =合并调整抵消分录!U9 -> 0 | AU15: =AR15+AS15-AT15 -> 0 | AV15: =VLOOKUP(A15,合并资产负债表!$A$6:$C$87,3,0) -> #N/A | AW15: =K15-AV15 -> #N/A
A16: 应收款项融资 | B16: =VLOOKUP(A16,快速BS新!A$6:C$212,3,0) -> 0 | C16: =VLOOKUP(A16,新材料BS新!$A$4:$D$191,3,0) -> 0 | D16: =VLOOKUP(A16,精铸BS新!$A$6:$C$86,3,0) -> 0 | E16: =VLOOKUP(A16,热等静压BS新!$A$6:$C$86,3,0) -> 0 | K16: =H16+I16-J16 -> 0 | L16: 0 | M16: 0 | N16: 0 | O16: 0 | R16: =SUM(L16:Q16) -> 0 | U16: =R16+S16-T16 -> 0
A17: 预付款项 | B17: =VLOOKUP(A17,快速BS新!A$6:C$212,3,0) -> 4125185.1 | C17: =VLOOKUP(A17,新材料BS新!$A$4:$D$191,3,0) -> 2983761.2 | D17: =VLOOKUP(A17,精铸BS新!$A$6:$C$86,3,0) -> 150161.06 | E17: =VLOOKUP(A17,热等静压BS新!$A$6:$C$86,3,0) -> 176 | H17: =SUM(B17:G17) -> 7259283.4 | I17: =合并调整抵消分录!E10 -> 0 | J17: =合并调整抵消分录!F10 -> 0 | K17: =H17+I17-J17 -> 7259283.4 | L17: 7808447.8 | M17: 4659949.2 | N17: 148033.26 | O17: 151176 | R17: =SUM(L17:Q17) -> 12767606 | S17: 0 | T17: 0 | U17: =R17+S17-T17 -> 12767606 | V17: 2827235.5 | W17: 369050.36 | X17: 122681.91 | Z17: =[6]TB子公司4!M17 -> 0 | AA17: =[6]TB子公司5!M17 -> 0 | AB17: =SUM(V17:AA17) -> 3318967.8 | AC17: =合并调整抵消分录!N10 -> 0 | AD17: =合并调整抵消分录!O10 -> 1408058.1 | AE17: =AB17+AC17-AD17 -> 1910909.6 | AL17: =SUM(AF17:AK17) -> 0 | AM17: =合并调整抵消分录!Q10 -> 0 | AN17: =合并调整抵消分录!R10 -> 0 | AO17: =AL17+AM17-AN17 -> 0 | AR17: =SUM(AP17:AQ17) -> 0 | AS17: =合并调整抵消分录!T10 -> 0 | AT17: =合并调整抵消分录!U10 -> 0 | AU17: =AR17+AS17-AT17 -> 0 | AV17: =VLOOKUP(A17,合并资产负债表!$A$6:$C$87,3,0) -> #N/A | AW17: =K17-AV17 -> #N/A
A18: △应收保费 | H18: =SUM(B18:G18) -> 0 | I18: =合并调整抵消分录!E11 -> 0 | J18: =合并调整抵消分录!F11 -> 0 | K18: =H18+I18-J18 -> 0 | R18: =SUM(L18:Q18) -> 0 | S18: 0 | T18: 0 | U18: =R18+S18-T18 -> 0 | V18: 0 | W18: 0 | X18: 0 | Z18: =[6]TB子公司4!M18 -> 0 | AA18: =[6]TB子公司5!M18 -> 0 | AB18: =SUM(V18:AA18) -> 0 | AC18: =合并调整抵消分录!N11 -> 0 | AD18: =合并调整抵消分录!O11 -> 0 | AE18: =AB18+AC18-AD18 -> 0 | AL18: =SUM(AF18:AK18) -> 0 | AM18: =合并调整抵消分录!Q11 -> 0 | AN18: =合并调整抵消分录!R11 -> 0 | AO18: =AL18+AM18-AN18 -> 0 | AR18: =SUM(AP18:AQ18) -> 0 | AS18: =合并调整抵消分录!T11 -> 0 | AT18: =合并调整抵消分录!U11 -> 0 | AU18: =AR18+AS18-AT18 -> 0 | AW18: =K18-AV18 -> 0
A19: △应收分保账款 | H19: =SUM(B19:G19) -> 0 | I19: =合并调整抵消分录!E12 -> 0 | J19: =合并调整抵消分录!F12 -> 0 | K19: =H19+I19-J19 -> 0 | R19: =SUM(L19:Q19) -> 0 | S19: 0 | T19: 0 | U19: =R19+S19-T19 -> 0 | Z19: =[6]TB子公司4!M19 -> 0 | AA19: =[6]TB子公司5!M19 -> 0 | AB19: =SUM(V19:AA19) -> 0 | AC19: =合并调整抵消分录!N12 -> 0 | AD19: =合并调整抵消分录!O12 -> 0 | AE19: =AB19+AC19-AD19 -> 0 | AL19: =SUM(AF19:AK19) -> 0 | AM19: =合并调整抵消分录!Q12 -> 0 | AN19: =合并调整抵消分录!R12 -> 0 | AO19: =AL19+AM19-AN19 -> 0 | AR19: =SUM(AP19:AQ19) -> 0 | AS19: =合并调整抵消分录!T12 -> 0 | AT19: =合并调整抵消分录!U12 -> 0 | AU19: =AR19+AS19-AT19 -> 0 | AW19: =K19-AV19 -> 0
A20: △应收分保合同准备金 | H20: =SUM(B20:G20) -> 0 | I20: =合并调整抵消分录!E13 -> 0 | J20: =合并调整抵消分录!F13 -> 0 | K20: =H20+I20-J20 -> 0 | R20: =SUM(L20:Q20) -> 0 | S20: 0 | T20: 0 | U20: =R20+S20-T20 -> 0 | V20: 0 | W20: 0 | X20: 0 | Z20: =[6]TB子公司4!M20 -> 0 | AA20: =[6]TB子公司5!M20 -> 0 | AB20: =SUM(V20:AA20) -> 0 | AC20: =合并调整抵消分录!N13 -> 0 | AD20: =合并调整抵消分录!O13 -> 0 | AE20: =AB20+AC20-AD20 -> 0 | AL20: =SUM(AF20:AK20) -> 0 | AM20: =合并调整抵消分录!Q13 -> 0 | AN20: =合并调整抵消分录!R13 -> 0 | AO20: =AL20+AM20-AN20 -> 0 | AR20: =SUM(AP20:AQ20) -> 0 | AS20: =合并调整抵消分录!T13 -> 0 | AT20: =合并调整抵消分录!U13 -> 0 | AU20: =AR20+AS20-AT20 -> 0 | AW20: =K20-AV20 -> 0
A21: 应收利息 | B21: =VLOOKUP(A21,快速BS新!A$6:C$212,3,0) -> 0 | C21: =VLOOKUP(A21,新材料BS新!$A$4:$D$191,3,0) -> 0 | D21: =VLOOKUP(A21,精铸BS新!$A$6:$C$86,3,0) -> 0 | E21: =VLOOKUP(A21,热等静压BS新!$A$6:$C$86,3,0) -> 0 | H21: =SUM(B21:G21) -> 0 | I21: =合并调整抵消分录!E14 -> 0 | J21: =合并调整抵消分录!F14 -> 0 | K21: =H21+I21-J21 -> 0 | L21: 0 | M21: 0 | N21: 0 | O21: 0 | R21: =SUM(L21:Q21) -> 0 | S21: 0 | T21: 0 | U21: =R21+S21-T21 -> 0 | V21: 0 | W21: 0 | X21: 0 | Z21: =[6]TB子公司4!M21 -> 0 | AA21: =[6]TB子公司5!M21 -> 0 | AB21: =SUM(V21:AA21) -> 0 | AC21: =合并调整抵消分录!N14 -> 0 | AD21: =合并调整抵消分录!O14 -> 0 | AE21: =AB21+AC21-AD21 -> 0 | AL21: =SUM(AF21:AK21) -> 0 | AM21: =合并调整抵消分录!Q14 -> 0 | AN21: =合并调整抵消分录!R14 -> 0 | AO21: =AL21+AM21-AN21 -> 0 | AR21: =SUM(AP21:AQ21) -> 0 | AS21: =合并调整抵消分录!T14 -> 0 | AT21: =合并调整抵消分录!U14 -> 0 | AU21: =AR21+AS21-AT21 -> 0 | AV21: =VLOOKUP(A21,合并资产负债表!$A$6:$C$87,3,0) -> #N/A | AW21: =K21-AV21 -> #N/A
A22: 应收股利 | B22: =VLOOKUP(A22,快速BS新!A$6:C$212,3,0) -> 0 | C22: =VLOOKUP(A22,新材料BS新!$A$4:$D$191,3,0) -> 0 | D22: =VLOOKUP(A22,精铸BS新!$A$6:$C$86,3,0) -> 0 | E22: =VLOOKUP(A22,热等静压BS新!$A$6:$C$86,3,0) -> 0 | H22: =SUM(B22:G22) -> 0 | I22: =合并调整抵消分录!E15 -> 0 | J22: =合并调整抵消分录!F15 -> 0 | K22: =H22+I22-J22 -> 0 | L22: 0 | M22: 0 | N22: 0 | O22: 0 | R22: =SUM(L22:Q22) -> 0 | S22: 0 | T22: 0 | U22: =R22+S22-T22 -> 0 | V22: 0 | W22: 0 | X22: 0 | Z22: =[6]TB子公司4!M22 -> 0 | AA22: =[6]TB子公司5!M22 -> 0 | AB22: =SUM(V22:AA22) -> 0 | AC22: =合并调整抵消分录!N15 -> 0 | AD22: =合并调整抵消分录!O15 -> 0 | AE22: =AB22+AC22-AD22 -> 0 | AL22: =SUM(AF22:AK22) -> 0 | AM22: =合并调整抵消分录!Q15 -> 0 | AN22: =合并调整抵消分录!R15 -> 0 | AO22: =AL22+AM22-AN22 -> 0 | AR22: =SUM(AP22:AQ22) -> 0 | AS22: =合并调整抵消分录!T15 -> 0 | AT22: =合并调整抵消分录!U15 -> 0 | AU22: =AR22+AS22-AT22 -> 0 | AV22: =VLOOKUP(A22,合并资产负债表!$A$6:$C$87,3,0) -> #N/A | AW22: =K22-AV22 -> #N/A
A23: 其他应收款 | B23: =VLOOKUP(A23,快速BS新!A$6:C$212,3,0) -> 83537.31 | C23: =VLOOKUP(A23,新材料BS新!$A$4:$D$191,3,0) -> 242421.69 | D23: =VLOOKUP(A23,精铸BS新!$A$6:$C$86,3,0) -> 233520.98 | E23: =VLOOKUP(A23,热等静压BS新!$A$6:$C$86,3,0) -> 161683.13 | H23: =SUM(B23:G23) -> 721163.11 | I23: =合并调整抵消分录!E16 -> 0 | J23: =合并调整抵消分录!F16 -> 0 | K23: =H23+I23-J23 -> 721163.11 | L23: 101888.49 | M23: 698113.73 | N23: 210509.69 | O23: 136338.05 | R23: =SUM(L23:Q23) -> 1146850 | S23: 0 | T23: 336853 | U23: =R23+S23-T23 -> 809996.96 | V23: 1744391.1 | W23: 76009.5 | X23: 1899.33 | Z23: =[6]TB子公司4!M23 -> 0 | AA23: =[6]TB子公司5!M23 -> 0 | AB23: =SUM(V23:AA23) -> 1822299.9 | AC23: =合并调整抵消分录!N16 -> 0 | AD23: =合并调整抵消分录!O16 -> 559382.32 | AE23: =AB23+AC23-AD23 -> 1262917.6 | AL23: =SUM(AF23:AK23) -> 0 | AM23: =合并调整抵消分录!Q16 -> 0 | AN23: =合并调整抵消分录!R16 -> 0 | AO23: =AL23+AM23-AN23 -> 0 | AR23: =SUM(AP23:AQ23) -> 0 | AS23: =合并调整抵消分录!T16 -> 0 | AT23: =合并调整抵消分录!U16 -> 0 | AU23: =AR23+AS23-AT23 -> 0 | AV23: =VLOOKUP(A23,合并资产负债表!$A$6:$C$87,3,0) -> #N/A | AW23: =K23-AV23 -> #N/A
A24: △买入返售金融资产 | H24: =SUM(B24:G24) -> 0 | I24: =合并调整抵消分录!E17 -> 0 | J24: =合并调整抵消分录!F17 -> 0 | K24: =H24+I24-J24 -> 0 | R24: =SUM(L24:Q24) -> 0 | S24: 0 | T24: 0 | U24: =R24+S24-T24 -> 0 | V24: 0 | W24: 0 | X24: 0 | Z24: =[6]TB子公司4!M24 -> 0 | AA24: =[6]TB子公司5!M24 -> 0 | AB24: =SUM(V24:AA24) -> 0 | AC24: =合并调整抵消分录!N17 -> 0 | AD24: =合并调整抵消分录!O17 -> 0 | AE24: =AB24+AC24-AD24 -> 0 | AL24: =SUM(AF24:AK24) -> 0 | AM24: =合并调整抵消分录!Q17 -> 0 | AN24: =合并调整抵消分录!R17 -> 0 | AO24: =AL24+AM24-AN24 -> 0 | AR24: =SUM(AP24:AQ24) -> 0 | AS24: =合并调整抵消分录!T17 -> 0 | AT24: =合并调整抵消分录!U17 -> 0 | AU24: =AR24+AS24-AT24 -> 0 | AW24: =K24-AV24 -> 0
A25: 存货 | B25: =VLOOKUP(A25,快速BS新!A$6:C$212,3,0) -> 13492044 | C25: =VLOOKUP(A25,新材料BS新!$A$4:$D$191,3,0) -> 82156041 | D25: =VLOOKUP(A25,精铸BS新!$A$6:$C$86,3,0) -> 8214116.1 | E25: =VLOOKUP(A25,热等静压BS新!$A$6:$C$86,3,0) -> 9470975.7 | H25: =SUM(B25:G25) -> 1.1333318e+08 | I25: =合并调整抵消分录!E18 -> 0 | J25: =合并调整抵消分录!F18 -> 21888.38 | K25: =H25+I25-J25 -> 1.1331129e+08 | L25: 12211515 | M25: 63786150 | N25: 4231996.6 | O25: 9481405.3 | R25: =SUM(L25:Q25) -> 89711068 | S25: 0 | T25: 44089.49 | U25: =R25+S25-T25 -> 89666978 | V25: 36733409 | W25: 3436516.1 | X25: 2517723.7 | Z25: =[6]TB子公司4!M25 -> 0 | AA25: =[6]TB子公司5!M25 -> 0 | AB25: =SUM(V25:AA25) -> 42687649 | AC25: =合并调整抵消分录!N18 -> 0 | AD25: =合并调整抵消分录!O18 -> 0 | AE25: =AB25+AC25-AD25 -> 42687649 | AL25: =SUM(AF25:AK25) -> 0 | AM25: =合并调整抵消分录!Q18 -> 0 | AN25: =合并调整抵消分录!R18 -> 0 | AO25: =AL25+AM25-AN25 -> 0 | AR25: =SUM(AP25:AQ25) -> 0 | AS25: =合并调整抵消分录!T18 -> 0 | AT25: =合并调整抵消分录!U18 -> 0 | AU25: =AR25+AS25-AT25 -> 0 | AV25: =VLOOKUP(A25,合并资产负债表!$A$6:$C$87,3,0) -> #N/A | AW25: =K25-AV25 -> #N/A
A26: 合同资产 | B26: =VLOOKUP(A26,快速BS新!A$6:C$212,3,0) -> 0 | C26: =VLOOKUP(A26,新材料BS新!$A$4:$D$191,3,0) -> 1426653 | D26: =VLOOKUP(A26,精铸BS新!$A$6:$C$86,3,0) -> 0 | E26: =VLOOKUP(A26,热等静压BS新!$A$6:$C$86,3,0) -> 0 | H26: =SUM(B26:G26) -> 1426653 | K26: =H26+I26-J26 -> 1426653 | L26: 713818.6 | M26: 1649153.4 | N26: 0 | O26: 0 | R26: =SUM(L26:Q26) -> 2362972 | U26: =R26+S26-T26 -> 2362972
A27: 划分为持有待售的资产 | H27: =SUM(B27:G27) -> 0 | I27: =合并调整抵消分录!E19 -> 0 | J27: =合并调整抵消分录!F19 -> 0 | K27: =H27+I27-J27 -> 0 | R27: =SUM(L27:Q27) -> 0 | S27: 0 | T27: 0 | U27: =R27+S27-T27 -> 0 | V27: 0 | W27: 0 | X27: 0 | Z27: =[6]TB子公司4!M26 -> 0 | AA27: =[6]TB子公司5!M26 -> 0 | AB27: =SUM(V27:AA27) -> 0 | AC27: =合并调整抵消分录!N19 -> 0 | AD27: =合并调整抵消分录!O19 -> 0 | AE27: =AB27+AC27-AD27 -> 0 | AL27: =SUM(AF27:AK27) -> 0 | AM27: =合并调整抵消分录!Q19 -> 0 | AN27: =合并调整抵消分录!R19 -> 0 | AO27: =AL27+AM27-AN27 -> 0 | AR27: =SUM(AP27:AQ27) -> 0 | AS27: =合并调整抵消分录!T19 -> 0 | AT27: =合并调整抵消分录!U19 -> 0 | AU27: =AR27+AS27-AT27 -> 0 | AW27: =K27-AV27 -> 0
A28: 一年内到期的非流动资产 | B28: =VLOOKUP(A28,快速BS新!A$6:C$212,3,0) -> 0 | C28: =VLOOKUP(A28,新材料BS新!$A$4:$D$191,3,0) -> 0 | D28: =VLOOKUP(A28,精铸BS新!$A$6:$C$86,3,0) -> 0 | E28: =VLOOKUP(A28,热等静压BS新!$A$6:$C$86,3,0) -> 0 | H28: =SUM(B28:G28) -> 0 | I28: =合并调整抵消分录!E20 -> 0 | J28: =合并调整抵消分录!F20 -> 0 | K28: =H28+I28-J28 -> 0 | L28: 0 | M28: 0 | N28: 0 | O28: 0 | R28: =SUM(L28:Q28) -> 0 | S28: 0 | T28: 0 | U28: =R28+S28-T28 -> 0 | Z28: =[6]TB子公司4!M27 -> 0 | AA28: =[6]TB子公司5!M27 -> 0 | AB28: =SUM(V28:AA28) -> 0 | AC28: =合并调整抵消分录!N20 -> 0 | AD28: =合并调整抵消分录!O20 -> 0 | AE28: =AB28+AC28-AD28 -> 0 | AL28: =SUM(AF28:AK28) -> 0 | AM28: =合并调整抵消分录!Q20 -> 0 | AN28: =合并调整抵消分录!R20 -> 0 | AO28: =AL28+AM28-AN28 -> 0 | AR28: =SUM(AP28:AQ28) -> 0 | AS28: =合并调整抵消分录!T20 -> 0 | AT28: =合并调整抵消分录!U20 -> 0 | AU28: =AR28+AS28-AT28 -> 0 | AV28: =VLOOKUP(A28,合并资产负债表!$A$6:$C$87,3,0) -> #N/A | AW28: =K28-AV28 -> #N/A
A29: 其他流动资产 | B29: =VLOOKUP(A29,快速BS新!A$6:C$212,3,0)+快速BS新!C25 -> 2908777.3 | C29: =VLOOKUP(A29,新材料BS新!$A$4:$D$191,3,0)+新材料BS新!C21 -> 526300.76 | D29: =VLOOKUP(A29,精铸BS新!$A$6:$C$86,3,0)+精铸BS新!C25 -> 30771.11 | E29: =VLOOKUP(A29,热等静压BS新!$A$6:$C$86,3,0)+热等静压BS新!C22 -> 159221.08 | H29: =SUM(B29:G29) -> 3625070.3 | I29: =合并调整抵消分录!E21 -> 0 | J29: =合并调整抵消分录!F21 -> 0 | K29: =H29+I29-J29 -> 3625070.3 | L29: 99880.84 | M29: 117873.86 | N29: 0 | O29: 840368.37 | R29: =SUM(L29:Q29) -> 1058123.1 | S29: 0 | T29: 0 | U29: =R29+S29-T29 -> 1058123.1 | V29: 10188421 | W29: 74229.85 | Z29: =[6]TB子公司4!M28 -> 0 | AA29: =[6]TB子公司5!M28 -> 0 | AB29: =SUM(V29:AA29) -> 10262651 | AC29: =合并调整抵消分录!N21 -> 0 | AD29: =合并调整抵消分录!O21 -> 0 | AE29: =AB29+AC29-AD29 -> 10262651 | AL29: =SUM(AF29:AK29) -> 0 | AM29: =合并调整抵消分录!Q21 -> 0 | AN29: =合并调整抵消分录!R21 -> 0 | AO29: =AL29+AM29-AN29 -> 0 | AR29: =SUM(AP29:AQ29) -> 0 | AS29: =合并调整抵消分录!T21 -> 0 | AT29: =合并调整抵消分录!U21 -> 0 | AU29: =AR29+AS29-AT29 -> 0 | AV29: =VLOOKUP(A29,合并资产负债表!$A$6:$C$87,3,0) -> #N/A | AW29: =K29-AV29 -> #N/A
A30: 流动资产合计 | B30: =SUM(B9:B29) -> 1.1209745e+08 | C30: =SUM(C9:C29) -> 2.3285033e+08 | D30: =SUM(D9:D29) -> 19007841 | E30: =SUM(E9:E29) -> 25203112 | F30: =SUM(F9:F29) -> 0 | G30: =SUM(G9:G29) -> 0 | H30: =SUM(H9:H29) -> 3.8915873e+08 | I30: =SUM(I9:I29) -> 0 | ... K30: =SUM(K9:K29) -> 3.0541432e+08 | L30: 97239762 | M30: 1.8553352e+08 | N30: 16711630 | O30: 22555611 | P30: =SUM(P9:P29) -> 0 | Q30: =SUM(Q9:Q29) -> 0 | R30: =SUM(R9:R29) -> 3.2204053e+08 | S30: 0 | T30: 63459551 | U30: =SUM(U9:U29) -> 2.5858098e+08 | V30: 1.3906536e+08 | W30: 12708075 | X30: 11222590 | Z30: =SUM(Z9:Z29) -> 0 | AA30: =SUM(AA9:AA29) -> 0 | AB30: =SUM(AB9:AB29) -> 1.6299603e+08 | AC30: =SUM(AC9:AC29) -> 0 | AD30: =SUM(AD9:AD29) -> 6436846.2 | AE30: =SUM(AE9:AE29) -> 1.5655918e+08 | AL30: =SUM(AL9:AL29) -> 0 | AM30: =SUM(AM9:AM29) -> 0 | AN30: =SUM(AN9:AN29) -> 0 | AO30: =SUM(AO9:AO29) -> 0 | AR30: =SUM(AR9:AR29) -> 0 | AS30: =SUM(AS9:AS29) -> 0 | AT30: =SUM(AT9:AT29) -> 0 | AU30: =SUM(AU9:AU29) -> 0 | AV30: =VLOOKUP(A30,合并资产负债表!$A$6:$C$87,3,0) -> 1.6861249e+08 | AW30: =K30-AV30 -> 1.3680183e+08
A31: 非流动资产 | AW31: =K31-AV31 -> 0
A32: △发放贷款及垫款 | H32: =SUM(B32:G32) -> 0 | I32: =合并调整抵消分录!E22 -> 0 | J32: =合并调整抵消分录!F22 -> 0 | K32: =H32+I32-J32 -> 0 | R32: =SUM(L32:Q32) -> 0 | S32: 0 | T32: 0 | U32: =R32+S32-T32 -> 0 | Z32: =[6]TB子公司4!M31 -> 0 | AA32: =[6]TB子公司5!M31 -> 0 | AB32: =SUM(V32:AA32) -> 0 | AC32: =合并调整抵消分录!N22 -> 0 | AD32: =合并调整抵消分录!O22 -> 0 | AE32: =AB32+AC32-AD32 -> 0 | AL32: =SUM(AF32:AK32) -> 0 | AM32: =合并调整抵消分录!Q22 -> 0 | AN32: =合并调整抵消分录!R22 -> 0 | AO32: =AL32+AM32-AN32 -> 0 | AR32: =SUM(AP32:AQ32) -> 0 | AS32: =合并调整抵消分录!T22 -> 0 | AT32: =合并调整抵消分录!U22 -> 0 | AU32: =AR32+AS32-AT32 -> 0 | AW32: =K32-AV32 -> 0
A33: 可供出售金融资产 | H33: =SUM(B33:G33) -> 0 | I33: =合并调整抵消分录!E23 -> 0 | J33: =合并调整抵消分录!F23 -> 0 | K33: =H33+I33-J33 -> 0 | R33: =SUM(L33:Q33) -> 0 | S33: 0 | T33: 0 | U33: =R33+S33-T33 -> 0 | Z33: =[6]TB子公司4!M32 -> 0 | AA33: =[6]TB子公司5!M32 -> 0 | AB33: =SUM(V33:AA33) -> 0 | AC33: =合并调整抵消分录!N23 -> 0 | AD33: =合并调整抵消分录!O23 -> 0 | AE33: =AB33+AC33-AD33 -> 0 | AL33: =SUM(AF33:AK33) -> 0 | AM33: =合并调整抵消分录!Q23 -> 0 | AN33: =合并调整抵消分录!R23 -> 0 | AO33: =AL33+AM33-AN33 -> 0 | AR33: =SUM(AP33:AQ33) -> 0 | AS33: =合并调整抵消分录!T23 -> 0 | AT33: =合并调整抵消分录!U23 -> 0 | AU33: =AR33+AS33-AT33 -> 0 | AV33: =VLOOKUP(A33,合并资产负债表!$A$6:$C$87,3,0) -> 0 | AW33: =K33-AV33 -> 0
A34: 持有至到期投资 | H34: =SUM(B34:G34) -> 0 | I34: =合并调整抵消分录!E24 -> 0 | J34: =合并调整抵消分录!F24 -> 0 | K34: =H34+I34-J34 -> 0 | R34: =SUM(L34:Q34) -> 0 | S34: 0 | T34: 0 | U34: =R34+S34-T34 -> 0 | Z34: =[6]TB子公司4!M33 -> 0 | AA34: =[6]TB子公司5!M33 -> 0 | AB34: =SUM(V34:AA34) -> 0 | AC34: =合并调整抵消分录!N24 -> 0 | AD34: =合并调整抵消分录!O24 -> 0 | AE34: =AB34+AC34-AD34 -> 0 | AL34: =SUM(AF34:AK34) -> 0 | AM34: =合并调整抵消分录!Q24 -> 0 | AN34: =合并调整抵消分录!R24 -> 0 | AO34: =AL34+AM34-AN34 -> 0 | AR34: =SUM(AP34:AQ34) -> 0 | AS34: =合并调整抵消分录!T24 -> 0 | AT34: =合并调整抵消分录!U24 -> 0 | AU34: =AR34+AS34-AT34 -> 0 | AV34: =VLOOKUP(A34,合并资产负债表!$A$6:$C$87,3,0) -> 0 | AW34: =K34-AV34 -> 0
A35: 长期应收款 | B35: =VLOOKUP(A35,快速BS新!A$6:C$212,3,0) -> 0 | C35: =VLOOKUP(A35,新材料BS新!$A$4:$D$191,3,0) -> 0 | D35: =VLOOKUP(A35,精铸BS新!$A$6:$C$86,3,0) -> 0 | E35: =VLOOKUP(A35,热等静压BS新!$A$6:$C$86,3,0) -> 0 | H35: =SUM(B35:G35) -> 0 | I35: =合并调整抵消分录!E25 -> 0 | J35: =合并调整抵消分录!F25 -> 0 | K35: =H35+I35-J35 -> 0 | L35: 0 | M35: 0 | N35: 0 | O35: 0 | P35: =[6]TB子公司4!I34 -> 0 | Q35: =[6]TB子公司5!I34 -> 0 | R35: =SUM(L35:Q35) -> 0 | S35: 0 | T35: 0 | U35: =R35+S35-T35 -> 0 | V35: 0 | W35: 0 | X35: 0 | Z35: =[6]TB子公司4!M34 -> 0 | AA35: =[6]TB子公司5!M34 -> 0 | AB35: =SUM(V35:AA35) -> 0 | AC35: =合并调整抵消分录!N25 -> 0 | AD35: =合并调整抵消分录!O25 -> 0 | AE35: =AB35+AC35-AD35 -> 0 | AL35: =SUM(AF35:AK35) -> 0 | AM35: =合并调整抵消分录!Q25 -> 0 | AN35: =合并调整抵消分录!R25 -> 0 | AO35: =AL35+AM35-AN35 -> 0 | AR35: =SUM(AP35:AQ35) -> 0 | AS35: =合并调整抵消分录!T25 -> 0 | AT35: =合并调整抵消分录!U25 -> 0 | AU35: =AR35+AS35-AT35 -> 0 | AV35: =VLOOKUP(A35,合并资产负债表!$A$6:$C$87,3,0) -> #N/A | AW35: =K35-AV35 -> #N/A
A36: 长期股权投资 | B36: =VLOOKUP(A36,快速BS新!A$6:C$212,3,0) -> 2.6042899e+08 | C36: =VLOOKUP(A36,新材料BS新!$A$4:$D$191,3,0) -> 0 | D36: =VLOOKUP(A36,精铸BS新!$A$6:$C$86,3,0) -> 0 | E36: =VLOOKUP(A36,热等静压BS新!$A$6:$C$86,3,0) -> 0 | H36: =SUM(B36:G36) -> 2.6042899e+08 | I36: =合并调整抵消分录!E26 -> -14518786 | J36: =合并调整抵消分录!F26 -> 2.4591021e+08 | K36: =H36+I36-J36 -> 0 | L36: 2.6042899e+08 | M36: 0 | N36: 0 | O36: 0 | P36: =[6]TB子公司4!I35 -> 0 | Q36: =[6]TB子公司5!I35 -> 0 | R36: =SUM(L36:Q36) -> 2.6042899e+08 | S36: -9951097.7 | T36: 2.5047789e+08 | U36: =R36+S36-T36 -> 0 | V36: 32000000 | W36: 0 | X36: 0 | Z36: =[6]TB子公司4!M35 -> 0 | AA36: =[6]TB子公司5!M35 -> 0 | AB36: =SUM(V36:AA36) -> 32000000 | AC36: =合并调整抵消分录!N26 -> 1626803.3 | AD36: =合并调整抵消分录!O26 -> 35385058 | AE36: =AB36+AC36-AD36 -> -1758254.9 | AL36: =SUM(AF36:AK36) -> 0 | AM36: =合并调整抵消分录!Q26 -> 0 | AN36: =合并调整抵消分录!R26 -> 0 | AO36: =AL36+AM36-AN36 -> 0 | AR36: =SUM(AP36:AQ36) -> 0 | AS36: =合并调整抵消分录!T26 -> 0 | AT36: =合并调整抵消分录!U26 -> 0 | AU36: =AR36+AS36-AT36 -> 0 | AV36: =VLOOKUP(A36,合并资产负债表!$A$6:$C$87,3,0) -> #N/A | AW36: =K36-AV36 -> #N/A
A37: 其他权益工具投资 | H37: =SUM(B37:G37) -> 0 | K37: =H37+I37-J37 -> 0 | R37: =SUM(L37:Q37) -> 0 | U37: =R37+S37-T37 -> 0
A38: 其他非流动金融资产 | B38: =VLOOKUP(A38,快速BS新!A$6:C$212,3,0) -> 3000000 | C38: =VLOOKUP(A38,新材料BS新!$A$4:$D$191,3,0) -> 0 | D38: =VLOOKUP(A38,精铸BS新!$A$6:$C$86,3,0) -> 0 | E38: =VLOOKUP(A38,热等静压BS新!$A$6:$C$86,3,0) -> 0 | H38: =SUM(B38:G38) -> 3000000 | K38: =H38+I38-J38 -> 3000000 | L38: 17507066 | M38: 0 | N38: 0 | O38: 0 | R38: =SUM(L38:Q38) -> 17507066 | U38: =R38+S38-T38 -> 17507066
A39: 投资性房地产 | B39: =VLOOKUP(A39,快速BS新!A$6:C$212,3,0) -> 0 | C39: =VLOOKUP(A39,新材料BS新!$A$4:$D$191,3,0) -> 0 | D39: =VLOOKUP(A39,精铸BS新!$A$6:$C$86,3,0) -> 0 | E39: =VLOOKUP(A39,热等静压BS新!$A$6:$C$86,3,0) -> 0 | H39: =SUM(B39:G39) -> 0 | I39: =合并调整抵消分录!E27 -> 0 | J39: =合并调整抵消分录!F27 -> 0 | K39: =H39+I39-J39 -> 0 | L39: 0 | M39: 0 | N39: 0 | O39: 0 | P39: =[6]TB子公司4!I36 -> 0 | Q39: =[6]TB子公司5!I36 -> 0 | R39: =SUM(L39:Q39) -> 0 | S39: 0 | T39: 0 | U39: =R39+S39-T39 -> 0 | V39: 0 | W39: 0 | X39: 0 | Z39: =[6]TB子公司4!M36 -> 0 | AA39: =[6]TB子公司5!M36 -> 0 | AB39: =SUM(V39:AA39) -> 0 | AC39: =合并调整抵消分录!N27 -> 0 | AD39: =合并调整抵消分录!O27 -> 0 | AE39: =AB39+AC39-AD39 -> 0 | AL39: =SUM(AF39:AK39) -> 0 | AM39: =合并调整抵消分录!Q27 -> 0 | AN39: =合并调整抵消分录!R27 -> 0 | AO39: =AL39+AM39-AN39 -> 0 | AR39: =SUM(AP39:AQ39) -> 0 | AS39: =合并调整抵消分录!T27 -> 0 | AT39: =合并调整抵消分录!U27 -> 0 | AU39: =AR39+AS39-AT39 -> 0 | AV39: =VLOOKUP(A39,合并资产负债表!$A$6:$C$87,3,0) -> #N/A | AW39: =K39-AV39 -> #N/A
A40: 固定资产 | B40: =VLOOKUP(A40,快速BS新!A$6:C$212,3,0) -> 1.4427001e+08 | C40: =VLOOKUP(A40,新材料BS新!$A$4:$D$191,3,0) -> 1.9551608e+08 | D40: =VLOOKUP(A40,精铸BS新!$A$6:$C$86,3,0) -> 10718249 | E40: =VLOOKUP(A40,热等静压BS新!$A$6:$C$86,3,0) -> 13257298 | H40: =SUM(B40:G40) -> 3.6376163e+08 | I40: =合并调整抵消分录!E28 -> 0 | J40: =合并调整抵消分录!F28 -> 0 | K40: =H40+I40-J40 -> 3.6376163e+08 | L40: 1.3110889e+08 | M40: 1.8978847e+08 | N40: 9940107.8 | O40: 13249688 | R40: =SUM(L40:Q40) -> 3.4408716e+08 | S40: 0 | T40: 0 | U40: =R40+S40-T40 -> 3.4408716e+08 | V40: 1.164069e+08 | W40: 12609489 | X40: 9718700.1 | Z40: =[6]TB子公司4!M37 -> 0 | AA40: =[6]TB子公司5!M37 -> 0 | AB40: =SUM(V40:AA40) -> 1.3873509e+08 | AC40: =合并调整抵消分录!N28 -> 0 | AD40: =合并调整抵消分录!O28 -> 0 | AE40: =AB40+AC40-AD40 -> 1.3873509e+08 | AL40: =SUM(AF40:AK40) -> 0 | AM40: =合并调整抵消分录!Q28 -> 0 | AN40: =合并调整抵消分录!R28 -> 0 | AO40: =AL40+AM40-AN40 -> 0 | AR40: =SUM(AP40:AQ40) -> 0 | AS40: =合并调整抵消分录!T28 -> 0 | AT40: =合并调整抵消分录!U28 -> 0 | AU40: =AR40+AS40-AT40 -> 0 | AV40: =VLOOKUP(A40,合并资产负债表!$A$6:$C$87,3,0) -> #N/A | AW40: =K40-AV40 -> #N/A
A41: 减:累计折旧 | B41: =VLOOKUP(A41,快速BS新!A$6:C$212,3,0) -> 76500620 | C41: =VLOOKUP(A41,新材料BS新!$A$4:$D$191,3,0) -> 72041900 | D41: =VLOOKUP(A41,精铸BS新!$A$6:$C$86,3,0) -> 7759467.6 | E41: =VLOOKUP(A41,热等静压BS新!$A$6:$C$86,3,0) -> 12207474 | H41: =SUM(B41:G41) -> 1.6850946e+08 | I41: =合并调整抵消分录!E29 -> 0 | J41: =合并调整抵消分录!F29 -> 0 | K41: =H41-I41+J41 -> 1.6850946e+08 | L41: 69959453 | M41: 54713218 | N41: 7258587.8 | O41: 11071925 | R41: =SUM(L41:Q41) -> 1.4300318e+08 | S41: 0 | T41: 0 | U41: =R41-S41+T41 -> 1.4300318e+08 | V41: 44249259 | W41: 5464669.2 | X41: 3790504.5 | Z41: =[6]TB子公司4!M38 -> 0 | AA41: =[6]TB子公司5!M38 -> 0 | AB41: =SUM(V41:AA41) -> 53504432 | AC41: =合并调整抵消分录!N29 -> 0 | AD41: =合并调整抵消分录!O29 -> 0 | AE41: =AB41-AC41+AD41 -> 53504432 | AL41: =SUM(AF41:AK41) -> 0 | AM41: =合并调整抵消分录!Q29 -> 0 | AN41: =合并调整抵消分录!R29 -> 0 | AO41: =AL41-AM41+AN41 -> 0 | AR41: =SUM(AP41:AQ41) -> 0 | AS41: =合并调整抵消分录!T29 -> 0 | AT41: =合并调整抵消分录!U29 -> 0 | AU41: =AR41-AS41+AT41 -> 0 | AV41: =VLOOKUP(A41,合并资产负债表!$A$6:$C$87,3,0) -> #N/A | AW41: =K41-AV41 -> #N/A
A42: 固定资产净值 | B42: =B40-B41 -> 67769387 | C42: =C40-C41 -> 1.2347418e+08 | D42: =D40-D41 -> 2958781.8 | E42: =E40-E41 -> 1049823.7 | F42: =F40-F41 -> 0 | G42: =G40-G41 -> 0 | H42: =H40-H41 -> 1.9525217e+08 | I42: =I40-I41 -> 0 | ... K42: =K40-K41 -> 1.9525217e+08 | L42: 61149434 | M42: 1.3507526e+08 | N42: 2681520 | O42: 2177762.4 | P42: =P40-P41 -> 0 | Q42: =Q40-Q41 -> 0 | R42: =R40-R41 -> 2.0108397e+08 | S42: 0 | T42: 0 | U42: =U40-U41 -> 2.0108397e+08 | V42: 72157645 | W42: 7144819.9 | X42: 5928195.6 | Y42: =Y40-Y41 -> 0 | Z42: =Z40-Z41 -> 0 | AA42: =AA40-AA41 -> 0 | AB42: =AB40-AB41 -> 85230661 | AC42: =AC40-AC41 -> 0 | AD42: =AD40-AD41 -> 0 | AE42: =AE40-AE41 -> 85230661 | AF42: =AF40-AF41 -> 0 | ... AO42: =AO40-AO41 -> 0 | AR42: =AR40-AR41 -> 0 | AS42: =AS40-AS41 -> 0 | AT42: =AT40-AT41 -> 0 | AU42: =AU40-AU41 -> 0 | AV42: =VLOOKUP(A42,合并资产负债表!$A$6:$C$87,3,0) -> #N/A | AW42: =K42-AV42 -> #N/A
A43: 减：固定资产减值准备 | H43: =SUM(B43:G43) -> 0 | I43: =合并调整抵消分录!E30 -> 0 | J43: =合并调整抵消分录!F30 -> 0 | K43: =H43+I43-J43 -> 0 | R43: =SUM(L43:Q43) -> 0 | S43: 0 | T43: 0 | U43: =R43+S43-T43 -> 0 | Y43: ='[7]VT德国-人民币'!$M$40 -> 0 | Z43: =[6]TB子公司4!M40 -> 0 | AA43: =[6]TB子公司5!M40 -> 0 | AB43: =SUM(V43:AA43) -> 0 | AC43: =合并调整抵消分录!N30 -> 0 | AD43: =合并调整抵消分录!O30 -> 0 | AE43: =AB43+AC43-AD43 -> 0 | AF43: =[8]无锡威唐TB!$Q$40 -> 0 | AG43: =[9]芜湖威唐TB!$Q$40 -> 0 | AH43: =[10]威唐沃伦TB!$Q$40 -> 0 | AI43: ='[7]VT德国-人民币'!$Q$40 -> 0 | AJ43: =[6]TB子公司4!Q40 -> 0 | AK43: =[6]TB子公司5!Q40 -> 0 | AL43: =SUM(AF43:AK43) -> 0 | AM43: =合并调整抵消分录!Q30 -> 0 | AN43: =合并调整抵消分录!R30 -> 0 | AO43: =AL43+AM43-AN43 -> 0 | AR43: =SUM(AP43:AQ43) -> 0 | AS43: =合并调整抵消分录!T30 -> 0 | AT43: =合并调整抵消分录!U30 -> 0 | AU43: =AR43+AS43-AT43 -> 0 | AW43: =K43-AV43 -> 0
A44: 固定资产净额 | B44: =B42-B43 -> 67769387 | C44: =C42-C43 -> 1.2347418e+08 | D44: =D42-D43 -> 2958781.8 | E44: =E42-E43 -> 1049823.7 | F44: =F42-F43 -> 0 | G44: =G42-G43 -> 0 | H44: =H42-H43 -> 1.9525217e+08 | I44: =I42-I43 -> 0 | ... K44: =K42-K43 -> 1.9525217e+08 | L44: 61149434 | M44: 1.3507526e+08 | N44: 2681520 | O44: 2177762.4 | P44: =P42-P43 -> 0 | Q44: =Q42-Q43 -> 0 | R44: =R42-R43 -> 2.0108397e+08 | S44: 0 | T44: 0 | U44: =U42-U43 -> 2.0108397e+08 | V44: 72157645 | W44: 7144819.9 | X44: 5928195.6 | Y44: =Y42-Y43 -> 0 | Z44: =Z42-Z43 -> 0 | AA44: =AA42-AA43 -> 0 | AB44: =AB42-AB43 -> 85230661 | AC44: =AC42-AC43 -> 0 | AD44: =AD42-AD43 -> 0 | AE44: =AE42-AE43 -> 85230661 | AF44: =AF42-AF43 -> 0 | ... AO44: =AO42-AO43 -> 0 | AR44: =AR42-AR43 -> 0 | AS44: =AS42-AS43 -> 0 | AT44: =AT42-AT43 -> 0 | AU44: =AU42-AU43 -> 0 | AV44: =AV42 -> #N/A | AW44: =K44-AV44 -> #N/A
A45: 在建工程 | B45: =VLOOKUP(A45,快速BS新!A$6:C$212,3,0) -> 31434621 | C45: =VLOOKUP(A45,新材料BS新!$A$4:$D$191,3,0) -> 11228638 | D45: =VLOOKUP(A45,精铸BS新!$A$6:$C$86,3,0) -> 0 | E45: =VLOOKUP(A45,热等静压BS新!$A$6:$C$86,3,0) -> 0 | H45: =SUM(B45:G45) -> 42663260 | I45: =合并调整抵消分录!E31 -> 0 | J45: =合并调整抵消分录!F31 -> 0 | K45: =H45+I45-J45 -> 42663260 | L45: 3109954.1 | M45: 8203362.6 | N45: 0 | O45: 0 | R45: =SUM(L45:Q45) -> 11313317 | S45: 0 | T45: 0 | U45: =R45+S45-T45 -> 11313317 | V45: 78526307 | AB45: =SUM(V45:AA45) -> 78526307 | AC45: =合并调整抵消分录!N31 -> 0 | AD45: =合并调整抵消分录!O31 -> 0 | AE45: =AB45+AC45-AD45 -> 78526307 | AL45: =SUM(AF45:AK45) -> 0 | AM45: =合并调整抵消分录!Q31 -> 0 | AN45: =合并调整抵消分录!R31 -> 0 | AO45: =AL45+AM45-AN45 -> 0 | AR45: =SUM(AP45:AQ45) -> 0 | AS45: =合并调整抵消分录!T31 -> 0 | AT45: =合并调整抵消分录!U31 -> 0 | AU45: =AR45+AS45-AT45 -> 0 | AV45: =VLOOKUP(A45,合并资产负债表!$A$6:$C$87,3,0) -> #N/A | AW45: =K45-AV45 -> #N/A
A46: 工程物资 | B46: =VLOOKUP(A46,快速BS!A$6:D$212,4,0) -> 0 | C46: =VLOOKUP(A46,新材料BS!$A$6:$D$328,4,0) -> 0 | D46: =VLOOKUP(A46,精铸BS!$A$6:$C$86,3,0) -> 0 | E46: =VLOOKUP(A46,热等静压BS!$A$6:$C$86,3,0) -> 0 | H46: =SUM(B46:G46) -> 0 | I46: =合并调整抵消分录!E32 -> 0 | J46: =合并调整抵消分录!F32 -> 0 | K46: =H46+I46-J46 -> 0 | L46: 0 | M46: 0 | N46: 0 | O46: 0 | R46: =SUM(L46:Q46) -> 0 | S46: 0 | T46: 0 | U46: =R46+S46-T46 -> 0 | AB46: =SUM(V46:AA46) -> 0 | AC46: =合并调整抵消分录!N32 -> 0 | AD46: =合并调整抵消分录!O32 -> 0 | AE46: =AB46+AC46-AD46 -> 0 | AL46: =SUM(AF46:AK46) -> 0 | AM46: =合并调整抵消分录!Q32 -> 0 | AN46: =合并调整抵消分录!R32 -> 0 | AO46: =AL46+AM46-AN46 -> 0 | AR46: =SUM(AP46:AQ46) -> 0 | AS46: =合并调整抵消分录!T32 -> 0 | AT46: =合并调整抵消分录!U32 -> 0 | AU46: =AR46+AS46-AT46 -> 0 | AV46: =VLOOKUP(A46,合并资产负债表!$A$6:$C$87,3,0) -> 0 | AW46: =K46-AV46 -> 0
A47: 固定资产清理 | B47: =VLOOKUP(A47,快速BS新!A$6:C$212,3,0) -> 0 | C47: =VLOOKUP(A47,新材料BS新!$A$4:$D$191,3,0) -> 0 | D47: =VLOOKUP(A47,精铸BS新!$A$6:$C$86,3,0) -> 0 | E47: =VLOOKUP(A47,热等静压BS新!$A$6:$C$86,3,0) -> 0 | H47: =SUM(B47:G47) -> 0 | I47: =合并调整抵消分录!E33 -> 0 | J47: =合并调整抵消分录!F33 -> 0 | K47: =H47+I47-J47 -> 0 | L47: 0 | M47: 0 | N47: 0 | O47: 0 | R47: =SUM(L47:Q47) -> 0 | S47: 0 | T47: 0 | U47: =R47+S47-T47 -> 0 | AB47: =SUM(V47:AA47) -> 0 | AC47: =合并调整抵消分录!N33 -> 0 | AD47: =合并调整抵消分录!O33 -> 0 | AE47: =AB47+AC47-AD47 -> 0 | AL47: =SUM(AF47:AK47) -> 0 | AM47: =合并调整抵消分录!Q33 -> 0 | AN47: =合并调整抵消分录!R33 -> 0 | AO47: =AL47+AM47-AN47 -> 0 | AR47: =SUM(AP47:AQ47) -> 0 | AS47: =合并调整抵消分录!T33 -> 0 | AT47: =合并调整抵消分录!U33 -> 0 | AU47: =AR47+AS47-AT47 -> 0 | AV47: =VLOOKUP(A47,合并资产负债表!$A$6:$C$87,3,0) -> #N/A | AW47: =K47-AV47 -> #N/A
A48: 生产性生物资产 | B48: =VLOOKUP(A48,快速BS!A$6:D$212,4,0) -> 0 | C48: =VLOOKUP(A48,新材料BS!$A$6:$D$328,4,0) -> 0 | D48: =VLOOKUP(A48,精铸BS!$A$6:$C$86,3,0) -> 0 | E48: =VLOOKUP(A48,热等静压BS!$A$6:$C$86,3,0) -> 0 | H48: =SUM(B48:G48) -> 0 | I48: =合并调整抵消分录!E34 -> 0 | J48: =合并调整抵消分录!F34 -> 0 | K48: =H48+I48-J48 -> 0 | L48: 0 | M48: 0 | N48: 0 | O48: 0 | R48: =SUM(L48:Q48) -> 0 | S48: 0 | T48: 0 | U48: =R48+S48-T48 -> 0 | AB48: =SUM(V48:AA48) -> 0 | AC48: =合并调整抵消分录!N34 -> 0 | AD48: =合并调整抵消分录!O34 -> 0 | AE48: =AB48+AC48-AD48 -> 0 | AL48: =SUM(AF48:AK48) -> 0 | AM48: =合并调整抵消分录!Q34 -> 0 | AN48: =合并调整抵消分录!R34 -> 0 | AO48: =AL48+AM48-AN48 -> 0 | AR48: =SUM(AP48:AQ48) -> 0 | AS48: =合并调整抵消分录!T34 -> 0 | AT48: =合并调整抵消分录!U34 -> 0 | AU48: =AR48+AS48-AT48 -> 0 | AV48: =VLOOKUP(A48,合并资产负债表!$A$6:$C$87,3,0) -> 0 | AW48: =K48-AV48 -> 0
A49: 油气资产 | B49: =VLOOKUP(A49,快速BS!A$6:D$212,4,0) -> 0 | C49: =VLOOKUP(A49,新材料BS!$A$6:$D$328,4,0) -> 0 | D49: =VLOOKUP(A49,精铸BS!$A$6:$C$86,3,0) -> 0 | E49: =VLOOKUP(A49,热等静压BS!$A$6:$C$86,3,0) -> 0 | H49: =SUM(B49:G49) -> 0 | I49: =合并调整抵消分录!E35 -> 0 | J49: =合并调整抵消分录!F35 -> 0 | K49: =H49+I49-J49 -> 0 | L49: 0 | M49: 0 | N49: 0 | O49: 0 | R49: =SUM(L49:Q49) -> 0 | S49: 0 | T49: 0 | U49: =R49+S49-T49 -> 0 | AB49: =SUM(V49:AA49) -> 0 | AC49: =合并调整抵消分录!N35 -> 0 | AD49: =合并调整抵消分录!O35 -> 0 | AE49: =AB49+AC49-AD49 -> 0 | AL49: =SUM(AF49:AK49) -> 0 | AM49: =合并调整抵消分录!Q35 -> 0 | AN49: =合并调整抵消分录!R35 -> 0 | AO49: =AL49+AM49-AN49 -> 0 | AR49: =SUM(AP49:AQ49) -> 0 | AS49: =合并调整抵消分录!T35 -> 0 | AT49: =合并调整抵消分录!U35 -> 0 | AU49: =AR49+AS49-AT49 -> 0 | AV49: =VLOOKUP(A49,合并资产负债表!$A$6:$C$87,3,0) -> 0 | AW49: =K49-AV49 -> 0
A50: 无形资产 | B50: =VLOOKUP(A50,快速BS新!A$6:C$212,3,0) -> 11601524 | C50: =VLOOKUP(A50,新材料BS新!$A$4:$D$191,3,0) -> 1410354 | D50: =VLOOKUP(A50,精铸BS新!$A$6:$C$86,3,0) -> 0 | E50: =VLOOKUP(A50,热等静压BS新!$A$6:$C$86,3,0) -> 0 | H50: =SUM(B50:G50) -> 13011878 | I50: =合并调整抵消分录!E36 -> 0 | J50: =合并调整抵消分录!F36 -> 0 | K50: =H50+I50-J50 -> 13011878 | L50: 11984001 | M50: 1139469.2 | N50: 0 | O50: 0 | R50: =SUM(L50:Q50) -> 13123470 | S50: 0 | T50: 0 | U50: =R50+S50-T50 -> 13123470 | V50: 13333091 | W50: 0 | X50: 0 | AB50: =SUM(V50:AA50) -> 13333091 | AC50: =合并调整抵消分录!N36 -> 0 | AD50: =合并调整抵消分录!O36 -> 0 | AE50: =AB50+AC50-AD50 -> 13333091 | AL50: =SUM(AF50:AK50) -> 0 | AM50: =合并调整抵消分录!Q36 -> 0 | AN50: =合并调整抵消分录!R36 -> 0 | AO50: =AL50+AM50-AN50 -> 0 | AR50: =SUM(AP50:AQ50) -> 0 | AS50: =合并调整抵消分录!T36 -> 0 | AT50: =合并调整抵消分录!U36 -> 0 | AU50: =AR50+AS50-AT50 -> 0 | AV50: =VLOOKUP(A50,合并资产负债表!$A$6:$C$87,3,0) -> #N/A | AW50: =K50-AV50 -> #N/A
A51: 开发支出 | B51: =VLOOKUP(A51,快速BS新!A$6:C$212,3,0) -> 0 | C51: =VLOOKUP(A51,新材料BS新!$A$4:$D$191,3,0) -> 0 | D51: =VLOOKUP(A51,精铸BS新!$A$6:$C$86,3,0) -> 0 | E51: =VLOOKUP(A51,热等静压BS新!$A$6:$C$86,3,0) -> 0 | H51: =SUM(B51:G51) -> 0 | I51: =合并调整抵消分录!E37 -> 0 | J51: =合并调整抵消分录!F37 -> 0 | K51: =H51+I51-J51 -> 0 | L51: 0 | M51: 0 | N51: 0 | O51: 0 | R51: =SUM(L51:Q51) -> 0 | S51: 0 | T51: 0 | U51: =R51+S51-T51 -> 0 | V51: 0 | W51: 0 | X51: 0 | AB51: =SUM(V51:AA51) -> 0 | AC51: =合并调整抵消分录!N37 -> 0 | AD51: =合并调整抵消分录!O37 -> 0 | AE51: =AB51+AC51-AD51 -> 0 | AL51: =SUM(AF51:AK51) -> 0 | AM51: =合并调整抵消分录!Q37 -> 0 | AN51: =合并调整抵消分录!R37 -> 0 | AO51: =AL51+AM51-AN51 -> 0 | AR51: =SUM(AP51:AQ51) -> 0 | AS51: =合并调整抵消分录!T37 -> 0 | AT51: =合并调整抵消分录!U37 -> 0 | AU51: =AR51+AS51-AT51 -> 0 | AV51: =VLOOKUP(A51,合并资产负债表!$A$6:$C$87,3,0) -> #N/A | AW51: =K51-AV51 -> #N/A
A52: 商誉 | B52: =VLOOKUP(A52,快速BS新!A$6:C$212,3,0) -> 0 | C52: =VLOOKUP(A52,新材料BS新!$A$4:$D$191,3,0) -> 0 | D52: =VLOOKUP(A52,精铸BS新!$A$6:$C$86,3,0) -> 0 | E52: =VLOOKUP(A52,热等静压BS新!$A$6:$C$86,3,0) -> 0 | H52: =SUM(B52:G52) -> 0 | I52: =合并调整抵消分录!E38 -> 6070777.8 | J52: =合并调整抵消分录!F38 -> 2027402.3 | K52: =H52+I52-J52 -> 4043375.5 | L52: 0 | M52: 0 | N52: 0 | O52: 0 | R52: =SUM(L52:Q52) -> 0 | S52: 6070777.8 | T52: 1259075.9 | U52: =R52+S52-T52 -> 4811701.9 | V52: 0 | W52: 0 | X52: 0 | AB52: =SUM(V52:AA52) -> 0 | AC52: =合并调整抵消分录!N38 -> 6070777.8 | AD52: =合并调整抵消分录!O38 -> 0 | AE52: =AB52+AC52-AD52 -> 6070777.8 | AL52: =SUM(AF52:AK52) -> 0 | AM52: =合并调整抵消分录!Q38 -> 0 | AN52: =合并调整抵消分录!R38 -> 0 | AO52: =AL52+AM52-AN52 -> 0 | AR52: =SUM(AP52:AQ52) -> 0 | AS52: =合并调整抵消分录!T38 -> 0 | AT52: =合并调整抵消分录!U38 -> 0 | AU52: =AR52+AS52-AT52 -> 0 | AV52: =VLOOKUP(A52,合并资产负债表!$A$6:$C$87,3,0) -> #N/A | AW52: =K52-AV52 -> #N/A
A53: 长期待摊费用 | B53: =VLOOKUP(A53,快速BS新!A$6:C$212,3,0) -> 2442357.9 | C53: =VLOOKUP(A53,新材料BS新!$A$4:$D$191,3,0) -> 516811.09 | D53: =VLOOKUP(A53,精铸BS新!$A$6:$C$86,3,0) -> 0 | E53: =VLOOKUP(A53,热等静压BS新!$A$6:$C$86,3,0) -> 300945.95 | H53: =SUM(B53:G53) -> 3260115 | I53: =合并调整抵消分录!E39 -> 0 | J53: =合并调整抵消分录!F39 -> 0 | K53: =H53+I53-J53 -> 3260115 | L53: 3654561.2 | M53: 654922.6 | N53: 0 | O53: 532167.82 | R53: =SUM(L53:Q53) -> 4841651.7 | S53: 0 | T53: 0 | U53: =R53+S53-T53 -> 4841651.7 | V53: 0 | W53: 33898.66 | X53: 274315.54 | AB53: =SUM(V53:AA53) -> 308214.2 | AC53: =合并调整抵消分录!N39 -> 0 | AD53: =合并调整抵消分录!O39 -> 0 | AE53: =AB53+AC53-AD53 -> 308214.2 | AL53: =SUM(AF53:AK53) -> 0 | AM53: =合并调整抵消分录!Q39 -> 0 | AN53: =合并调整抵消分录!R39 -> 0 | AO53: =AL53+AM53-AN53 -> 0 | AR53: =SUM(AP53:AQ53) -> 0 | AS53: =合并调整抵消分录!T39 -> 0 | AT53: =合并调整抵消分录!U39 -> 0 | AU53: =AR53+AS53-AT53 -> 0 | AV53: =VLOOKUP(A53,合并资产负债表!$A$6:$C$87,3,0) -> #N/A | AW53: =K53-AV53 -> #N/A
A54: 递延所得税资产 | B54: =VLOOKUP(A54,快速BS新!A$6:C$212,3,0) -> 0 | C54: =VLOOKUP(A54,新材料BS新!$A$4:$D$191,3,0) -> 0 | D54: =VLOOKUP(A54,精铸BS新!$A$6:$C$86,3,0) -> 0 | E54: =VLOOKUP(A54,热等静压BS新!$A$6:$C$86,3,0) -> 10042.63 | H54: =SUM(B54:G54) -> 10042.63 | I54: =合并调整抵消分录!E40 -> 0 | J54: =合并调整抵消分录!F40 -> 0 | K54: =H54+I54-J54 -> 10042.63 | L54: 0 | M54: 102931.58 | N54: 0 | O54: 0 | R54: =SUM(L54:Q54) -> 102931.58 | S54: 0 | T54: 0 | U54: =R54+S54-T54 -> 102931.58 | V54: 0 | W54: 85808.95 | X54: 0 | AB54: =SUM(V54:AA54) -> 85808.95 | AC54: =合并调整抵消分录!N40 -> 0 | AD54: =合并调整抵消分录!O40 -> 0 | AE54: =AB54+AC54-AD54 -> 85808.95 | AL54: =SUM(AF54:AK54) -> 0 | AM54: =合并调整抵消分录!Q40 -> 0 | AN54: =合并调整抵消分录!R40 -> 0 | AO54: =AL54+AM54-AN54 -> 0 | AR54: =SUM(AP54:AQ54) -> 0 | AS54: =合并调整抵消分录!T40 -> 0 | AT54: =合并调整抵消分录!U40 -> 0 | AU54: =AR54+AS54-AT54 -> 0 | AV54: =VLOOKUP(A54,合并资产负债表!$A$6:$C$87,3,0) -> #N/A | AW54: =K54-AV54 -> #N/A
A55: 其他非流动资产 | B55: =VLOOKUP(A55,快速BS新!A$6:C$212,3,0) -> 0 | C55: =VLOOKUP(A55,新材料BS新!$A$4:$D$191,3,0) -> 0 | D55: =VLOOKUP(A55,精铸BS新!$A$6:$C$86,3,0) -> 0 | E55: =VLOOKUP(A55,热等静压BS新!$A$6:$C$86,3,0) -> 0 | H55: =SUM(B55:G55) -> 0 | I55: =合并调整抵消分录!E41 -> 0 | J55: =合并调整抵消分录!F41 -> 0 | K55: =H55+I55-J55 -> 0 | L55: 0 | M55: 0 | N55: 0 | O55: 0 | R55: =SUM(L55:Q55) -> 0 | S55: 0 | T55: 0 | U55: =R55+S55-T55 -> 0 | V55: 309667.73 | W55: 1181400.9 | X55: 0 | AB55: =SUM(V55:AA55) -> 1491068.7 | AC55: =合并调整抵消分录!N41 -> 0 | AD55: =合并调整抵消分录!O41 -> 0 | AE55: =AB55+AC55-AD55 -> 1491068.7 | AL55: =SUM(AF55:AK55) -> 0 | AM55: =合并调整抵消分录!Q41 -> 0 | AN55: =合并调整抵消分录!R41 -> 0 | AO55: =AL55+AM55-AN55 -> 0 | AR55: =SUM(AP55:AQ55) -> 0 | AS55: =合并调整抵消分录!T41 -> 0 | AT55: =合并调整抵消分录!U41 -> 0 | AU55: =AR55+AS55-AT55 -> 0 | AV55: =VLOOKUP(A55,合并资产负债表!$A$6:$C$87,3,0) -> #N/A | AW55: =K55-AV55 -> #N/A
A56: 非流动资产合计 | B56: =SUM(B32:B39,B44:B55) -> 3.7667688e+08 | C56: =SUM(C32:C39,C44:C55) -> 1.3662998e+08 | D56: =SUM(D32:D39,D44:D55) -> 2958781.8 | E56: =SUM(E32:E39,E44:E55) -> 1360812.3 | F56: =SUM(F32:F39,F44:F55) -> 0 | G56: =SUM(G32:G39,G44:G55) -> 0 | H56: =SUM(H32:H39,H44:H55) -> 5.1762646e+08 | I56: =SUM(I32:I39,I44:I55) -> -8448008.2 | ... K56: =SUM(K32:K39,K44:K55) -> 2.6124084e+08 | L56: 3.5783401e+08 | M56: 1.4517594e+08 | N56: 2681520 | O56: 2709930.2 | P56: =SUM(P32:P39,P44:P55) -> 0 | Q56: =SUM(Q32:Q39,Q44:Q55) -> 0 | R56: =SUM(R32:R39,R44:R55) -> 5.084014e+08 | S56: -3880319.9 | T56: 2.5173697e+08 | U56: =SUM(U32:U39,U44:U55) -> 2.5278411e+08 | V56: 1.9632671e+08 | W56: 8445928.5 | X56: 6202511.2 | Y56: =SUM(Y32:Y39,Y44:Y55) -> 0 | Z56: =SUM(Z32:Z39,Z44:Z55) -> 0 | AA56: =SUM(AA32:AA39,AA44:AA55) -> 0 | AB56: =SUM(AB32:AB39,AB44:AB55) -> 2.1097515e+08 | AC56: =SUM(AC32:AC39,AC44:AC55) -> 7697581.1 | AD56: =SUM(AD32:AD39,AD44:AD55) -> 35385058 | AE56: =SUM(AE32:AE39,AE44:AE55) -> 1.8328767e+08 | AF56: =SUM(AF32:AF39,AF44:AF55) -> 0 | ... AU56: =SUM(AU32:AU39,AU44:AU55) -> 0 | AV56: =VLOOKUP(A56,合并资产负债表!$A$6:$C$87,3,0) -> 1.9065589e+08 | AW56: =K56-AV56 -> 70584953
A57: 资产总计 | B57: =B30+B56 -> 4.8877433e+08 | C57: =C30+C56 -> 3.6948031e+08 | D57: =D30+D56 -> 21966622 | E57: =E30+E56 -> 26563925 | F57: =F30+F56 -> 0 | G57: =G30+G56 -> 0 | H57: =H30+H56 -> 9.0678519e+08 | I57: =I30+I56 -> -8448008.2 | ... K57: =K30+K56 -> 5.6665516e+08 | L57: 4.5507377e+08 | M57: 3.3070946e+08 | N57: 19393150 | O57: 25265541 | P57: =P30+P56 -> 0 | Q57: =Q30+Q56 -> 0 | R57: =R30+R56 -> 8.3044193e+08 | S57: -3880319.9 | T57: 3.1519652e+08 | U57: =U30+U56 -> 5.1136508e+08 | V57: 3.3539207e+08 | W57: 21154003 | X57: 17425101 | Y57: =Y30+Y56 -> 0 | Z57: =Z30+Z56 -> 0 | AA57: =AA30+AA56 -> 0 | AB57: =AB30+AB56 -> 3.7397118e+08 | AC57: =AC30+AC56 -> 7697581.1 | AD57: =AD30+AD56 -> 41821904 | AE57: =AE30+AE56 -> 3.3984685e+08 | AF57: =AF30+AF56 -> 0 | ... AU57: =AU30+AU56 -> 0 | AV57: =VLOOKUP(A57,合并资产负债表!$A$6:$C$87,3,0) -> 3.5926838e+08 | AW57: =K57-AV57 -> 2.0738678e+08
B58: =B57-快速BS新!C54 -> 0 | C58: =C57-新材料BS新!C50 -> 0 | D58: =D57-精铸BS新!C54 -> 0 | E58: =E57-热等静压BS新!C51 -> 0 | H58: =H57-H118 -> 0 | K58: =K57-K118 -> 0.0032678843 | R58: =R57-R118 -> 0 | U58: =U57-U118 -> 0.0021959543 | AW58: =K58-AV58 -> 0.0032678843
A59: 合并试算平衡表-负债和权益表 | AW59: =K59-AV59 -> 0
A60: =A5 -> 编制单位：飞而康快速制造科技有限责任公司 | AO60: =AO5 -> 金额：人民币元 | AU60: =AU5 -> 金额：人民币元 | AW60: =K60-AV60 -> 0
A61: 项目 | B61: =B6 -> 45991 | I61: 合并调整抵消 | K61: =B61 -> 45991 | L61: =L6 -> 45657 | S61: 合并调整抵消 | U61: =L61 -> 45657 | V61: =V6 -> 45291 | AC61: 合并调整抵消 | AE61: =V61 -> 45291 | AF61: =AF6 -> 0 | AM61: 合并调整抵消 | AO61: =AF61 -> 0 | AP61: =AP6 -> 41639 | AS61: 合并调整抵消 | AU61: =AP61 -> 41639 | AW61: =K61-AV61 -> 45991
B62: =B7 -> 母公司 | C62: =C7 -> 飞而康新材料 | D62: =D7 -> 飞而康精铸 | E62: =E7 -> 飞而康热等静压 | F62: =F7 -> 0 | G62: =G7 -> 0 | H62: =H7 -> 汇总数 | I62: 借 方 | J62: 贷 方 | K62: 合并审定数 | L62: =L7 -> 母公司 | M62: =M7 -> 飞而康新材料 | N62: =N7 -> 飞而康精铸 | O62: =O7 -> 飞而康热等静压 | P62: =P7 -> 0 | Q62: =Q7 -> 0 | R62: =R7 -> 汇总数 | S62: 借 方 | T62: 贷 方 | U62: 合并审定数 | V62: =V7 -> 母公司 | W62: =W7 -> 飞而康新材料 | X62: =X7 -> 飞而康精铸 | Y62: =Y7 -> 飞而康热等静压 | Z62: =Z7 -> 0 | AA62: =AA7 -> 0 | AB62: =AB7 -> 汇总数 | AC62: 借 方 | AD62: 贷 方 | AE62: 合并审定数 | AF62: =AF7 -> 母公司 | AG62: =AG7 -> 飞而康新材料 | AH62: =AH7 -> 飞而康精铸 | AI62: =AI7 -> 飞而康热等静压 | AJ62: =AJ7 -> 0 | AK62: =AK7 -> 0 | AL62: =AL7 -> 汇总数 | AM62: 借 方 | AN62: 贷 方 | AO62: 合并审定数 | AP62: =AP7 -> 母公司 | AQ62: =AQ7 -> 飞而康新材料 | AR62: =AR7 -> 汇总数 | AS62: 借 方 | AT62: 贷 方 | AU62: 合并审定数 | AW62: =K62-AV62 -> #VALUE!
A63: 流动负债 | AW63: =K63-AV63 -> 0
A64: 短期借款 | B64: =VLOOKUP(A64,快速BS新!A$6:C$212,3,0) -> 81680000 | C64: =VLOOKUP(A64,新材料BS新!$A$4:$D$191,3,0) -> 28000000 | D64: =VLOOKUP(A64,精铸BS新!$A$6:$C$86,3,0) -> 6872069.2 | E64: =VLOOKUP(A64,热等静压BS新!$A$6:$C$86,3,0) -> 0 | H64: =SUM(B64:G64) -> 1.1655207e+08 | I64: =合并调整抵消分录!E42 -> 0 | J64: =合并调整抵消分录!F42 -> 0 | K64: =H64-I64+J64 -> 1.1655207e+08 | L64: 71680000 | M64: 25000000 | N64: 6000000 | O64: 0 | R64: =SUM(L64:Q64) -> 102680000 | S64: 0 | T64: 0 | U64: =R64-S64+T64 -> 102680000 | V64: 40000000 | W64: 0 | X64: 0 | AB64: =SUM(V64:AA64) -> 40000000 | AC64: =合并调整抵消分录!N42 -> 0 | AD64: =合并调整抵消分录!O42 -> 0 | AE64: =AB64-AC64+AD64 -> 40000000 | AL64: =SUM(AF64:AK64) -> 0 | AM64: =合并调整抵消分录!Q42 -> 0 | AN64: =合并调整抵消分录!R42 -> 0 | AO64: =AL64-AM64+AN64 -> 0 | AR64: =SUM(AP64:AQ64) -> 0 | AS64: =合并调整抵消分录!T42 -> 0 | AT64: =合并调整抵消分录!U42 -> 0 | AU64: =AR64-AS64+AT64 -> 0 | AV64: =VLOOKUP(A64,合并资产负债表!$A$6:$C$87,3,0) -> #N/A | AW64: =K64-AV64 -> #N/A
A65: △向中央银行借款 | H65: =SUM(B65:G65) -> 0 | I65: =合并调整抵消分录!E43 -> 0 | J65: =合并调整抵消分录!F43 -> 0 | K65: =H65-I65+J65 -> 0 | R65: =SUM(L65:Q65) -> 0 | S65: 0 | T65: 0 | U65: =R65-S65+T65 -> 0 | V65: 0 | W65: 0 | X65: 0 | AB65: =SUM(V65:AA65) -> 0 | AC65: =合并调整抵消分录!N43 -> 0 | AD65: =合并调整抵消分录!O43 -> 0 | AE65: =AB65-AC65+AD65 -> 0 | AL65: =SUM(AF65:AK65) -> 0 | AM65: =合并调整抵消分录!Q43 -> 0 | AN65: =合并调整抵消分录!R43 -> 0 | AO65: =AL65-AM65+AN65 -> 0 | AR65: =SUM(AP65:AQ65) -> 0 | AS65: =合并调整抵消分录!T43 -> 0 | AT65: =合并调整抵消分录!U43 -> 0 | AU65: =AR65-AS65+AT65 -> 0 | AW65: =K65-AV65 -> 0
A66: △吸收存款及同业存款 | H66: =SUM(B66:G66) -> 0 | I66: =合并调整抵消分录!E44 -> 0 | J66: =合并调整抵消分录!F44 -> 0 | K66: =H66-I66+J66 -> 0 | R66: =SUM(L66:Q66) -> 0 | S66: 0 | T66: 0 | U66: =R66-S66+T66 -> 0 | V66: 0 | W66: 0 | X66: 0 | AB66: =SUM(V66:AA66) -> 0 | AC66: =合并调整抵消分录!N44 -> 0 | AD66: =合并调整抵消分录!O44 -> 0 | AE66: =AB66-AC66+AD66 -> 0 | AL66: =SUM(AF66:AK66) -> 0 | AM66: =合并调整抵消分录!Q44 -> 0 | AN66: =合并调整抵消分录!R44 -> 0 | AO66: =AL66-AM66+AN66 -> 0 | AR66: =SUM(AP66:AQ66) -> 0 | AS66: =合并调整抵消分录!T44 -> 0 | AT66: =合并调整抵消分录!U44 -> 0 | AU66: =AR66-AS66+AT66 -> 0 | AW66: =K66-AV66 -> 0
A67: 交易性金融负债 | B67: =VLOOKUP(A67,快速BS新!A$6:C$212,3,0) -> 0 | C67: =VLOOKUP(A67,新材料BS新!$A$4:$D$191,3,0) -> 0 | D67: =VLOOKUP(A67,精铸BS新!$A$6:$C$86,3,0) -> 0 | E67: =VLOOKUP(A67,热等静压BS新!$A$6:$C$86,3,0) -> 0 | H67: =SUM(B67:G67) -> 0 | I67: =合并调整抵消分录!E45 -> 0 | J67: =合并调整抵消分录!F45 -> 0 | K67: =H67-I67+J67 -> 0 | L67: 0 | M67: 0 | N67: 0 | O67: 0 | R67: =SUM(L67:Q67) -> 0 | S67: 0 | T67: 0 | U67: =R67-S67+T67 -> 0 | V67: 0 | W67: 0 | X67: 0 | AB67: =SUM(V67:AA67) -> 0 | AC67: =合并调整抵消分录!N45 -> 0 | AD67: =合并调整抵消分录!O45 -> 0 | AE67: =AB67-AC67+AD67 -> 0 | AL67: =SUM(AF67:AK67) -> 0 | AM67: =合并调整抵消分录!Q45 -> 0 | AN67: =合并调整抵消分录!R45 -> 0 | AO67: =AL67-AM67+AN67 -> 0 | AR67: =SUM(AP67:AQ67) -> 0 | AS67: =合并调整抵消分录!T45 -> 0 | AT67: =合并调整抵消分录!U45 -> 0 | AU67: =AR67-AS67+AT67 -> 0 | AW67: =K67-AV67 -> 0
A68: 衍生金融负债 | H68: =SUM(B68:G68) -> 0 | I68: =合并调整抵消分录!E46 -> 0 | J68: =合并调整抵消分录!F46 -> 0 | K68: =H68-I68+J68 -> 0 | R68: =SUM(L68:Q68) -> 0 | S68: 0 | T68: 0 | U68: =R68-S68+T68 -> 0 | V68: 0 | W68: 0 | X68: 0 | AB68: =SUM(V68:AA68) -> 0 | AC68: =合并调整抵消分录!N46 -> 0 | AD68: =合并调整抵消分录!O46 -> 0 | AE68: =AB68-AC68+AD68 -> 0 | AL68: =SUM(AF68:AK68) -> 0 | AM68: =合并调整抵消分录!Q46 -> 0 | AN68: =合并调整抵消分录!R46 -> 0 | AO68: =AL68-AM68+AN68 -> 0 | AR68: =SUM(AP68:AQ68) -> 0 | AS68: =合并调整抵消分录!T46 -> 0 | AT68: =合并调整抵消分录!U46 -> 0 | AU68: =AR68-AS68+AT68 -> 0 | AW68: =K68-AV68 -> 0
A69: △拆入资金 | H69: =SUM(B69:G69) -> 0 | I69: =合并调整抵消分录!E47 -> 0 | J69: =合并调整抵消分录!F47 -> 0 | K69: =H69-I69+J69 -> 0 | R69: =SUM(L69:Q69) -> 0 | S69: 0 | T69: 0 | U69: =R69-S69+T69 -> 0 | V69: 0 | W69: 0 | X69: 0 | AB69: =SUM(V69:AA69) -> 0 | AC69: =合并调整抵消分录!N47 -> 0 | AD69: =合并调整抵消分录!O47 -> 0 | AE69: =AB69-AC69+AD69 -> 0 | AL69: =SUM(AF69:AK69) -> 0 | AM69: =合并调整抵消分录!Q47 -> 0 | AN69: =合并调整抵消分录!R47 -> 0 | AO69: =AL69-AM69+AN69 -> 0 | AR69: =SUM(AP69:AQ69) -> 0 | AS69: =合并调整抵消分录!T47 -> 0 | AT69: =合并调整抵消分录!U47 -> 0 | AU69: =AR69-AS69+AT69 -> 0 | AW69: =K69-AV69 -> 0
A70: 应付票据 | B70: =VLOOKUP(A70,快速BS新!A$6:C$212,3,0) -> 1128557.5 | C70: =VLOOKUP(A70,新材料BS新!$A$4:$D$191,3,0) -> 0 | D70: =VLOOKUP(A70,精铸BS新!$A$6:$C$86,3,0) -> 0 | E70: =VLOOKUP(A70,热等静压BS新!$A$6:$C$86,3,0) -> 0 | H70: =SUM(B70:G70) -> 1128557.5 | I70: =合并调整抵消分录!E48 -> 0 | J70: =合并调整抵消分录!F48 -> 0 | K70: =H70-I70+J70 -> 1128557.5 | L70: 0 | M70: 0 | N70: 0 | O70: 0 | R70: =SUM(L70:Q70) -> 0 | S70: 0 | T70: 0 | U70: =R70-S70+T70 -> 0 | V70: 0 | W70: 0 | X70: 0 | AB70: =SUM(V70:AA70) -> 0 | AC70: =合并调整抵消分录!N48 -> 0 | AD70: =合并调整抵消分录!O48 -> 0 | AE70: =AB70-AC70+AD70 -> 0 | AL70: =SUM(AF70:AK70) -> 0 | AM70: =合并调整抵消分录!Q48 -> 0 | AN70: =合并调整抵消分录!R48 -> 0 | AO70: =AL70-AM70+AN70 -> 0 | AR70: =SUM(AP70:AQ70) -> 0 | AS70: =合并调整抵消分录!T48 -> 0 | AT70: =合并调整抵消分录!U48 -> 0 | AU70: =AR70-AS70+AT70 -> 0 | AV70: =VLOOKUP(A70,合并资产负债表!$A$6:$C$87,3,0) -> #N/A | AW70: =K70-AV70 -> #N/A
A71: 应付账款 | B71: =VLOOKUP(A71,快速BS新!A$6:C$212,3,0) -> 99797183 | C71: =VLOOKUP(A71,新材料BS新!$A$4:$D$191,3,0) -> 1.1202226e+08 | D71: =VLOOKUP(A71,精铸BS新!$A$6:$C$86,3,0) -> 6099688.6 | E71: =VLOOKUP(A71,热等静压BS新!$A$6:$C$86,3,0) -> 15578155 | H71: =SUM(B71:G71) -> 2.3349729e+08 | I71: =合并调整抵消分录!E49 -> 84166417 | J71: =合并调整抵消分录!F49 -> 0 | K71: =H71-I71+J71 -> 1.4933087e+08 | L71: 1.0347976e+08 | M71: 69251153 | N71: 3993067.4 | O71: 14821460 | R71: =SUM(L71:Q71) -> 1.9154544e+08 | S71: 63078609 | T71: 0 | U71: =R71-S71+T71 -> 1.2846684e+08 | V71: 43708666 | W71: 4618775.4 | X71: 1299478.8 | AB71: =SUM(V71:AA71) -> 49626920 | AC71: =合并调整抵消分录!N49 -> 5028788.1 | AD71: =合并调整抵消分录!O49 -> 0 | AE71: =AB71-AC71+AD71 -> 44598132 | AL71: =SUM(AF71:AK71) -> 0 | AM71: =合并调整抵消分录!Q49 -> 0 | AN71: =合并调整抵消分录!R49 -> 0 | AO71: =AL71-AM71+AN71 -> 0 | AR71: =SUM(AP71:AQ71) -> 0 | AS71: =合并调整抵消分录!T49 -> 0 | AT71: =合并调整抵消分录!U49 -> 0 | AU71: =AR71-AS71+AT71 -> 0 | AV71: =VLOOKUP(A71,合并资产负债表!$A$6:$C$87,3,0) -> #N/A | AW71: =K71-AV71 -> #N/A
A72: 预收账款 | B72: =VLOOKUP(A72,快速BS新!A$6:C$212,3,0) -> 2852509.1 | C72: =VLOOKUP(A72,新材料BS新!$A$4:$D$191,3,0) -> 336613.72 | D72: =VLOOKUP(A72,精铸BS新!$A$6:$C$86,3,0) -> 17730 | E72: =VLOOKUP(A72,热等静压BS新!$A$6:$C$86,3,0) -> 303641.02 | H72: =SUM(B72:G72) -> 3510493.9 | I72: =合并调整抵消分录!E50 -> 0 | J72: =合并调整抵消分录!F50 -> 0 | K72: =H72-I72+J72 -> 3510493.9 | L72: 4378884.1 | M72: 248395.32 | N72: 11100 | O72: 579551.02 | R72: =SUM(L72:Q72) -> 5217930.5 | S72: 0 | T72: 0 | U72: =R72-S72+T72 -> 5217930.5 | V72: 237853.35 | W72: 280652 | X72: 1482338.6 | AB72: =SUM(V72:AA72) -> 2000844 | AC72: =合并调整抵消分录!N50 -> 0 | AD72: =合并调整抵消分录!O50 -> 0 | AE72: =AB72-AC72+AD72 -> 2000844 | AL72: =SUM(AF72:AK72) -> 0 | AM72: =合并调整抵消分录!Q50 -> 0 | AN72: =合并调整抵消分录!R50 -> 0 | AO72: =AL72-AM72+AN72 -> 0 | AR72: =SUM(AP72:AQ72) -> 0 | AS72: =合并调整抵消分录!T50 -> 0 | AT72: =合并调整抵消分录!U50 -> 0 | AU72: =AR72-AS72+AT72 -> 0 | AV72: =VLOOKUP(A72,合并资产负债表!$A$6:$C$87,3,0) -> #N/A | AW72: =K72-AV72 -> #N/A
A73: 合同负债 | B73: =VLOOKUP(A73,快速BS新!A$6:C$212,3,0) -> 795634.24 | C73: =VLOOKUP(A73,新材料BS新!$A$4:$D$191,3,0) -> 3872910.8 | D73: =VLOOKUP(A73,精铸BS新!$A$6:$C$86,3,0) -> 176978.65 | E73: =VLOOKUP(A73,热等静压BS新!$A$6:$C$86,3,0) -> 0 | H73: =SUM(B73:G73) -> 4845523.6 | J73: =合并调整抵消分录!F168 -> 443894.34 | K73: =H73-I73+J73 -> 5289418 | L73: 0 | M73: 4281052.3 | N73: 167155.64 | O73: 0 | R73: =SUM(L73:Q73) -> 4448207.9 | T73: 0 | U73: =R73-S73+T73 -> 4448207.9
A74: △卖出回购金融资产款 | H74: =SUM(B74:G74) -> 0 | I74: =合并调整抵消分录!E51 -> 0 | J74: =合并调整抵消分录!F51 -> 0 | K74: =H74-I74+J74 -> 0 | R74: =SUM(L74:Q74) -> 0 | S74: 0 | T74: 0 | U74: =R74-S74+T74 -> 0 | V74: 0 | W74: 0 | X74: 0 | AB74: =SUM(V74:AA74) -> 0 | AC74: =合并调整抵消分录!N51 -> 0 | AD74: =合并调整抵消分录!O51 -> 0 | AE74: =AB74-AC74+AD74 -> 0 | AL74: =SUM(AF74:AK74) -> 0 | AM74: =合并调整抵消分录!Q51 -> 0 | AN74: =合并调整抵消分录!R51 -> 0 | AO74: =AL74-AM74+AN74 -> 0 | AR74: =SUM(AP74:AQ74) -> 0 | AS74: =合并调整抵消分录!T51 -> 0 | AT74: =合并调整抵消分录!U51 -> 0 | AU74: =AR74-AS74+AT74 -> 0 | AW74: =K74-AV74 -> 0
A75: △应付手续费及佣金 | H75: =SUM(B75:G75) -> 0 | I75: =合并调整抵消分录!E52 -> 0 | J75: =合并调整抵消分录!F52 -> 0 | K75: =H75-I75+J75 -> 0 | R75: =SUM(L75:Q75) -> 0 | S75: 0 | T75: 0 | U75: =R75-S75+T75 -> 0 | V75: 0 | W75: 0 | X75: 0 | AB75: =SUM(V75:AA75) -> 0 | AC75: =合并调整抵消分录!N52 -> 0 | AD75: =合并调整抵消分录!O52 -> 0 | AE75: =AB75-AC75+AD75 -> 0 | AL75: =SUM(AF75:AK75) -> 0 | AM75: =合并调整抵消分录!Q52 -> 0 | AN75: =合并调整抵消分录!R52 -> 0 | AO75: =AL75-AM75+AN75 -> 0 | AR75: =SUM(AP75:AQ75) -> 0 | AS75: =合并调整抵消分录!T52 -> 0 | AT75: =合并调整抵消分录!U52 -> 0 | AU75: =AR75-AS75+AT75 -> 0 | AW75: =K75-AV75 -> 0
A76: 应付职工薪酬 | B76: =VLOOKUP(A76,快速BS新!A$6:C$212,3,0) -> 832375.14 | C76: =VLOOKUP(A76,新材料BS新!$A$4:$D$191,3,0) -> 1665876.2 | D76: =VLOOKUP(A76,精铸BS新!$A$6:$C$86,3,0) -> 501580.68 | E76: =VLOOKUP(A76,热等静压BS新!$A$6:$C$86,3,0) -> 192235.89 | H76: =SUM(B76:G76) -> 3192067.9 | I76: =合并调整抵消分录!E53 -> 0 | J76: =合并调整抵消分录!F53 -> 0 | K76: =H76-I76+J76 -> 3192067.9 | L76: 1789823.1 | M76: 4563905.5 | N76: 376992.4 | O76: 372259.01 | R76: =SUM(L76:Q76) -> 7102980 | S76: 0 | T76: 0 | U76: =R76-S76+T76 -> 7102980 | V76: 1347645.9 | W76: 402231.63 | X76: 889648.09 | AB76: =SUM(V76:AA76) -> 2639525.6 | AC76: =合并调整抵消分录!N53 -> 0 | AD76: =合并调整抵消分录!O53 -> 0 | AE76: =AB76-AC76+AD76 -> 2639525.6 | AL76: =SUM(AF76:AK76) -> 0 | AM76: =合并调整抵消分录!Q53 -> 0 | AN76: =合并调整抵消分录!R53 -> 0 | AO76: =AL76-AM76+AN76 -> 0 | AR76: =SUM(AP76:AQ76) -> 0 | AS76: =合并调整抵消分录!T53 -> 0 | AT76: =合并调整抵消分录!U53 -> 0 | AU76: =AR76-AS76+AT76 -> 0 | AV76: =VLOOKUP(A76,合并资产负债表!$A$6:$C$87,3,0) -> #N/A | AW76: =K76-AV76 -> #N/A
A77: 应交税费 | B77: =VLOOKUP(A77,快速BS新!A$6:C$212,3,0) -> 135260.06 | C77: =VLOOKUP(A77,新材料BS新!$A$4:$D$191,3,0) -> 625110.89 | D77: =VLOOKUP(A77,精铸BS新!$A$6:$C$86,3,0) -> -22570.11 | E77: =VLOOKUP(A77,热等静压BS新!$A$6:$C$86,3,0) -> 297.6 | F77: ='[11]VT北美-人民币'!$E$73 -> 0 | H77: =SUM(B77:G77) -> 738098.44 | I77: =合并调整抵消分录!E54 -> 0 | J77: =合并调整抵消分录!F54 -> 0 | K77: =H77-I77+J77 -> 738098.44 | L77: 1270209.9 | M77: 1575055.4 | N77: 196025.77 | O77: 44341.87 | R77: =SUM(L77:Q77) -> 3085633 | S77: 0 | T77: 0 | U77: =R77-S77+T77 -> 3085633 | V77: 140856.31 | W77: 61711.33 | X77: 223103.75 | AB77: =SUM(V77:AA77) -> 425671.39 | AC77: =合并调整抵消分录!N54 -> 0 | AD77: =合并调整抵消分录!O54 -> 0 | AE77: =AB77-AC77+AD77 -> 425671.39 | AL77: =SUM(AF77:AK77) -> 0 | AM77: =合并调整抵消分录!Q54 -> 0 | AN77: =合并调整抵消分录!R54 -> 0 | AO77: =AL77-AM77+AN77 -> 0 | AR77: =SUM(AP77:AQ77) -> 0 | AS77: =合并调整抵消分录!T54 -> 0 | AT77: =合并调整抵消分录!U54 -> 0 | AU77: =AR77-AS77+AT77 -> 0 | AV77: =VLOOKUP(A77,合并资产负债表!$A$6:$C$87,3,0) -> #N/A | AW77: =K77-AV77 -> #N/A
A78: 应付利息 | B78: =VLOOKUP(A78,快速BS新!A$6:C$212,3,0) -> 427719.6 | C78: =VLOOKUP(A78,新材料BS新!$A$4:$D$191,3,0) -> 23722.23 | D78: =VLOOKUP(A78,精铸BS新!$A$6:$C$86,3,0) -> 4744.44 | E78: =VLOOKUP(A78,热等静压BS新!$A$6:$C$86,3,0) -> 0 | H78: =SUM(B78:G78) -> 456186.27 | I78: =合并调整抵消分录!E55 -> 0 | J78: =合并调整抵消分录!F55 -> 0 | K78: =H78-I78+J78 -> 456186.27 | L78: 136289.31 | M78: 25055.55 | N78: 6319.45 | O78: 0 | R78: =SUM(L78:Q78) -> 167664.31 | S78: 0 | T78: 0 | U78: =R78-S78+T78 -> 167664.31 | V78: 56501.81 | W78: 0 | X78: 0 | AB78: =SUM(V78:AA78) -> 56501.81 | AC78: =合并调整抵消分录!N55 -> 0 | AD78: =合并调整抵消分录!O55 -> 0 | AE78: =AB78-AC78+AD78 -> 56501.81 | AL78: =SUM(AF78:AK78) -> 0 | AM78: =合并调整抵消分录!Q55 -> 0 | AN78: =合并调整抵消分录!R55 -> 0 | AO78: =AL78-AM78+AN78 -> 0 | AR78: =SUM(AP78:AQ78) -> 0 | AS78: =合并调整抵消分录!T55 -> 0 | AT78: =合并调整抵消分录!U55 -> 0 | AU78: =AR78-AS78+AT78 -> 0 | AV78: =VLOOKUP(A78,合并资产负债表!$A$6:$C$87,3,0) -> #N/A | AW78: =K78-AV78 -> #N/A
A79: 应付股利 | B79: =VLOOKUP(A79,快速BS新!A$6:C$212,3,0) -> 0 | C79: =VLOOKUP(A79,新材料BS新!$A$4:$D$191,3,0) -> 0 | D79: =VLOOKUP(A79,精铸BS新!$A$6:$C$86,3,0) -> 0 | E79: =VLOOKUP(A79,热等静压BS新!$A$6:$C$86,3,0) -> 0 | H79: =SUM(B79:G79) -> 0 | I79: =合并调整抵消分录!E56 -> 0 | J79: =合并调整抵消分录!F56 -> 0 | K79: =H79-I79+J79 -> 0 | L79: 0 | M79: 0 | N79: 0 | O79: 0 | R79: =SUM(L79:Q79) -> 0 | S79: 0 | T79: 0 | U79: =R79-S79+T79 -> 0 | V79: 0 | W79: 0 | X79: 0 | AB79: =SUM(V79:AA79) -> 0 | AC79: =合并调整抵消分录!N56 -> 0 | AD79: =合并调整抵消分录!O56 -> 0 | AE79: =AB79-AC79+AD79 -> 0 | AL79: =SUM(AF79:AK79) -> 0 | AM79: =合并调整抵消分录!Q56 -> 0 | AN79: =合并调整抵消分录!R56 -> 0 | AO79: =AL79-AM79+AN79 -> 0 | AR79: =SUM(AP79:AQ79) -> 0 | AS79: =合并调整抵消分录!T56 -> 0 | AT79: =合并调整抵消分录!U56 -> 0 | AU79: =AR79-AS79+AT79 -> 0 | AV79: =VLOOKUP(A79,合并资产负债表!$A$6:$C$87,3,0) -> #N/A | AW79: =K79-AV79 -> #N/A
A80: 其他应付款 | B80: =VLOOKUP(A80,快速BS新!A$6:C$212,3,0) -> 2953198.6 | C80: =VLOOKUP(A80,新材料BS新!$A$4:$D$191,3,0) -> 264881.03 | D80: =VLOOKUP(A80,精铸BS新!$A$6:$C$86,3,0) -> 262920.15 | E80: =VLOOKUP(A80,热等静压BS新!$A$6:$C$86,3,0) -> 520 | H80: =SUM(B80:G80) -> 3481519.8 | I80: =合并调整抵消分录!E57 -> 0 | J80: =合并调整抵消分录!F57 -> 0 | K80: =H80-I80+J80 -> 3481519.8 | L80: 1375495.7 | M80: 312546.75 | N80: 275934.23 | O80: 220 | R80: =SUM(L80:Q80) -> 1964196.6 | S80: 336853 | T80: 0 | U80: =R80-S80+T80 -> 1627343.6 | V80: 31980888 | W80: 0 | X80: 0 | AB80: =SUM(V80:AA80) -> 31980888 | AC80: =合并调整抵消分录!N57 -> 0 | AD80: =合并调整抵消分录!O57 -> 0 | AE80: =AB80-AC80+AD80 -> 31980888 | AL80: =SUM(AF80:AK80) -> 0 | AM80: =合并调整抵消分录!Q57 -> 0 | AN80: =合并调整抵消分录!R57 -> 0 | AO80: =AL80-AM80+AN80 -> 0 | AR80: =SUM(AP80:AQ80) -> 0 | AS80: =合并调整抵消分录!T57 -> 0 | AT80: =合并调整抵消分录!U57 -> 0 | AU80: =AR80-AS80+AT80 -> 0 | AV80: =VLOOKUP(A80,合并资产负债表!$A$6:$C$87,3,0) -> #N/A | AW80: =K80-AV80 -> #N/A
A81: △应付分保账款 | H81: =SUM(B81:G81) -> 0 | I81: =合并调整抵消分录!E58 -> 0 | J81: =合并调整抵消分录!F58 -> 0 | K81: =H81-I81+J81 -> 0 | R81: =SUM(L81:Q81) -> 0 | S81: 0 | T81: 0 | U81: =R81-S81+T81 -> 0 | AB81: =SUM(V81:AA81) -> 0 | AC81: =合并调整抵消分录!N58 -> 0 | AD81: =合并调整抵消分录!O58 -> 0 | AE81: =AB81-AC81+AD81 -> 0 | AL81: =SUM(AF81:AK81) -> 0 | AM81: =合并调整抵消分录!Q58 -> 0 | AN81: =合并调整抵消分录!R58 -> 0 | AO81: =AL81-AM81+AN81 -> 0 | AR81: =SUM(AP81:AQ81) -> 0 | AS81: =合并调整抵消分录!T58 -> 0 | AT81: =合并调整抵消分录!U58 -> 0 | AU81: =AR81-AS81+AT81 -> 0 | AW81: =K81-AV81 -> 0
A82: △保险合同准备金 | H82: =SUM(B82:G82) -> 0 | I82: =合并调整抵消分录!E59 -> 0 | J82: =合并调整抵消分录!F59 -> 0 | K82: =H82-I82+J82 -> 0 | R82: =SUM(L82:Q82) -> 0 | S82: 0 | T82: 0 | U82: =R82-S82+T82 -> 0 | AB82: =SUM(V82:AA82) -> 0 | AC82: =合并调整抵消分录!N59 -> 0 | AD82: =合并调整抵消分录!O59 -> 0 | AE82: =AB82-AC82+AD82 -> 0 | AL82: =SUM(AF82:AK82) -> 0 | AM82: =合并调整抵消分录!Q59 -> 0 | AN82: =合并调整抵消分录!R59 -> 0 | AO82: =AL82-AM82+AN82 -> 0 | AR82: =SUM(AP82:AQ82) -> 0 | AS82: =合并调整抵消分录!T59 -> 0 | AT82: =合并调整抵消分录!U59 -> 0 | AU82: =AR82-AS82+AT82 -> 0 | AW82: =K82-AV82 -> 0
A83: △代理买卖证券款 | H83: =SUM(B83:G83) -> 0 | I83: =合并调整抵消分录!E60 -> 0 | J83: =合并调整抵消分录!F60 -> 0 | K83: =H83-I83+J83 -> 0 | R83: =SUM(L83:Q83) -> 0 | S83: 0 | T83: 0 | U83: =R83-S83+T83 -> 0 | AB83: =SUM(V83:AA83) -> 0 | AC83: =合并调整抵消分录!N60 -> 0 | AD83: =合并调整抵消分录!O60 -> 0 | AE83: =AB83-AC83+AD83 -> 0 | AL83: =SUM(AF83:AK83) -> 0 | AM83: =合并调整抵消分录!Q60 -> 0 | AN83: =合并调整抵消分录!R60 -> 0 | AO83: =AL83-AM83+AN83 -> 0 | AR83: =SUM(AP83:AQ83) -> 0 | AS83: =合并调整抵消分录!T60 -> 0 | AT83: =合并调整抵消分录!U60 -> 0 | AU83: =AR83-AS83+AT83 -> 0 | AW83: =K83-AV83 -> 0
A84: △代理承销证券款 | H84: =SUM(B84:G84) -> 0 | I84: =合并调整抵消分录!E61 -> 0 | J84: =合并调整抵消分录!F61 -> 0 | K84: =H84-I84+J84 -> 0 | R84: =SUM(L84:Q84) -> 0 | S84: 0 | T84: 0 | U84: =R84-S84+T84 -> 0 | V84: 0 | W84: 0 | X84: 0 | AB84: =SUM(V84:AA84) -> 0 | AC84: =合并调整抵消分录!N61 -> 0 | AD84: =合并调整抵消分录!O61 -> 0 | AE84: =AB84-AC84+AD84 -> 0 | AL84: =SUM(AF84:AK84) -> 0 | AM84: =合并调整抵消分录!Q61 -> 0 | AN84: =合并调整抵消分录!R61 -> 0 | AO84: =AL84-AM84+AN84 -> 0 | AR84: =SUM(AP84:AQ84) -> 0 | AS84: =合并调整抵消分录!T61 -> 0 | AT84: =合并调整抵消分录!U61 -> 0 | AU84: =AR84-AS84+AT84 -> 0 | AW84: =K84-AV84 -> 0
A85: 划分为持有待售的负债 | H85: =SUM(B85:G85) -> 0 | I85: =合并调整抵消分录!E62 -> 0 | J85: =合并调整抵消分录!F62 -> 0 | K85: =H85-I85+J85 -> 0 | R85: =SUM(L85:Q85) -> 0 | S85: 0 | T85: 0 | U85: =R85-S85+T85 -> 0 | V85: 0 | W85: 0 | X85: 0 | AB85: =SUM(V85:AA85) -> 0 | AC85: =合并调整抵消分录!N62 -> 0 | AD85: =合并调整抵消分录!O62 -> 0 | AE85: =AB85-AC85+AD85 -> 0 | AL85: =SUM(AF85:AK85) -> 0 | AM85: =合并调整抵消分录!Q62 -> 0 | AN85: =合并调整抵消分录!R62 -> 0 | AO85: =AL85-AM85+AN85 -> 0 | AR85: =SUM(AP85:AQ85) -> 0 | AS85: =合并调整抵消分录!T62 -> 0 | AT85: =合并调整抵消分录!U62 -> 0 | AU85: =AR85-AS85+AT85 -> 0 | AW85: =K85-AV85 -> 0
A86: 一年内到期的非流动负债 | B86: =VLOOKUP(A86,快速BS新!A$6:C$212,3,0) -> 8372322.7 | C86: =VLOOKUP(A86,新材料BS新!$A$4:$D$191,3,0) -> 0 | D86: =VLOOKUP(A86,精铸BS新!$A$6:$C$86,3,0) -> 0 | E86: =VLOOKUP(A86,热等静压BS新!$A$6:$C$86,3,0) -> 0 | H86: =SUM(B86:G86) -> 8372322.7 | I86: =合并调整抵消分录!E63 -> 0 | J86: =合并调整抵消分录!F63 -> 0 | K86: =H86-I86+J86 -> 8372322.7 | L86: 34947726 | M86: 0 | N86: 0 | O86: 0 | R86: =SUM(L86:Q86) -> 34947726 | S86: 0 | T86: 0 | U86: =R86-S86+T86 -> 34947726 | V86: 4439663.7 | W86: 0 | X86: 0 | AB86: =SUM(V86:AA86) -> 4439663.7 | AC86: =合并调整抵消分录!N63 -> 0 | AD86: =合并调整抵消分录!O63 -> 0 | AE86: =AB86-AC86+AD86 -> 4439663.7 | AL86: =SUM(AF86:AK86) -> 0 | AM86: =合并调整抵消分录!Q63 -> 0 | AN86: =合并调整抵消分录!R63 -> 0 | AO86: =AL86-AM86+AN86 -> 0 | AR86: =SUM(AP86:AQ86) -> 0 | AS86: =合并调整抵消分录!T63 -> 0 | AT86: =合并调整抵消分录!U63 -> 0 | AU86: =AR86-AS86+AT86 -> 0 | AV86: =VLOOKUP(A86,合并资产负债表!$A$6:$C$87,3,0) -> #N/A | AW86: =K86-AV86 -> #N/A
A87: 其他流动负债 | B87: =VLOOKUP(A87,快速BS新!A$6:C$212,3,0) -> 2047336.8 | C87: =VLOOKUP(A87,新材料BS新!$A$4:$D$191,3,0) -> 2231181.9 | D87: =VLOOKUP(A87,精铸BS新!$A$6:$C$86,3,0) -> 1276.99 | E87: =VLOOKUP(A87,热等静压BS新!$A$6:$C$86,3,0) -> 0 | H87: =SUM(B87:G87) -> 4279795.6 | I87: =合并调整抵消分录!E64 -> 0 | J87: =合并调整抵消分录!F64 -> 0 | K87: =H87-I87+J87 -> 4279795.6 | L87: 0 | M87: 0 | N87: 0 | O87: 0 | R87: =SUM(L87:Q87) -> 0 | S87: 0 | T87: 0 | U87: =R87-S87+T87 -> 0 | W87: 0 | X87: 0 | AB87: =SUM(V87:AA87) -> 0 | AC87: =合并调整抵消分录!N64 -> 0 | AD87: =合并调整抵消分录!O64 -> 0 | AE87: =AB87-AC87+AD87 -> 0 | AL87: =SUM(AF87:AK87) -> 0 | AM87: =合并调整抵消分录!Q64 -> 0 | AN87: =合并调整抵消分录!R64 -> 0 | AO87: =AL87-AM87+AN87 -> 0 | AR87: =SUM(AP87:AQ87) -> 0 | AS87: =合并调整抵消分录!T64 -> 0 | AT87: =合并调整抵消分录!U64 -> 0 | AU87: =AR87-AS87+AT87 -> 0 | AW87: =K87-AV87 -> 4279795.6
A88: 流动负债合计 | B88: =SUM(B64:B87) -> 2.010221e+08 | C88: =SUM(C64:C87) -> 1.4904256e+08 | D88: =SUM(D64:D87) -> 13914419 | E88: =SUM(E64:E87) -> 16074849 | F88: =SUM(F64:F87) -> 0 | G88: =SUM(G64:G87) -> 0 | H88: =SUM(H64:H87) -> 3.8005393e+08 | I88: =SUM(I64:I87) -> 84166417 | ... K88: =SUM(K64:K87) -> 2.963314e+08 | L88: 2.1905819e+08 | M88: 1.0525716e+08 | N88: 11026595 | O88: 15817832 | P88: =SUM(P64:P87) -> 0 | Q88: =SUM(Q64:Q87) -> 0 | R88: =SUM(R64:R87) -> 3.5115978e+08 | S88: 63415462 | T88: 0 | U88: =SUM(U64:U87) -> 2.8774432e+08 | V88: 1.2191207e+08 | W88: 5363370.3 | X88: 3894569.3 | Y88: =SUM(Y64:Y87) -> 0 | Z88: =SUM(Z64:Z87) -> 0 | AA88: =SUM(AA64:AA87) -> 0 | AB88: =SUM(AB64:AB87) -> 1.3117001e+08 | AC88: =SUM(AC64:AC87) -> 5028788.1 | AD88: =SUM(AD64:AD87) -> 0 | AE88: =SUM(AE64:AE87) -> 1.2614123e+08 | AF88: =SUM(AF64:AF87) -> 0 | ... AU88: =SUM(AU64:AU87) -> 0 | AV88: =VLOOKUP(A88,合并资产负债表!$A$6:$C$87,3,0) -> 84982093 | AW88: =K88-AV88 -> 2.1134931e+08
A89: 非流动负债 | AW89: =K89-AV89 -> 0
A90: 长期借款 | B90: =VLOOKUP(A90,快速BS新!A$6:C$212,3,0) -> 48710000 | C90: =VLOOKUP(A90,新材料BS新!$A$4:$D$191,3,0) -> 0 | D90: =VLOOKUP(A90,精铸BS新!$A$6:$C$86,3,0) -> 0 | E90: =VLOOKUP(A90,热等静压BS新!$A$6:$C$86,3,0) -> 0 | H90: =SUM(B90:G90) -> 48710000 | I90: =合并调整抵消分录!E65 -> 0 | J90: =合并调整抵消分录!F65 -> 0 | K90: =H90-I90+J90 -> 48710000 | L90: 23800000 | M90: 0 | N90: 0 | O90: 0 | R90: =SUM(L90:Q90) -> 23800000 | S90: 0 | T90: 0 | U90: =R90-S90+T90 -> 23800000 | AB90: =SUM(V90:AA90) -> 0 | AC90: =合并调整抵消分录!N65 -> 0 | AD90: =合并调整抵消分录!O65 -> 0 | AE90: =AB90-AC90+AD90 -> 0 | AL90: =SUM(AF90:AK90) -> 0 | AM90: =合并调整抵消分录!Q65 -> 0 | AN90: =合并调整抵消分录!R65 -> 0 | AO90: =AL90-AM90+AN90 -> 0 | AR90: =SUM(AP90:AQ90) -> 0 | AS90: =合并调整抵消分录!T65 -> 0 | AT90: =合并调整抵消分录!U65 -> 0 | AU90: =AR90-AS90+AT90 -> 0 | AV90: =VLOOKUP(A90,合并资产负债表!$A$6:$C$87,3,0) -> #N/A | AW90: =K90-AV90 -> #N/A
A91: 应付债券 | B91: =VLOOKUP(A91,快速BS新!A$6:C$212,3,0) -> 0 | C91: =VLOOKUP(A91,新材料BS新!$A$4:$D$191,3,0) -> 0 | D91: =VLOOKUP(A91,精铸BS新!$A$6:$C$86,3,0) -> 0 | E91: =VLOOKUP(A91,热等静压BS新!$A$6:$C$86,3,0) -> 0 | H91: =SUM(B91:G91) -> 0 | I91: =合并调整抵消分录!E66 -> 0 | J91: =合并调整抵消分录!F66 -> 0 | K91: =H91-I91+J91 -> 0 | L91: 0 | M91: 0 | N91: 0 | O91: 0 | R91: =SUM(L91:Q91) -> 0 | S91: 0 | T91: 0 | U91: =R91-S91+T91 -> 0 | AB91: =SUM(V91:AA91) -> 0 | AC91: =合并调整抵消分录!N66 -> 0 | AD91: =合并调整抵消分录!O66 -> 0 | AE91: =AB91-AC91+AD91 -> 0 | AL91: =SUM(AF91:AK91) -> 0 | AM91: =合并调整抵消分录!Q66 -> 0 | AN91: =合并调整抵消分录!R66 -> 0 | AO91: =AL91-AM91+AN91 -> 0 | AR91: =SUM(AP91:AQ91) -> 0 | AS91: =合并调整抵消分录!T66 -> 0 | AT91: =合并调整抵消分录!U66 -> 0 | AU91: =AR91-AS91+AT91 -> 0 | AV91: =VLOOKUP(A91,合并资产负债表!$A$6:$C$87,3,0) -> #N/A | AW91: =K91-AV91 -> #N/A
A92: 其中:优先股 | H92: =SUM(B92:G92) -> 0 | I92: =合并调整抵消分录!E67 -> 0 | J92: =合并调整抵消分录!F67 -> 0 | K92: =H92-I92+J92 -> 0 | R92: =SUM(L92:Q92) -> 0 | S92: 0 | T92: 0 | U92: =R92-S92+T92 -> 0 | AB92: =SUM(V92:AA92) -> 0 | AC92: =合并调整抵消分录!N67 -> 0 | AD92: =合并调整抵消分录!O67 -> 0 | AE92: =AB92-AC92+AD92 -> 0 | AL92: =SUM(AF92:AK92) -> 0 | AM92: =合并调整抵消分录!Q67 -> 0 | AN92: =合并调整抵消分录!R67 -> 0 | AO92: =AL92-AM92+AN92 -> 0 | AR92: =SUM(AP92:AQ92) -> 0 | AS92: =合并调整抵消分录!T67 -> 0 | AT92: =合并调整抵消分录!U67 -> 0 | AU92: =AR92-AS92+AT92 -> 0 | AW92: =K92-AV92 -> 0
A93: 永续债 | H93: =SUM(B93:G93) -> 0 | I93: =合并调整抵消分录!E68 -> 0 | J93: =合并调整抵消分录!F68 -> 0 | K93: =H93-I93+J93 -> 0 | R93: =SUM(L93:Q93) -> 0 | S93: 0 | T93: 0 | U93: =R93-S93+T93 -> 0 | AB93: =SUM(V93:AA93) -> 0 | AC93: =合并调整抵消分录!N68 -> 0 | AD93: =合并调整抵消分录!O68 -> 0 | AE93: =AB93-AC93+AD93 -> 0 | AL93: =SUM(AF93:AK93) -> 0 | AM93: =合并调整抵消分录!Q68 -> 0 | AN93: =合并调整抵消分录!R68 -> 0 | AO93: =AL93-AM93+AN93 -> 0 | AR93: =SUM(AP93:AQ93) -> 0 | AS93: =合并调整抵消分录!T68 -> 0 | AT93: =合并调整抵消分录!U68 -> 0 | AU93: =AR93-AS93+AT93 -> 0 | AW93: =K93-AV93 -> 0
A94: 长期应付款 | B94: =VLOOKUP(A94,快速BS新!A$6:C$212,3,0) -> 0 | C94: =VLOOKUP(A94,新材料BS新!$A$4:$D$191,3,0) -> 0 | D94: =VLOOKUP(A94,精铸BS新!$A$6:$C$86,3,0) -> 0 | E94: =VLOOKUP(A94,热等静压BS新!$A$6:$C$86,3,0) -> 0 | H94: =SUM(B94:G94) -> 0 | I94: =合并调整抵消分录!E69 -> 0 | J94: =合并调整抵消分录!F69 -> 0 | K94: =H94-I94+J94 -> 0 | L94: 0 | M94: 0 | N94: 0 | O94: 0 | R94: =SUM(L94:Q94) -> 0 | S94: 0 | T94: 0 | U94: =R94-S94+T94 -> 0 | V94: 4778600.4 | AB94: =SUM(V94:AA94) -> 4778600.4 | AC94: =合并调整抵消分录!N69 -> 0 | AD94: =合并调整抵消分录!O69 -> 0 | AE94: =AB94-AC94+AD94 -> 4778600.4 | AL94: =SUM(AF94:AK94) -> 0 | AM94: =合并调整抵消分录!Q69 -> 0 | AN94: =合并调整抵消分录!R69 -> 0 | AO94: =AL94-AM94+AN94 -> 0 | AR94: =SUM(AP94:AQ94) -> 0 | AS94: =合并调整抵消分录!T69 -> 0 | AT94: =合并调整抵消分录!U69 -> 0 | AU94: =AR94-AS94+AT94 -> 0 | AV94: =VLOOKUP(A94,合并资产负债表!$A$6:$C$87,3,0) -> #N/A | AW94: =K94-AV94 -> #N/A
A95: 长期应付职工薪酬 | H95: =SUM(B95:G95) -> 0 | I95: =合并调整抵消分录!E70 -> 0 | J95: =合并调整抵消分录!F70 -> 0 | K95: =H95-I95+J95 -> 0 | R95: =SUM(L95:Q95) -> 0 | S95: 0 | T95: 0 | U95: =R95-S95+T95 -> 0 | V95: 0 | AB95: =SUM(V95:AA95) -> 0 | AC95: =合并调整抵消分录!N70 -> 0 | AD95: =合并调整抵消分录!O70 -> 0 | AE95: =AB95-AC95+AD95 -> 0 | AL95: =SUM(AF95:AK95) -> 0 | AM95: =合并调整抵消分录!Q70 -> 0 | AN95: =合并调整抵消分录!R70 -> 0 | AO95: =AL95-AM95+AN95 -> 0 | AR95: =SUM(AP95:AQ95) -> 0 | AS95: =合并调整抵消分录!T70 -> 0 | AT95: =合并调整抵消分录!U70 -> 0 | AU95: =AR95-AS95+AT95 -> 0 | AW95: =K95-AV95 -> 0
A96: 专项应付款 | B96: =VLOOKUP(A96,快速BS新!A$6:C$212,3,0) -> 0 | C96: =VLOOKUP(A96,新材料BS新!$A$4:$D$191,3,0) -> 0 | D96: =VLOOKUP(A96,精铸BS新!$A$6:$C$86,3,0) -> 0 | E96: =VLOOKUP(A96,热等静压BS新!$A$6:$C$86,3,0) -> 0 | H96: =SUM(B96:G96) -> 0 | I96: =合并调整抵消分录!E71 -> 0 | J96: =合并调整抵消分录!F71 -> 0 | K96: =H96-I96+J96 -> 0 | L96: 0 | M96: 0 | N96: 0 | O96: 0 | R96: =SUM(L96:Q96) -> 0 | S96: 0 | T96: 0 | U96: =R96-S96+T96 -> 0 | V96: 0 | AB96: =SUM(V96:AA96) -> 0 | AC96: =合并调整抵消分录!N71 -> 0 | AD96: =合并调整抵消分录!O71 -> 0 | AE96: =AB96-AC96+AD96 -> 0 | AL96: =SUM(AF96:AK96) -> 0 | AM96: =合并调整抵消分录!Q71 -> 0 | AN96: =合并调整抵消分录!R71 -> 0 | AO96: =AL96-AM96+AN96 -> 0 | AR96: =SUM(AP96:AQ96) -> 0 | AS96: =合并调整抵消分录!T71 -> 0 | AT96: =合并调整抵消分录!U71 -> 0 | AU96: =AR96-AS96+AT96 -> 0 | AV96: =VLOOKUP(A96,合并资产负债表!$A$6:$C$87,3,0) -> #N/A | AW96: =K96-AV96 -> #N/A
A97: 预计负债 | B97: =VLOOKUP(A97,快速BS新!A$6:C$212,3,0) -> 0 | C97: =VLOOKUP(A97,新材料BS新!$A$4:$D$191,3,0) -> 0 | D97: =VLOOKUP(A97,精铸BS新!$A$6:$C$86,3,0) -> 0 | E97: =VLOOKUP(A97,热等静压BS新!$A$6:$C$86,3,0) -> 0 | H97: =SUM(B97:G97) -> 0 | I97: =合并调整抵消分录!E72 -> 0 | J97: =合并调整抵消分录!F72 -> 0 | K97: =H97-I97+J97 -> 0 | L97: 0 | M97: 0 | N97: 0 | O97: 0 | R97: =SUM(L97:Q97) -> 0 | S97: 0 | T97: 0 | U97: =R97-S97+T97 -> 0 | V97: 0 | AB97: =SUM(V97:AA97) -> 0 | AC97: =合并调整抵消分录!N72 -> 0 | AD97: =合并调整抵消分录!O72 -> 0 | AE97: =AB97-AC97+AD97 -> 0 | AL97: =SUM(AF97:AK97) -> 0 | AM97: =合并调整抵消分录!Q72 -> 0 | AN97: =合并调整抵消分录!R72 -> 0 | AO97: =AL97-AM97+AN97 -> 0 | AR97: =SUM(AP97:AQ97) -> 0 | AS97: =合并调整抵消分录!T72 -> 0 | AT97: =合并调整抵消分录!U72 -> 0 | AU97: =AR97-AS97+AT97 -> 0 | AV97: =VLOOKUP(A97,合并资产负债表!$A$6:$C$87,3,0) -> #N/A | AW97: =K97-AV97 -> #N/A
A98: 递延收益 | B98: =VLOOKUP(A98,快速BS新!A$6:C$212,3,0) -> 33580809 | C98: =VLOOKUP(A98,新材料BS新!$A$4:$D$191,3,0) -> 350000 | D98: =VLOOKUP(A98,精铸BS新!$A$6:$C$86,3,0) -> 0 | E98: =VLOOKUP(A98,热等静压BS新!$A$6:$C$86,3,0) -> 0 | H98: =SUM(B98:G98) -> 33930809 | I98: =合并调整抵消分录!E73 -> 0 | J98: =合并调整抵消分录!F73 -> 0 | K98: =H98-I98+J98 -> 33930809 | L98: 8345132.6 | M98: 0 | N98: 0 | O98: 0 | R98: =SUM(L98:Q98) -> 8345132.6 | S98: 0 | T98: 0 | U98: =R98-S98+T98 -> 8345132.6 | V98: 1945941.2 | AB98: =SUM(V98:AA98) -> 1945941.2 | AC98: =合并调整抵消分录!N73 -> 0 | AD98: =合并调整抵消分录!O73 -> 0 | AE98: =AB98-AC98+AD98 -> 1945941.2 | AL98: =SUM(AF98:AK98) -> 0 | AM98: =合并调整抵消分录!Q73 -> 0 | AN98: =合并调整抵消分录!R73 -> 0 | AO98: =AL98-AM98+AN98 -> 0 | AR98: =SUM(AP98:AQ98) -> 0 | AS98: =合并调整抵消分录!T73 -> 0 | AT98: =合并调整抵消分录!U73 -> 0 | AU98: =AR98-AS98+AT98 -> 0 | AV98: =VLOOKUP(A98,合并资产负债表!$A$6:$C$87,3,0) -> #N/A | AW98: =K98-AV98 -> #N/A
A99: 递延所得税负债 | B99: =VLOOKUP(A99,快速BS新!A$6:C$212,3,0) -> 0 | C99: =VLOOKUP(A99,新材料BS新!$A$4:$D$191,3,0) -> 0 | D99: =VLOOKUP(A99,精铸BS新!$A$6:$C$86,3,0) -> 0 | E99: =VLOOKUP(A99,热等静压BS新!$A$6:$C$86,3,0) -> 0 | H99: =SUM(B99:G99) -> 0 | I99: =合并调整抵消分录!E74 -> 0 | J99: =合并调整抵消分录!F74 -> 0 | K99: =H99-I99+J99 -> 0 | L99: 0 | M99: 0 | N99: 0 | O99: 0 | R99: =SUM(L99:Q99) -> 0 | S99: 0 | T99: 0 | U99: =R99-S99+T99 -> 0 | AB99: =SUM(V99:AA99) -> 0 | AC99: =合并调整抵消分录!N74 -> 0 | AD99: =合并调整抵消分录!O74 -> 0 | AE99: =AB99-AC99+AD99 -> 0 | AL99: =SUM(AF99:AK99) -> 0 | AM99: =合并调整抵消分录!Q74 -> 0 | AN99: =合并调整抵消分录!R74 -> 0 | AO99: =AL99-AM99+AN99 -> 0 | AR99: =SUM(AP99:AQ99) -> 0 | AS99: =合并调整抵消分录!T74 -> 0 | AT99: =合并调整抵消分录!U74 -> 0 | AU99: =AR99-AS99+AT99 -> 0 | AV99: =VLOOKUP(A99,合并资产负债表!$A$6:$C$87,3,0) -> #N/A | AW99: =K99-AV99 -> #N/A
A100: 其他非流动负债 | B100: =VLOOKUP(A100,快速BS新!A$6:C$212,3,0) -> 0 | C100: =VLOOKUP(A100,新材料BS新!$A$4:$D$191,3,0) -> 0 | D100: =VLOOKUP(A100,精铸BS新!$A$6:$C$86,3,0) -> 0 | E100: =VLOOKUP(A100,热等静压BS新!$A$6:$C$86,3,0) -> 0 | H100: =SUM(B100:G100) -> 0 | I100: =合并调整抵消分录!E75 -> 0 | J100: =合并调整抵消分录!F75 -> 0 | K100: =H100-I100+J100 -> 0 | L100: 0 | M100: 0 | N100: 0 | O100: 0 | R100: =SUM(L100:Q100) -> 0 | S100: 0 | T100: 0 | U100: =R100-S100+T100 -> 0 | AB100: =SUM(V100:AA100) -> 0 | AC100: =合并调整抵消分录!N75 -> 0 | AD100: =合并调整抵消分录!O75 -> 0 | AE100: =AB100-AC100+AD100 -> 0 | AL100: =SUM(AF100:AK100) -> 0 | AM100: =合并调整抵消分录!Q75 -> 0 | AN100: =合并调整抵消分录!R75 -> 0 | AO100: =AL100-AM100+AN100 -> 0 | AR100: =SUM(AP100:AQ100) -> 0 | AS100: =合并调整抵消分录!T75 -> 0 | AT100: =合并调整抵消分录!U75 -> 0 | AU100: =AR100-AS100+AT100 -> 0 | AV100: =VLOOKUP(A100,合并资产负债表!$A$6:$C$87,3,0) -> #N/A | AW100: =K100-AV100 -> #N/A
...

Sheet 合并调整抵消分录
H1: =基本信息!C13&"调整分录汇总" -> 2024年度调整分录汇总 | K1: =基本信息!C12&"调整分录汇总" -> 2023年度调整分录汇总 | N1: =基本信息!C11&"调整分录汇总" -> 2022年度调整分录汇总 | Q1: =基本信息!C10&"调整分录汇总" -> 调整分录汇总 | T1: 2012年度调整分录汇总
E2: 借方 | F2: 贷方 | H2: 借方 | I2: 贷方 | K2: 借方 | L2: 贷方 | N2: 借方 | O2: 贷方 | Q2: 借方 | R2: 贷方 | T2: 借方 | U2: 贷方
C3: =TRIM(合并试算平衡表!A9) -> 货币资金 | E3: =SUMIFS(E$134:E$407,$C$134:$C$407,$C3,$G$134:$G$407,"Y") -> 0 | F3: =SUMIFS(F$134:F$407,$C$134:$C$407,$C3,$G$134:$G$407,"Y") -> 0 | H3: =SUMIFS(H$134:H$407,$C$134:$C$407,$C3,$J$134:$J$407,"Y") -> 0 | I3: =SUMIFS(I$134:I$407,$C$134:$C$407,$C3,$J$134:$J$407,"Y") -> 0 | K3: =SUMIFS(K$134:K$407,$C$134:$C$407,$C3,$M$134:$M$407,"Y") -> 0 | L3: =SUMIFS(L$134:L$407,$C$134:$C$407,$C3,$M$134:$M$407,"Y") -> 0 | N3: =SUMIFS(N$135:N$407,$C$135:$C$407,$C3,$P$135:$P$407,"Y") -> 0 | O3: =SUMIFS(O$135:O$407,$C$135:$C$407,$C3,$P$135:$P$407,"Y") -> 0 | Q3: =SUMIFS(Q$135:Q$407,$C$135:$C$407,$C3,$S$135:$S$407,"Y") -> 0 | R3: =SUMIFS(R$135:R$407,$C$135:$C$407,$C3,$S$135:$S$407,"Y") -> 0 | T3: =SUMIFS(T$135:T$407,$C$135:$C$407,$C3,$V$135:$V$407,"Y") -> 0 | U3: =SUMIFS(U$135:U$407,$C$135:$C$407,$C3,$V$135:$V$407,"Y") -> 0
C4: =TRIM(合并试算平衡表!A10) -> △结算备付金 | E4: =SUMIFS(E$134:E$407,$C$134:$C$407,$C4,$G$134:$G$407,"Y") -> 0 | F4: =SUMIFS(F$134:F$407,$C$134:$C$407,$C4,$G$134:$G$407,"Y") -> 0 | H4: =SUMIFS(H$134:H$407,$C$134:$C$407,$C4,$J$134:$J$407,"Y") -> 0 | I4: =SUMIFS(I$134:I$407,$C$134:$C$407,$C4,$J$134:$J$407,"Y") -> 0 | K4: =SUMIFS(K$134:K$407,$C$134:$C$407,$C4,$M$134:$M$407,"Y") -> 0 | L4: =SUMIFS(L$134:L$407,$C$134:$C$407,$C4,$M$134:$M$407,"Y") -> 0 | N4: =SUMIFS(N$135:N$407,$C$135:$C$407,$C4,$P$135:$P$407,"Y") -> 0 | O4: =SUMIFS(O$135:O$407,$C$135:$C$407,$C4,$P$135:$P$407,"Y") -> 0 | Q4: =SUMIFS(Q$135:Q$407,$C$135:$C$407,$C4,$S$135:$S$407,"Y") -> 0 | R4: =SUMIFS(R$135:R$407,$C$135:$C$407,$C4,$S$135:$S$407,"Y") -> 0 | T4: =SUMIFS(T$135:T$407,$C$135:$C$407,$C4,$V$135:$V$407,"Y") -> 0 | U4: =SUMIFS(U$135:U$407,$C$135:$C$407,$C4,$V$135:$V$407,"Y") -> 0
C5: =TRIM(合并试算平衡表!A11) -> △拆出资金 | E5: =SUMIFS(E$134:E$407,$C$134:$C$407,$C5,$G$134:$G$407,"Y") -> 0 | F5: =SUMIFS(F$134:F$407,$C$134:$C$407,$C5,$G$134:$G$407,"Y") -> 0 | H5: =SUMIFS(H$134:H$407,$C$134:$C$407,$C5,$J$134:$J$407,"Y") -> 0 | I5: =SUMIFS(I$134:I$407,$C$134:$C$407,$C5,$J$134:$J$407,"Y") -> 0 | K5: =SUMIFS(K$134:K$407,$C$134:$C$407,$C5,$M$134:$M$407,"Y") -> 0 | L5: =SUMIFS(L$134:L$407,$C$134:$C$407,$C5,$M$134:$M$407,"Y") -> 0 | N5: =SUMIFS(N$135:N$407,$C$135:$C$407,$C5,$P$135:$P$407,"Y") -> 0 | O5: =SUMIFS(O$135:O$407,$C$135:$C$407,$C5,$P$135:$P$407,"Y") -> 0 | Q5: =SUMIFS(Q$135:Q$407,$C$135:$C$407,$C5,$S$135:$S$407,"Y") -> 0 | R5: =SUMIFS(R$135:R$407,$C$135:$C$407,$C5,$S$135:$S$407,"Y") -> 0 | T5: =SUMIFS(T$135:T$407,$C$135:$C$407,$C5,$V$135:$V$407,"Y") -> 0 | U5: =SUMIFS(U$135:U$407,$C$135:$C$407,$C5,$V$135:$V$407,"Y") -> 0
C6: =TRIM(合并试算平衡表!A12) -> 交易性金融资产 | E6: =SUMIFS(E$134:E$407,$C$134:$C$407,$C6,$G$134:$G$407,"Y") -> 0 | F6: =SUMIFS(F$134:F$407,$C$134:$C$407,$C6,$G$134:$G$407,"Y") -> 0 | H6: =SUMIFS(H$134:H$407,$C$134:$C$407,$C6,$J$134:$J$407,"Y") -> 0 | I6: =SUMIFS(I$134:I$407,$C$134:$C$407,$C6,$J$134:$J$407,"Y") -> 0 | K6: =SUMIFS(K$134:K$407,$C$134:$C$407,$C6,$M$134:$M$407,"Y") -> 0 | L6: =SUMIFS(L$134:L$407,$C$134:$C$407,$C6,$M$134:$M$407,"Y") -> 0 | N6: =SUMIFS(N$135:N$407,$C$135:$C$407,$C6,$P$135:$P$407,"Y") -> 0 | O6: =SUMIFS(O$135:O$407,$C$135:$C$407,$C6,$P$135:$P$407,"Y") -> 0 | Q6: =SUMIFS(Q$135:Q$407,$C$135:$C$407,$C6,$S$135:$S$407,"Y") -> 0 | R6: =SUMIFS(R$135:R$407,$C$135:$C$407,$C6,$S$135:$S$407,"Y") -> 0 | T6: =SUMIFS(T$135:T$407,$C$135:$C$407,$C6,$V$135:$V$407,"Y") -> 0 | U6: =SUMIFS(U$135:U$407,$C$135:$C$407,$C6,$V$135:$V$407,"Y") -> 0
C7: =TRIM(合并试算平衡表!A13) -> 衍生金融资产 | E7: =SUMIFS(E$134:E$407,$C$134:$C$407,$C7,$G$134:$G$407,"Y") -> 0 | F7: =SUMIFS(F$134:F$407,$C$134:$C$407,$C7,$G$134:$G$407,"Y") -> 0 | H7: =SUMIFS(H$134:H$407,$C$134:$C$407,$C7,$J$134:$J$407,"Y") -> 0 | I7: =SUMIFS(I$134:I$407,$C$134:$C$407,$C7,$J$134:$J$407,"Y") -> 0 | K7: =SUMIFS(K$134:K$407,$C$134:$C$407,$C7,$M$134:$M$407,"Y") -> 0 | L7: =SUMIFS(L$134:L$407,$C$134:$C$407,$C7,$M$134:$M$407,"Y") -> 0 | N7: =SUMIFS(N$135:N$407,$C$135:$C$407,$C7,$P$135:$P$407,"Y") -> 0 | O7: =SUMIFS(O$135:O$407,$C$135:$C$407,$C7,$P$135:$P$407,"Y") -> 0 | Q7: =SUMIFS(Q$135:Q$407,$C$135:$C$407,$C7,$S$135:$S$407,"Y") -> 0 | R7: =SUMIFS(R$135:R$407,$C$135:$C$407,$C7,$S$135:$S$407,"Y") -> 0 | T7: =SUMIFS(T$135:T$407,$C$135:$C$407,$C7,$V$135:$V$407,"Y") -> 0 | U7: =SUMIFS(U$135:U$407,$C$135:$C$407,$C7,$V$135:$V$407,"Y") -> 0
C8: =TRIM(合并试算平衡表!A14) -> 应收票据 | E8: =SUMIFS(E$134:E$407,$C$134:$C$407,$C8,$G$134:$G$407,"Y") -> 0 | F8: =SUMIFS(F$134:F$407,$C$134:$C$407,$C8,$G$134:$G$407,"Y") -> 0 | H8: =SUMIFS(H$134:H$407,$C$134:$C$407,$C8,$J$134:$J$407,"Y") -> 0 | I8: =SUMIFS(I$134:I$407,$C$134:$C$407,$C8,$J$134:$J$407,"Y") -> 0 | K8: =SUMIFS(K$134:K$407,$C$134:$C$407,$C8,$M$134:$M$407,"Y") -> 0 | L8: =SUMIFS(L$134:L$407,$C$134:$C$407,$C8,$M$134:$M$407,"Y") -> 0 | N8: =SUMIFS(N$135:N$407,$C$135:$C$407,$C8,$P$135:$P$407,"Y") -> 0 | O8: =SUMIFS(O$135:O$407,$C$135:$C$407,$C8,$P$135:$P$407,"Y") -> 0 | Q8: =SUMIFS(Q$135:Q$407,$C$135:$C$407,$C8,$S$135:$S$407,"Y") -> 0 | R8: =SUMIFS(R$135:R$407,$C$135:$C$407,$C8,$S$135:$S$407,"Y") -> 0 | T8: =SUMIFS(T$135:T$407,$C$135:$C$407,$C8,$V$135:$V$407,"Y") -> 0 | U8: =SUMIFS(U$135:U$407,$C$135:$C$407,$C8,$V$135:$V$407,"Y") -> 0
C9: =TRIM(合并试算平衡表!A15) -> 应收账款 | E9: =SUMIFS(E$134:E$407,$C$134:$C$407,$C9,$G$134:$G$407,"Y") -> 0 | F9: =SUMIFS(F$134:F$407,$C$134:$C$407,$C9,$G$134:$G$407,"Y") -> 83722523 | H9: =SUMIFS(H$134:H$407,$C$134:$C$407,$C9,$J$134:$J$407,"Y") -> 0 | I9: =SUMIFS(I$134:I$407,$C$134:$C$407,$C9,$J$134:$J$407,"Y") -> 63078609 | K9: =SUMIFS(K$134:K$407,$C$134:$C$407,$C9,$M$134:$M$407,"Y") -> 0 | L9: =SUMIFS(L$134:L$407,$C$134:$C$407,$C9,$M$134:$M$407,"Y") -> 21170257 | N9: =SUMIFS(N$135:N$407,$C$135:$C$407,$C9,$P$135:$P$407,"Y") -> 0 | O9: =SUMIFS(O$135:O$407,$C$135:$C$407,$C9,$P$135:$P$407,"Y") -> 4469405.8 | Q9: =SUMIFS(Q$135:Q$407,$C$135:$C$407,$C9,$S$135:$S$407,"Y") -> 0 | R9: =SUMIFS(R$135:R$407,$C$135:$C$407,$C9,$S$135:$S$407,"Y") -> 0 | T9: =SUMIFS(T$135:T$407,$C$135:$C$407,$C9,$V$135:$V$407,"Y") -> 0 | U9: =SUMIFS(U$135:U$407,$C$135:$C$407,$C9,$V$135:$V$407,"Y") -> 0
C10: =TRIM(合并试算平衡表!A17) -> 预付款项 | E10: =SUMIFS(E$134:E$407,$C$134:$C$407,$C10,$G$134:$G$407,"Y") -> 0 | F10: =SUMIFS(F$134:F$407,$C$134:$C$407,$C10,$G$134:$G$407,"Y") -> 0 | H10: =SUMIFS(H$134:H$407,$C$134:$C$407,$C10,$J$134:$J$407,"Y") -> 0 | I10: =SUMIFS(I$134:I$407,$C$134:$C$407,$C10,$J$134:$J$407,"Y") -> 0 | K10: =SUMIFS(K$134:K$407,$C$134:$C$407,$C10,$M$134:$M$407,"Y") -> 0 | L10: =SUMIFS(L$134:L$407,$C$134:$C$407,$C10,$M$134:$M$407,"Y") -> 0 | N10: =SUMIFS(N$135:N$407,$C$135:$C$407,$C10,$P$135:$P$407,"Y") -> 0 | O10: =SUMIFS(O$135:O$407,$C$135:$C$407,$C10,$P$135:$P$407,"Y") -> 1408058.1 | Q10: =SUMIFS(Q$135:Q$407,$C$135:$C$407,$C10,$S$135:$S$407,"Y") -> 0 | R10: =SUMIFS(R$135:R$407,$C$135:$C$407,$C10,$S$135:$S$407,"Y") -> 0 | T10: =SUMIFS(T$135:T$407,$C$135:$C$407,$C10,$V$135:$V$407,"Y") -> 0 | U10: =SUMIFS(U$135:U$407,$C$135:$C$407,$C10,$V$135:$V$407,"Y") -> 0
C11: =TRIM(合并试算平衡表!A18) -> △应收保费 | E11: =SUMIFS(E$134:E$407,$C$134:$C$407,$C11,$G$134:$G$407,"Y") -> 0 | F11: =SUMIFS(F$134:F$407,$C$134:$C$407,$C11,$G$134:$G$407,"Y") -> 0 | H11: =SUMIFS(H$134:H$407,$C$134:$C$407,$C11,$J$134:$J$407,"Y") -> 0 | I11: =SUMIFS(I$134:I$407,$C$134:$C$407,$C11,$J$134:$J$407,"Y") -> 0 | K11: =SUMIFS(K$134:K$407,$C$134:$C$407,$C11,$M$134:$M$407,"Y") -> 0 | L11: =SUMIFS(L$134:L$407,$C$134:$C$407,$C11,$M$134:$M$407,"Y") -> 0 | N11: =SUMIFS(N$135:N$407,$C$135:$C$407,$C11,$P$135:$P$407,"Y") -> 0 | O11: =SUMIFS(O$135:O$407,$C$135:$C$407,$C11,$P$135:$P$407,"Y") -> 0 | Q11: =SUMIFS(Q$135:Q$407,$C$135:$C$407,$C11,$S$135:$S$407,"Y") -> 0 | R11: =SUMIFS(R$135:R$407,$C$135:$C$407,$C11,$S$135:$S$407,"Y") -> 0 | T11: =SUMIFS(T$135:T$407,$C$135:$C$407,$C11,$V$135:$V$407,"Y") -> 0 | U11: =SUMIFS(U$135:U$407,$C$135:$C$407,$C11,$V$135:$V$407,"Y") -> 0
C12: =TRIM(合并试算平衡表!A19) -> △应收分保账款 | E12: =SUMIFS(E$134:E$407,$C$134:$C$407,$C12,$G$134:$G$407,"Y") -> 0 | F12: =SUMIFS(F$134:F$407,$C$134:$C$407,$C12,$G$134:$G$407,"Y") -> 0 | H12: =SUMIFS(H$134:H$407,$C$134:$C$407,$C12,$J$134:$J$407,"Y") -> 0 | I12: =SUMIFS(I$134:I$407,$C$134:$C$407,$C12,$J$134:$J$407,"Y") -> 0 | K12: =SUMIFS(K$134:K$407,$C$134:$C$407,$C12,$M$134:$M$407,"Y") -> 0 | L12: =SUMIFS(L$134:L$407,$C$134:$C$407,$C12,$M$134:$M$407,"Y") -> 0 | N12: =SUMIFS(N$135:N$407,$C$135:$C$407,$C12,$P$135:$P$407,"Y") -> 0 | O12: =SUMIFS(O$135:O$407,$C$135:$C$407,$C12,$P$135:$P$407,"Y") -> 0 | Q12: =SUMIFS(Q$135:Q$407,$C$135:$C$407,$C12,$S$135:$S$407,"Y") -> 0 | R12: =SUMIFS(R$135:R$407,$C$135:$C$407,$C12,$S$135:$S$407,"Y") -> 0 | T12: =SUMIFS(T$135:T$407,$C$135:$C$407,$C12,$V$135:$V$407,"Y") -> 0 | U12: =SUMIFS(U$135:U$407,$C$135:$C$407,$C12,$V$135:$V$407,"Y") -> 0
C13: =TRIM(合并试算平衡表!A20) -> △应收分保合同准备金 | E13: =SUMIFS(E$134:E$407,$C$134:$C$407,$C13,$G$134:$G$407,"Y") -> 0 | F13: =SUMIFS(F$134:F$407,$C$134:$C$407,$C13,$G$134:$G$407,"Y") -> 0 | H13: =SUMIFS(H$134:H$407,$C$134:$C$407,$C13,$J$134:$J$407,"Y") -> 0 | I13: =SUMIFS(I$134:I$407,$C$134:$C$407,$C13,$J$134:$J$407,"Y") -> 0 | K13: =SUMIFS(K$134:K$407,$C$134:$C$407,$C13,$M$134:$M$407,"Y") -> 0 | L13: =SUMIFS(L$134:L$407,$C$134:$C$407,$C13,$M$134:$M$407,"Y") -> 0 | N13: =SUMIFS(N$135:N$407,$C$135:$C$407,$C13,$P$135:$P$407,"Y") -> 0 | O13: =SUMIFS(O$135:O$407,$C$135:$C$407,$C13,$P$135:$P$407,"Y") -> 0 | Q13: =SUMIFS(Q$135:Q$407,$C$135:$C$407,$C13,$S$135:$S$407,"Y") -> 0 | R13: =SUMIFS(R$135:R$407,$C$135:$C$407,$C13,$S$135:$S$407,"Y") -> 0 | T13: =SUMIFS(T$135:T$407,$C$135:$C$407,$C13,$V$135:$V$407,"Y") -> 0 | U13: =SUMIFS(U$135:U$407,$C$135:$C$407,$C13,$V$135:$V$407,"Y") -> 0
C14: =TRIM(合并试算平衡表!A21) -> 应收利息 | E14: =SUMIFS(E$134:E$407,$C$134:$C$407,$C14,$G$134:$G$407,"Y") -> 0 | F14: =SUMIFS(F$134:F$407,$C$134:$C$407,$C14,$G$134:$G$407,"Y") -> 0 | H14: =SUMIFS(H$134:H$407,$C$134:$C$407,$C14,$J$134:$J$407,"Y") -> 0 | I14: =SUMIFS(I$134:I$407,$C$134:$C$407,$C14,$J$134:$J$407,"Y") -> 0 | K14: =SUMIFS(K$134:K$407,$C$134:$C$407,$C14,$M$134:$M$407,"Y") -> 0 | L14: =SUMIFS(L$134:L$407,$C$134:$C$407,$C14,$M$134:$M$407,"Y") -> 0 | N14: =SUMIFS(N$135:N$407,$C$135:$C$407,$C14,$P$135:$P$407,"Y") -> 0 | O14: =SUMIFS(O$135:O$407,$C$135:$C$407,$C14,$P$135:$P$407,"Y") -> 0 | Q14: =SUMIFS(Q$135:Q$407,$C$135:$C$407,$C14,$S$135:$S$407,"Y") -> 0 | R14: =SUMIFS(R$135:R$407,$C$135:$C$407,$C14,$S$135:$S$407,"Y") -> 0 | T14: =SUMIFS(T$135:T$407,$C$135:$C$407,$C14,$V$135:$V$407,"Y") -> 0 | U14: =SUMIFS(U$135:U$407,$C$135:$C$407,$C14,$V$135:$V$407,"Y") -> 0
C15: =TRIM(合并试算平衡表!A22) -> 应收股利 | E15: =SUMIFS(E$134:E$407,$C$134:$C$407,$C15,$G$134:$G$407,"Y") -> 0 | F15: =SUMIFS(F$134:F$407,$C$134:$C$407,$C15,$G$134:$G$407,"Y") -> 0 | H15: =SUMIFS(H$134:H$407,$C$134:$C$407,$C15,$J$134:$J$407,"Y") -> 0 | I15: =SUMIFS(I$134:I$407,$C$134:$C$407,$C15,$J$134:$J$407,"Y") -> 0 | K15: =SUMIFS(K$134:K$407,$C$134:$C$407,$C15,$M$134:$M$407,"Y") -> 0 | L15: =SUMIFS(L$134:L$407,$C$134:$C$407,$C15,$M$134:$M$407,"Y") -> 0 | N15: =SUMIFS(N$135:N$407,$C$135:$C$407,$C15,$P$135:$P$407,"Y") -> 0 | O15: =SUMIFS(O$135:O$407,$C$135:$C$407,$C15,$P$135:$P$407,"Y") -> 0 | Q15: =SUMIFS(Q$135:Q$407,$C$135:$C$407,$C15,$S$135:$S$407,"Y") -> 0 | R15: =SUMIFS(R$135:R$407,$C$135:$C$407,$C15,$S$135:$S$407,"Y") -> 0 | T15: =SUMIFS(T$135:T$407,$C$135:$C$407,$C15,$V$135:$V$407,"Y") -> 0 | U15: =SUMIFS(U$135:U$407,$C$135:$C$407,$C15,$V$135:$V$407,"Y") -> 0
C16: =TRIM(合并试算平衡表!A23) -> 其他应收款 | E16: =SUMIFS(E$134:E$407,$C$134:$C$407,$C16,$G$134:$G$407,"Y") -> 0 | F16: =SUMIFS(F$134:F$407,$C$134:$C$407,$C16,$G$134:$G$407,"Y") -> 0 | H16: =SUMIFS(H$134:H$407,$C$134:$C$407,$C16,$J$134:$J$407,"Y") -> 0 | I16: =SUMIFS(I$134:I$407,$C$134:$C$407,$C16,$J$134:$J$407,"Y") -> 336853 | K16: =SUMIFS(K$134:K$407,$C$134:$C$407,$C16,$M$134:$M$407,"Y") -> 0 | L16: =SUMIFS(L$134:L$407,$C$134:$C$407,$C16,$M$134:$M$407,"Y") -> 1668414.2 | N16: =SUMIFS(N$135:N$407,$C$135:$C$407,$C16,$P$135:$P$407,"Y") -> 0 | O16: =SUMIFS(O$135:O$407,$C$135:$C$407,$C16,$P$135:$P$407,"Y") -> 559382.32 | Q16: =SUMIFS(Q$135:Q$407,$C$135:$C$407,$C16,$S$135:$S$407,"Y") -> 0 | R16: =SUMIFS(R$135:R$407,$C$135:$C$407,$C16,$S$135:$S$407,"Y") -> 0 | T16: =SUMIFS(T$135:T$407,$C$135:$C$407,$C16,$V$135:$V$407,"Y") -> 0 | U16: =SUMIFS(U$135:U$407,$C$135:$C$407,$C16,$V$135:$V$407,"Y") -> 0
C17: =TRIM(合并试算平衡表!A24) -> △买入返售金融资产 | E17: =SUMIFS(E$134:E$407,$C$134:$C$407,$C17,$G$134:$G$407,"Y") -> 0 | F17: =SUMIFS(F$134:F$407,$C$134:$C$407,$C17,$G$134:$G$407,"Y") -> 0 | H17: =SUMIFS(H$134:H$407,$C$134:$C$407,$C17,$J$134:$J$407,"Y") -> 0 | I17: =SUMIFS(I$134:I$407,$C$134:$C$407,$C17,$J$134:$J$407,"Y") -> 0 | K17: =SUMIFS(K$134:K$407,$C$134:$C$407,$C17,$M$134:$M$407,"Y") -> 0 | L17: =SUMIFS(L$134:L$407,$C$134:$C$407,$C17,$M$134:$M$407,"Y") -> 0 | N17: =SUMIFS(N$135:N$407,$C$135:$C$407,$C17,$P$135:$P$407,"Y") -> 0 | O17: =SUMIFS(O$135:O$407,$C$135:$C$407,$C17,$P$135:$P$407,"Y") -> 0 | Q17: =SUMIFS(Q$135:Q$407,$C$135:$C$407,$C17,$S$135:$S$407,"Y") -> 0 | R17: =SUMIFS(R$135:R$407,$C$135:$C$407,$C17,$S$135:$S$407,"Y") -> 0 | T17: =SUMIFS(T$135:T$407,$C$135:$C$407,$C17,$V$135:$V$407,"Y") -> 0 | U17: =SUMIFS(U$135:U$407,$C$135:$C$407,$C17,$V$135:$V$407,"Y") -> 0
C18: =TRIM(合并试算平衡表!A25) -> 存货 | E18: =SUMIFS(E$134:E$407,$C$134:$C$407,$C18,$G$134:$G$407,"Y") -> 0 | F18: =SUMIFS(F$134:F$407,$C$134:$C$407,$C18,$G$134:$G$407,"Y") -> 21888.38 | H18: =SUMIFS(H$134:H$407,$C$134:$C$407,$C18,$J$134:$J$407,"Y") -> 0 | I18: =SUMIFS(I$134:I$407,$C$134:$C$407,$C18,$J$134:$J$407,"Y") -> 44089.49 | K18: =SUMIFS(K$134:K$407,$C$134:$C$407,$C18,$M$134:$M$407,"Y") -> 0 | L18: =SUMIFS(L$134:L$407,$C$134:$C$407,$C18,$M$134:$M$407,"Y") -> 0 | N18: =SUMIFS(N$135:N$407,$C$135:$C$407,$C18,$P$135:$P$407,"Y") -> 0 | O18: =SUMIFS(O$135:O$407,$C$135:$C$407,$C18,$P$135:$P$407,"Y") -> 0 | Q18: =SUMIFS(Q$135:Q$407,$C$135:$C$407,$C18,$S$135:$S$407,"Y") -> 0 | R18: =SUMIFS(R$135:R$407,$C$135:$C$407,$C18,$S$135:$S$407,"Y") -> 0 | T18: =SUMIFS(T$135:T$407,$C$135:$C$407,$C18,$V$135:$V$407,"Y") -> 0 | U18: =SUMIFS(U$135:U$407,$C$135:$C$407,$C18,$V$135:$V$407,"Y") -> 0
C19: =TRIM(合并试算平衡表!A27) -> 划分为持有待售的资产 | E19: =SUMIFS(E$134:E$407,$C$134:$C$407,$C19,$G$134:$G$407,"Y") -> 0 | F19: =SUMIFS(F$134:F$407,$C$134:$C$407,$C19,$G$134:$G$407,"Y") -> 0 | H19: =SUMIFS(H$134:H$407,$C$134:$C$407,$C19,$J$134:$J$407,"Y") -> 0 | I19: =SUMIFS(I$134:I$407,$C$134:$C$407,$C19,$J$134:$J$407,"Y") -> 0 | K19: =SUMIFS(K$134:K$407,$C$134:$C$407,$C19,$M$134:$M$407,"Y") -> 0 | L19: =SUMIFS(L$134:L$407,$C$134:$C$407,$C19,$M$134:$M$407,"Y") -> 0 | N19: =SUMIFS(N$135:N$407,$C$135:$C$407,$C19,$P$135:$P$407,"Y") -> 0 | O19: =SUMIFS(O$135:O$407,$C$135:$C$407,$C19,$P$135:$P$407,"Y") -> 0 | Q19: =SUMIFS(Q$135:Q$407,$C$135:$C$407,$C19,$S$135:$S$407,"Y") -> 0 | R19: =SUMIFS(R$135:R$407,$C$135:$C$407,$C19,$S$135:$S$407,"Y") -> 0 | T19: =SUMIFS(T$135:T$407,$C$135:$C$407,$C19,$V$135:$V$407,"Y") -> 0 | U19: =SUMIFS(U$135:U$407,$C$135:$C$407,$C19,$V$135:$V$407,"Y") -> 0
C20: =TRIM(合并试算平衡表!A28) -> 一年内到期的非流动资产 | E20: =SUMIFS(E$134:E$407,$C$134:$C$407,$C20,$G$134:$G$407,"Y") -> 0 | F20: =SUMIFS(F$134:F$407,$C$134:$C$407,$C20,$G$134:$G$407,"Y") -> 0 | H20: =SUMIFS(H$134:H$407,$C$134:$C$407,$C20,$J$134:$J$407,"Y") -> 0 | I20: =SUMIFS(I$134:I$407,$C$134:$C$407,$C20,$J$134:$J$407,"Y") -> 0 | K20: =SUMIFS(K$134:K$407,$C$134:$C$407,$C20,$M$134:$M$407,"Y") -> 0 | L20: =SUMIFS(L$134:L$407,$C$134:$C$407,$C20,$M$134:$M$407,"Y") -> 0 | N20: =SUMIFS(N$135:N$407,$C$135:$C$407,$C20,$P$135:$P$407,"Y") -> 0 | O20: =SUMIFS(O$135:O$407,$C$135:$C$407,$C20,$P$135:$P$407,"Y") -> 0 | Q20: =SUMIFS(Q$135:Q$407,$C$135:$C$407,$C20,$S$135:$S$407,"Y") -> 0 | R20: =SUMIFS(R$135:R$407,$C$135:$C$407,$C20,$S$135:$S$407,"Y") -> 0 | T20: =SUMIFS(T$135:T$407,$C$135:$C$407,$C20,$V$135:$V$407,"Y") -> 0 | U20: =SUMIFS(U$135:U$407,$C$135:$C$407,$C20,$V$135:$V$407,"Y") -> 0
C21: =TRIM(合并试算平衡表!A29) -> 其他流动资产 | E21: =SUMIFS(E$134:E$407,$C$134:$C$407,$C21,$G$134:$G$407,"Y") -> 0 | F21: =SUMIFS(F$134:F$407,$C$134:$C$407,$C21,$G$134:$G$407,"Y") -> 0 | H21: =SUMIFS(H$134:H$407,$C$134:$C$407,$C21,$J$134:$J$407,"Y") -> 0 | I21: =SUMIFS(I$134:I$407,$C$134:$C$407,$C21,$J$134:$J$407,"Y") -> 0 | K21: =SUMIFS(K$134:K$407,$C$134:$C$407,$C21,$M$134:$M$407,"Y") -> 0 | L21: =SUMIFS(L$134:L$407,$C$134:$C$407,$C21,$M$134:$M$407,"Y") -> 0 | N21: =SUMIFS(N$135:N$407,$C$135:$C$407,$C21,$P$135:$P$407,"Y") -> 0 | O21: =SUMIFS(O$135:O$407,$C$135:$C$407,$C21,$P$135:$P$407,"Y") -> 0 | Q21: =SUMIFS(Q$135:Q$407,$C$135:$C$407,$C21,$S$135:$S$407,"Y") -> 0 | R21: =SUMIFS(R$135:R$407,$C$135:$C$407,$C21,$S$135:$S$407,"Y") -> 0 | T21: =SUMIFS(T$135:T$407,$C$135:$C$407,$C21,$V$135:$V$407,"Y") -> 0 | U21: =SUMIFS(U$135:U$407,$C$135:$C$407,$C21,$V$135:$V$407,"Y") -> 0
C22: =TRIM(合并试算平衡表!A32) -> △发放贷款及垫款 | E22: =SUMIFS(E$134:E$407,$C$134:$C$407,$C22,$G$134:$G$407,"Y") -> 0 | F22: =SUMIFS(F$134:F$407,$C$134:$C$407,$C22,$G$134:$G$407,"Y") -> 0 | H22: =SUMIFS(H$134:H$407,$C$134:$C$407,$C22,$J$134:$J$407,"Y") -> 0 | I22: =SUMIFS(I$134:I$407,$C$134:$C$407,$C22,$J$134:$J$407,"Y") -> 0 | K22: =SUMIFS(K$134:K$407,$C$134:$C$407,$C22,$M$134:$M$407,"Y") -> 0 | L22: =SUMIFS(L$134:L$407,$C$134:$C$407,$C22,$M$134:$M$407,"Y") -> 0 | N22: =SUMIFS(N$135:N$407,$C$135:$C$407,$C22,$P$135:$P$407,"Y") -> 0 | O22: =SUMIFS(O$135:O$407,$C$135:$C$407,$C22,$P$135:$P$407,"Y") -> 0 | Q22: =SUMIFS(Q$135:Q$407,$C$135:$C$407,$C22,$S$135:$S$407,"Y") -> 0 | R22: =SUMIFS(R$135:R$407,$C$135:$C$407,$C22,$S$135:$S$407,"Y") -> 0 | T22: =SUMIFS(T$135:T$407,$C$135:$C$407,$C22,$V$135:$V$407,"Y") -> 0 | U22: =SUMIFS(U$135:U$407,$C$135:$C$407,$C22,$V$135:$V$407,"Y") -> 0
C23: =TRIM(合并试算平衡表!A33) -> 可供出售金融资产 | E23: =SUMIFS(E$134:E$407,$C$134:$C$407,$C23,$G$134:$G$407,"Y") -> 0 | F23: =SUMIFS(F$134:F$407,$C$134:$C$407,$C23,$G$134:$G$407,"Y") -> 0 | H23: =SUMIFS(H$134:H$407,$C$134:$C$407,$C23,$J$134:$J$407,"Y") -> 0 | I23: =SUMIFS(I$134:I$407,$C$134:$C$407,$C23,$J$134:$J$407,"Y") -> 0 | K23: =SUMIFS(K$134:K$407,$C$134:$C$407,$C23,$M$134:$M$407,"Y") -> 0 | L23: =SUMIFS(L$134:L$407,$C$134:$C$407,$C23,$M$134:$M$407,"Y") -> 0 | N23: =SUMIFS(N$135:N$407,$C$135:$C$407,$C23,$P$135:$P$407,"Y") -> 0 | O23: =SUMIFS(O$135:O$407,$C$135:$C$407,$C23,$P$135:$P$407,"Y") -> 0 | Q23: =SUMIFS(Q$135:Q$407,$C$135:$C$407,$C23,$S$135:$S$407,"Y") -> 0 | R23: =SUMIFS(R$135:R$407,$C$135:$C$407,$C23,$S$135:$S$407,"Y") -> 0 | T23: =SUMIFS(T$135:T$407,$C$135:$C$407,$C23,$V$135:$V$407,"Y") -> 0 | U23: =SUMIFS(U$135:U$407,$C$135:$C$407,$C23,$V$135:$V$407,"Y") -> 0
C24: =TRIM(合并试算平衡表!A34) -> 持有至到期投资 | E24: =SUMIFS(E$134:E$407,$C$134:$C$407,$C24,$G$134:$G$407,"Y") -> 0 | F24: =SUMIFS(F$134:F$407,$C$134:$C$407,$C24,$G$134:$G$407,"Y") -> 0 | H24: =SUMIFS(H$134:H$407,$C$134:$C$407,$C24,$J$134:$J$407,"Y") -> 0 | I24: =SUMIFS(I$134:I$407,$C$134:$C$407,$C24,$J$134:$J$407,"Y") -> 0 | K24: =SUMIFS(K$134:K$407,$C$134:$C$407,$C24,$M$134:$M$407,"Y") -> 0 | L24: =SUMIFS(L$134:L$407,$C$134:$C$407,$C24,$M$134:$M$407,"Y") -> 0 | N24: =SUMIFS(N$135:N$407,$C$135:$C$407,$C24,$P$135:$P$407,"Y") -> 0 | O24: =SUMIFS(O$135:O$407,$C$135:$C$407,$C24,$P$135:$P$407,"Y") -> 0 | Q24: =SUMIFS(Q$135:Q$407,$C$135:$C$407,$C24,$S$135:$S$407,"Y") -> 0 | R24: =SUMIFS(R$135:R$407,$C$135:$C$407,$C24,$S$135:$S$407,"Y") -> 0 | T24: =SUMIFS(T$135:T$407,$C$135:$C$407,$C24,$V$135:$V$407,"Y") -> 0 | U24: =SUMIFS(U$135:U$407,$C$135:$C$407,$C24,$V$135:$V$407,"Y") -> 0
C25: =TRIM(合并试算平衡表!A35) -> 长期应收款 | E25: =SUMIFS(E$134:E$407,$C$134:$C$407,$C25,$G$134:$G$407,"Y") -> 0 | F25: =SUMIFS(F$134:F$407,$C$134:$C$407,$C25,$G$134:$G$407,"Y") -> 0 | H25: =SUMIFS(H$134:H$407,$C$134:$C$407,$C25,$J$134:$J$407,"Y") -> 0 | I25: =SUMIFS(I$134:I$407,$C$134:$C$407,$C25,$J$134:$J$407,"Y") -> 0 | K25: =SUMIFS(K$134:K$407,$C$134:$C$407,$C25,$M$134:$M$407,"Y") -> 0 | L25: =SUMIFS(L$134:L$407,$C$134:$C$407,$C25,$M$134:$M$407,"Y") -> 0 | N25: =SUMIFS(N$135:N$407,$C$135:$C$407,$C25,$P$135:$P$407,"Y") -> 0 | O25: =SUMIFS(O$135:O$407,$C$135:$C$407,$C25,$P$135:$P$407,"Y") -> 0 | Q25: =SUMIFS(Q$135:Q$407,$C$135:$C$407,$C25,$S$135:$S$407,"Y") -> 0 | R25: =SUMIFS(R$135:R$407,$C$135:$C$407,$C25,$S$135:$S$407,"Y") -> 0 | T25: =SUMIFS(T$135:T$407,$C$135:$C$407,$C25,$V$135:$V$407,"Y") -> 0 | U25: =SUMIFS(U$135:U$407,$C$135:$C$407,$C25,$V$135:$V$407,"Y") -> 0
C26: =TRIM(合并试算平衡表!A36) -> 长期股权投资 | E26: =SUMIFS(E$134:E$407,$C$134:$C$407,$C26,$G$134:$G$407,"Y") -> -14518786 | F26: =SUMIFS(F$134:F$407,$C$134:$C$407,$C26,$G$134:$G$407,"Y") -> 2.4591021e+08 | H26: =SUMIFS(H$134:H$407,$C$134:$C$407,$C26,$J$134:$J$407,"Y") -> -9951097.7 | I26: =SUMIFS(I$134:I$407,$C$134:$C$407,$C26,$J$134:$J$407,"Y") -> 2.5047789e+08 | K26: =SUMIFS(K$134:K$407,$C$134:$C$407,$C26,$M$134:$M$407,"Y") -> 683972.71 | L26: =SUMIFS(L$134:L$407,$C$134:$C$407,$C26,$M$134:$M$407,"Y") -> 32683973 | N26: =SUMIFS(N$135:N$407,$C$135:$C$407,$C26,$P$135:$P$407,"Y") -> 1626803.3 | O26: =SUMIFS(O$135:O$407,$C$135:$C$407,$C26,$P$135:$P$407,"Y") -> 35385058 | Q26: =SUMIFS(Q$135:Q$407,$C$135:$C$407,$C26,$S$135:$S$407,"Y") -> 0 | R26: =SUMIFS(R$135:R$407,$C$135:$C$407,$C26,$S$135:$S$407,"Y") -> 0 | T26: =SUMIFS(T$135:T$407,$C$135:$C$407,$C26,$V$135:$V$407,"Y") -> 0 | U26: =SUMIFS(U$135:U$407,$C$135:$C$407,$C26,$V$135:$V$407,"Y") -> 0
C27: =TRIM(合并试算平衡表!A39) -> 投资性房地产 | E27: =SUMIFS(E$134:E$407,$C$134:$C$407,$C27,$G$134:$G$407,"Y") -> 0 | F27: =SUMIFS(F$134:F$407,$C$134:$C$407,$C27,$G$134:$G$407,"Y") -> 0 | H27: =SUMIFS(H$134:H$407,$C$134:$C$407,$C27,$J$134:$J$407,"Y") -> 0 | I27: =SUMIFS(I$134:I$407,$C$134:$C$407,$C27,$J$134:$J$407,"Y") -> 0 | K27: =SUMIFS(K$134:K$407,$C$134:$C$407,$C27,$M$134:$M$407,"Y") -> 0 | L27: =SUMIFS(L$134:L$407,$C$134:$C$407,$C27,$M$134:$M$407,"Y") -> 0 | N27: =SUMIFS(N$135:N$407,$C$135:$C$407,$C27,$P$135:$P$407,"Y") -> 0 | O27: =SUMIFS(O$135:O$407,$C$135:$C$407,$C27,$P$135:$P$407,"Y") -> 0 | Q27: =SUMIFS(Q$135:Q$407,$C$135:$C$407,$C27,$S$135:$S$407,"Y") -> 0 | R27: =SUMIFS(R$135:R$407,$C$135:$C$407,$C27,$S$135:$S$407,"Y") -> 0 | T27: =SUMIFS(T$135:T$407,$C$135:$C$407,$C27,$V$135:$V$407,"Y") -> 0 | U27: =SUMIFS(U$135:U$407,$C$135:$C$407,$C27,$V$135:$V$407,"Y") -> 0
C28: =TRIM(合并试算平衡表!A40) -> 固定资产 | E28: =SUMIFS(E$134:E$407,$C$134:$C$407,$C28,$G$134:$G$407,"Y") -> 0 | F28: =SUMIFS(F$134:F$407,$C$134:$C$407,$C28,$G$134:$G$407,"Y") -> 0 | H28: =SUMIFS(H$134:H$407,$C$134:$C$407,$C28,$J$134:$J$407,"Y") -> 0 | I28: =SUMIFS(I$134:I$407,$C$134:$C$407,$C28,$J$134:$J$407,"Y") -> 0 | K28: =SUMIFS(K$134:K$407,$C$134:$C$407,$C28,$M$134:$M$407,"Y") -> 0 | L28: =SUMIFS(L$134:L$407,$C$134:$C$407,$C28,$M$134:$M$407,"Y") -> 0 | N28: =SUMIFS(N$135:N$407,$C$135:$C$407,$C28,$P$135:$P$407,"Y") -> 0 | O28: =SUMIFS(O$135:O$407,$C$135:$C$407,$C28,$P$135:$P$407,"Y") -> 0 | Q28: =SUMIFS(Q$135:Q$407,$C$135:$C$407,$C28,$S$135:$S$407,"Y") -> 0 | R28: =SUMIFS(R$135:R$407,$C$135:$C$407,$C28,$S$135:$S$407,"Y") -> 0 | T28: =SUMIFS(T$135:T$407,$C$135:$C$407,$C28,$V$135:$V$407,"Y") -> 0 | U28: =SUMIFS(U$135:U$407,$C$135:$C$407,$C28,$V$135:$V$407,"Y") -> 0
C29: 累计折旧 | E29: =SUMIFS(E$134:E$407,$C$134:$C$407,$C29,$G$134:$G$407,"Y") -> 0 | F29: =SUMIFS(F$134:F$407,$C$134:$C$407,$C29,$G$134:$G$407,"Y") -> 0 | H29: =SUMIFS(H$134:H$407,$C$134:$C$407,$C29,$J$134:$J$407,"Y") -> 0 | I29: =SUMIFS(I$134:I$407,$C$134:$C$407,$C29,$J$134:$J$407,"Y") -> 0 | K29: =SUMIFS(K$134:K$407,$C$134:$C$407,$C29,$M$134:$M$407,"Y") -> 0 | L29: =SUMIFS(L$134:L$407,$C$134:$C$407,$C29,$M$134:$M$407,"Y") -> 0 | N29: =SUMIFS(N$135:N$407,$C$135:$C$407,$C29,$P$135:$P$407,"Y") -> 0 | O29: =SUMIFS(O$135:O$407,$C$135:$C$407,$C29,$P$135:$P$407,"Y") -> 0 | Q29: =SUMIFS(Q$135:Q$407,$C$135:$C$407,$C29,$S$135:$S$407,"Y") -> 0 | R29: =SUMIFS(R$135:R$407,$C$135:$C$407,$C29,$S$135:$S$407,"Y") -> 0 | T29: =SUMIFS(T$135:T$407,$C$135:$C$407,$C29,$V$135:$V$407,"Y") -> 0 | U29: =SUMIFS(U$135:U$407,$C$135:$C$407,$C29,$V$135:$V$407,"Y") -> 0
C30: 固定资产减值准备 | E30: =SUMIFS(E$134:E$407,$C$134:$C$407,$C30,$G$134:$G$407,"Y") -> 0 | F30: =SUMIFS(F$134:F$407,$C$134:$C$407,$C30,$G$134:$G$407,"Y") -> 0 | H30: =SUMIFS(H$134:H$407,$C$134:$C$407,$C30,$J$134:$J$407,"Y") -> 0 | I30: =SUMIFS(I$134:I$407,$C$134:$C$407,$C30,$J$134:$J$407,"Y") -> 0 | K30: =SUMIFS(K$134:K$407,$C$134:$C$407,$C30,$M$134:$M$407,"Y") -> 0 | L30: =SUMIFS(L$134:L$407,$C$134:$C$407,$C30,$M$134:$M$407,"Y") -> 0 | N30: =SUMIFS(N$135:N$407,$C$135:$C$407,$C30,$P$135:$P$407,"Y") -> 0 | O30: =SUMIFS(O$135:O$407,$C$135:$C$407,$C30,$P$135:$P$407,"Y") -> 0 | Q30: =SUMIFS(Q$135:Q$407,$C$135:$C$407,$C30,$S$135:$S$407,"Y") -> 0 | R30: =SUMIFS(R$135:R$407,$C$135:$C$407,$C30,$S$135:$S$407,"Y") -> 0 | T30: =SUMIFS(T$135:T$407,$C$135:$C$407,$C30,$V$135:$V$407,"Y") -> 0 | U30: =SUMIFS(U$135:U$407,$C$135:$C$407,$C30,$V$135:$V$407,"Y") -> 0
C31: =TRIM(合并试算平衡表!A45) -> 在建工程 | E31: =SUMIFS(E$134:E$407,$C$134:$C$407,$C31,$G$134:$G$407,"Y") -> 0 | F31: =SUMIFS(F$134:F$407,$C$134:$C$407,$C31,$G$134:$G$407,"Y") -> 0 | H31: =SUMIFS(H$134:H$407,$C$134:$C$407,$C31,$J$134:$J$407,"Y") -> 0 | I31: =SUMIFS(I$134:I$407,$C$134:$C$407,$C31,$J$134:$J$407,"Y") -> 0 | K31: =SUMIFS(K$134:K$407,$C$134:$C$407,$C31,$M$134:$M$407,"Y") -> 0 | L31: =SUMIFS(L$134:L$407,$C$134:$C$407,$C31,$M$134:$M$407,"Y") -> 0 | N31: =SUMIFS(N$135:N$407,$C$135:$C$407,$C31,$P$135:$P$407,"Y") -> 0 | O31: =SUMIFS(O$135:O$407,$C$135:$C$407,$C31,$P$135:$P$407,"Y") -> 0 | Q31: =SUMIFS(Q$135:Q$407,$C$135:$C$407,$C31,$S$135:$S$407,"Y") -> 0 | R31: =SUMIFS(R$135:R$407,$C$135:$C$407,$C31,$S$135:$S$407,"Y") -> 0 | T31: =SUMIFS(T$135:T$407,$C$135:$C$407,$C31,$V$135:$V$407,"Y") -> 0 | U31: =SUMIFS(U$135:U$407,$C$135:$C$407,$C31,$V$135:$V$407,"Y") -> 0
C32: =TRIM(合并试算平衡表!A46) -> 工程物资 | E32: =SUMIFS(E$134:E$407,$C$134:$C$407,$C32,$G$134:$G$407,"Y") -> 0 | F32: =SUMIFS(F$134:F$407,$C$134:$C$407,$C32,$G$134:$G$407,"Y") -> 0 | H32: =SUMIFS(H$134:H$407,$C$134:$C$407,$C32,$J$134:$J$407,"Y") -> 0 | I32: =SUMIFS(I$134:I$407,$C$134:$C$407,$C32,$J$134:$J$407,"Y") -> 0 | K32: =SUMIFS(K$134:K$407,$C$134:$C$407,$C32,$M$134:$M$407,"Y") -> 0 | L32: =SUMIFS(L$134:L$407,$C$134:$C$407,$C32,$M$134:$M$407,"Y") -> 0 | N32: =SUMIFS(N$135:N$407,$C$135:$C$407,$C32,$P$135:$P$407,"Y") -> 0 | O32: =SUMIFS(O$135:O$407,$C$135:$C$407,$C32,$P$135:$P$407,"Y") -> 0 | Q32: =SUMIFS(Q$135:Q$407,$C$135:$C$407,$C32,$S$135:$S$407,"Y") -> 0 | R32: =SUMIFS(R$135:R$407,$C$135:$C$407,$C32,$S$135:$S$407,"Y") -> 0 | T32: =SUMIFS(T$135:T$407,$C$135:$C$407,$C32,$V$135:$V$407,"Y") -> 0 | U32: =SUMIFS(U$135:U$407,$C$135:$C$407,$C32,$V$135:$V$407,"Y") -> 0
C33: =TRIM(合并试算平衡表!A47) -> 固定资产清理 | E33: =SUMIFS(E$134:E$407,$C$134:$C$407,$C33,$G$134:$G$407,"Y") -> 0 | F33: =SUMIFS(F$134:F$407,$C$134:$C$407,$C33,$G$134:$G$407,"Y") -> 0 | H33: =SUMIFS(H$134:H$407,$C$134:$C$407,$C33,$J$134:$J$407,"Y") -> 0 | I33: =SUMIFS(I$134:I$407,$C$134:$C$407,$C33,$J$134:$J$407,"Y") -> 0 | K33: =SUMIFS(K$134:K$407,$C$134:$C$407,$C33,$M$134:$M$407,"Y") -> 0 | L33: =SUMIFS(L$134:L$407,$C$134:$C$407,$C33,$M$134:$M$407,"Y") -> 0 | N33: =SUMIFS(N$135:N$407,$C$135:$C$407,$C33,$P$135:$P$407,"Y") -> 0 | O33: =SUMIFS(O$135:O$407,$C$135:$C$407,$C33,$P$135:$P$407,"Y") -> 0 | Q33: =SUMIFS(Q$135:Q$407,$C$135:$C$407,$C33,$S$135:$S$407,"Y") -> 0 | R33: =SUMIFS(R$135:R$407,$C$135:$C$407,$C33,$S$135:$S$407,"Y") -> 0 | T33: =SUMIFS(T$135:T$407,$C$135:$C$407,$C33,$V$135:$V$407,"Y") -> 0 | U33: =SUMIFS(U$135:U$407,$C$135:$C$407,$C33,$V$135:$V$407,"Y") -> 0
C34: =TRIM(合并试算平衡表!A48) -> 生产性生物资产 | E34: =SUMIFS(E$134:E$407,$C$134:$C$407,$C34,$G$134:$G$407,"Y") -> 0 | F34: =SUMIFS(F$134:F$407,$C$134:$C$407,$C34,$G$134:$G$407,"Y") -> 0 | H34: =SUMIFS(H$134:H$407,$C$134:$C$407,$C34,$J$134:$J$407,"Y") -> 0 | I34: =SUMIFS(I$134:I$407,$C$134:$C$407,$C34,$J$134:$J$407,"Y") -> 0 | K34: =SUMIFS(K$134:K$407,$C$134:$C$407,$C34,$M$134:$M$407,"Y") -> 0 | L34: =SUMIFS(L$134:L$407,$C$134:$C$407,$C34,$M$134:$M$407,"Y") -> 0 | N34: =SUMIFS(N$135:N$407,$C$135:$C$407,$C34,$P$135:$P$407,"Y") -> 0 | O34: =SUMIFS(O$135:O$407,$C$135:$C$407,$C34,$P$135:$P$407,"Y") -> 0 | Q34: =SUMIFS(Q$135:Q$407,$C$135:$C$407,$C34,$S$135:$S$407,"Y") -> 0 | R34: =SUMIFS(R$135:R$407,$C$135:$C$407,$C34,$S$135:$S$407,"Y") -> 0 | T34: =SUMIFS(T$135:T$407,$C$135:$C$407,$C34,$V$135:$V$407,"Y") -> 0 | U34: =SUMIFS(U$135:U$407,$C$135:$C$407,$C34,$V$135:$V$407,"Y") -> 0
C35: =TRIM(合并试算平衡表!A49) -> 油气资产 | E35: =SUMIFS(E$134:E$407,$C$134:$C$407,$C35,$G$134:$G$407,"Y") -> 0 | F35: =SUMIFS(F$134:F$407,$C$134:$C$407,$C35,$G$134:$G$407,"Y") -> 0 | H35: =SUMIFS(H$134:H$407,$C$134:$C$407,$C35,$J$134:$J$407,"Y") -> 0 | I35: =SUMIFS(I$134:I$407,$C$134:$C$407,$C35,$J$134:$J$407,"Y") -> 0 | K35: =SUMIFS(K$134:K$407,$C$134:$C$407,$C35,$M$134:$M$407,"Y") -> 0 | L35: =SUMIFS(L$134:L$407,$C$134:$C$407,$C35,$M$134:$M$407,"Y") -> 0 | N35: =SUMIFS(N$135:N$407,$C$135:$C$407,$C35,$P$135:$P$407,"Y") -> 0 | O35: =SUMIFS(O$135:O$407,$C$135:$C$407,$C35,$P$135:$P$407,"Y") -> 0 | Q35: =SUMIFS(Q$135:Q$407,$C$135:$C$407,$C35,$S$135:$S$407,"Y") -> 0 | R35: =SUMIFS(R$135:R$407,$C$135:$C$407,$C35,$S$135:$S$407,"Y") -> 0 | T35: =SUMIFS(T$135:T$407,$C$135:$C$407,$C35,$V$135:$V$407,"Y") -> 0 | U35: =SUMIFS(U$135:U$407,$C$135:$C$407,$C35,$V$135:$V$407,"Y") -> 0
C36: =TRIM(合并试算平衡表!A50) -> 无形资产 | E36: =SUMIFS(E$134:E$407,$C$134:$C$407,$C36,$G$134:$G$407,"Y") -> 0 | F36: =SUMIFS(F$134:F$407,$C$134:$C$407,$C36,$G$134:$G$407,"Y") -> 0 | H36: =SUMIFS(H$134:H$407,$C$134:$C$407,$C36,$J$134:$J$407,"Y") -> 0 | I36: =SUMIFS(I$134:I$407,$C$134:$C$407,$C36,$J$134:$J$407,"Y") -> 0 | K36: =SUMIFS(K$134:K$407,$C$134:$C$407,$C36,$M$134:$M$407,"Y") -> 0 | L36: =SUMIFS(L$134:L$407,$C$134:$C$407,$C36,$M$134:$M$407,"Y") -> 0 | N36: =SUMIFS(N$135:N$407,$C$135:$C$407,$C36,$P$135:$P$407,"Y") -> 0 | O36: =SUMIFS(O$135:O$407,$C$135:$C$407,$C36,$P$135:$P$407,"Y") -> 0 | Q36: =SUMIFS(Q$135:Q$407,$C$135:$C$407,$C36,$S$135:$S$407,"Y") -> 0 | R36: =SUMIFS(R$135:R$407,$C$135:$C$407,$C36,$S$135:$S$407,"Y") -> 0 | T36: =SUMIFS(T$135:T$407,$C$135:$C$407,$C36,$V$135:$V$407,"Y") -> 0 | U36: =SUMIFS(U$135:U$407,$C$135:$C$407,$C36,$V$135:$V$407,"Y") -> 0
C37: =TRIM(合并试算平衡表!A51) -> 开发支出 | E37: =SUMIFS(E$134:E$407,$C$134:$C$407,$C37,$G$134:$G$407,"Y") -> 0 | F37: =SUMIFS(F$134:F$407,$C$134:$C$407,$C37,$G$134:$G$407,"Y") -> 0 | H37: =SUMIFS(H$134:H$407,$C$134:$C$407,$C37,$J$134:$J$407,"Y") -> 0 | I37: =SUMIFS(I$134:I$407,$C$134:$C$407,$C37,$J$134:$J$407,"Y") -> 0 | K37: =SUMIFS(K$134:K$407,$C$134:$C$407,$C37,$M$134:$M$407,"Y") -> 0 | L37: =SUMIFS(L$134:L$407,$C$134:$C$407,$C37,$M$134:$M$407,"Y") -> 0 | N37: =SUMIFS(N$135:N$407,$C$135:$C$407,$C37,$P$135:$P$407,"Y") -> 0 | O37: =SUMIFS(O$135:O$407,$C$135:$C$407,$C37,$P$135:$P$407,"Y") -> 0 | Q37: =SUMIFS(Q$135:Q$407,$C$135:$C$407,$C37,$S$135:$S$407,"Y") -> 0 | R37: =SUMIFS(R$135:R$407,$C$135:$C$407,$C37,$S$135:$S$407,"Y") -> 0 | T37: =SUMIFS(T$135:T$407,$C$135:$C$407,$C37,$V$135:$V$407,"Y") -> 0 | U37: =SUMIFS(U$135:U$407,$C$135:$C$407,$C37,$V$135:$V$407,"Y") -> 0
C38: =TRIM(合并试算平衡表!A52) -> 商誉 | E38: =SUMIFS(E$134:E$407,$C$134:$C$407,$C38,$G$134:$G$407,"Y") -> 6070777.8 | F38: =SUMIFS(F$134:F$407,$C$134:$C$407,$C38,$G$134:$G$407,"Y") -> 2027402.3 | H38: =SUMIFS(H$134:H$407,$C$134:$C$407,$C38,$J$134:$J$407,"Y") -> 6070777.8 | I38: =SUMIFS(I$134:I$407,$C$134:$C$407,$C38,$J$134:$J$407,"Y") -> 1259075.9 | K38: =SUMIFS(K$134:K$407,$C$134:$C$407,$C38,$M$134:$M$407,"Y") -> 6070777.8 | L38: =SUMIFS(L$134:L$407,$C$134:$C$407,$C38,$M$134:$M$407,"Y") -> 0 | N38: =SUMIFS(N$135:N$407,$C$135:$C$407,$C38,$P$135:$P$407,"Y") -> 6070777.8 | O38: =SUMIFS(O$135:O$407,$C$135:$C$407,$C38,$P$135:$P$407,"Y") -> 0 | Q38: =SUMIFS(Q$135:Q$407,$C$135:$C$407,$C38,$S$135:$S$407,"Y") -> 0 | R38: =SUMIFS(R$135:R$407,$C$135:$C$407,$C38,$S$135:$S$407,"Y") -> 0 | T38: =SUMIFS(T$135:T$407,$C$135:$C$407,$C38,$V$135:$V$407,"Y") -> 0 | U38: =SUMIFS(U$135:U$407,$C$135:$C$407,$C38,$V$135:$V$407,"Y") -> 0
C39: =TRIM(合并试算平衡表!A53) -> 长期待摊费用 | E39: =SUMIFS(E$134:E$407,$C$134:$C$407,$C39,$G$134:$G$407,"Y") -> 0 | F39: =SUMIFS(F$134:F$407,$C$134:$C$407,$C39,$G$134:$G$407,"Y") -> 0 | H39: =SUMIFS(H$134:H$407,$C$134:$C$407,$C39,$J$134:$J$407,"Y") -> 0 | I39: =SUMIFS(I$134:I$407,$C$134:$C$407,$C39,$J$134:$J$407,"Y") -> 0 | K39: =SUMIFS(K$134:K$407,$C$134:$C$407,$C39,$M$134:$M$407,"Y") -> 0 | L39: =SUMIFS(L$134:L$407,$C$134:$C$407,$C39,$M$134:$M$407,"Y") -> 0 | N39: =SUMIFS(N$135:N$407,$C$135:$C$407,$C39,$P$135:$P$407,"Y") -> 0 | O39: =SUMIFS(O$135:O$407,$C$135:$C$407,$C39,$P$135:$P$407,"Y") -> 0 | Q39: =SUMIFS(Q$135:Q$407,$C$135:$C$407,$C39,$S$135:$S$407,"Y") -> 0 | R39: =SUMIFS(R$135:R$407,$C$135:$C$407,$C39,$S$135:$S$407,"Y") -> 0 | T39: =SUMIFS(T$135:T$407,$C$135:$C$407,$C39,$V$135:$V$407,"Y") -> 0 | U39: =SUMIFS(U$135:U$407,$C$135:$C$407,$C39,$V$135:$V$407,"Y") -> 0
C40: =TRIM(合并试算平衡表!A54) -> 递延所得税资产 | E40: =SUMIFS(E$134:E$407,$C$134:$C$407,$C40,$G$134:$G$407,"Y") -> 0 | F40: =SUMIFS(F$134:F$407,$C$134:$C$407,$C40,$G$134:$G$407,"Y") -> 0 | H40: =SUMIFS(H$134:H$407,$C$134:$C$407,$C40,$J$134:$J$407,"Y") -> 0 | I40: =SUMIFS(I$134:I$407,$C$134:$C$407,$C40,$J$134:$J$407,"Y") -> 0 | K40: =SUMIFS(K$134:K$407,$C$134:$C$407,$C40,$M$134:$M$407,"Y") -> 0 | L40: =SUMIFS(L$134:L$407,$C$134:$C$407,$C40,$M$134:$M$407,"Y") -> 0 | N40: =SUMIFS(N$135:N$407,$C$135:$C$407,$C40,$P$135:$P$407,"Y") -> 0 | O40: =SUMIFS(O$135:O$407,$C$135:$C$407,$C40,$P$135:$P$407,"Y") -> 0 | Q40: =SUMIFS(Q$135:Q$407,$C$135:$C$407,$C40,$S$135:$S$407,"Y") -> 0 | R40: =SUMIFS(R$135:R$407,$C$135:$C$407,$C40,$S$135:$S$407,"Y") -> 0 | T40: =SUMIFS(T$135:T$407,$C$135:$C$407,$C40,$V$135:$V$407,"Y") -> 0 | U40: =SUMIFS(U$135:U$407,$C$135:$C$407,$C40,$V$135:$V$407,"Y") -> 0
C41: =TRIM(合并试算平衡表!A55) -> 其他非流动资产 | E41: =SUMIFS(E$134:E$407,$C$134:$C$407,$C41,$G$134:$G$407,"Y") -> 0 | F41: =SUMIFS(F$134:F$407,$C$134:$C$407,$C41,$G$134:$G$407,"Y") -> 0 | H41: =SUMIFS(H$134:H$407,$C$134:$C$407,$C41,$J$134:$J$407,"Y") -> 0 | I41: =SUMIFS(I$134:I$407,$C$134:$C$407,$C41,$J$134:$J$407,"Y") -> 0 | K41: =SUMIFS(K$134:K$407,$C$134:$C$407,$C41,$M$134:$M$407,"Y") -> 0 | L41: =SUMIFS(L$134:L$407,$C$134:$C$407,$C41,$M$134:$M$407,"Y") -> 0 | N41: =SUMIFS(N$135:N$407,$C$135:$C$407,$C41,$P$135:$P$407,"Y") -> 0 | O41: =SUMIFS(O$135:O$407,$C$135:$C$407,$C41,$P$135:$P$407,"Y") -> 0 | Q41: =SUMIFS(Q$135:Q$407,$C$135:$C$407,$C41,$S$135:$S$407,"Y") -> 0 | R41: =SUMIFS(R$135:R$407,$C$135:$C$407,$C41,$S$135:$S$407,"Y") -> 0 | T41: =SUMIFS(T$135:T$407,$C$135:$C$407,$C41,$V$135:$V$407,"Y") -> 0 | U41: =SUMIFS(U$135:U$407,$C$135:$C$407,$C41,$V$135:$V$407,"Y") -> 0
C42: =TRIM(合并试算平衡表!A64) -> 短期借款 | E42: =SUMIFS(E$134:E$407,$C$134:$C$407,$C42,$G$134:$G$407,"Y") -> 0 | F42: =SUMIFS(F$134:F$407,$C$134:$C$407,$C42,$G$134:$G$407,"Y") -> 0 | H42: =SUMIFS(H$134:H$407,$C$134:$C$407,$C42,$J$134:$J$407,"Y") -> 0 | I42: =SUMIFS(I$134:I$407,$C$134:$C$407,$C42,$J$134:$J$407,"Y") -> 0 | K42: =SUMIFS(K$134:K$407,$C$134:$C$407,$C42,$M$134:$M$407,"Y") -> 0 | L42: =SUMIFS(L$134:L$407,$C$134:$C$407,$C42,$M$134:$M$407,"Y") -> 0 | N42: =SUMIFS(N$135:N$407,$C$135:$C$407,$C42,$P$135:$P$407,"Y") -> 0 | O42: =SUMIFS(O$135:O$407,$C$135:$C$407,$C42,$P$135:$P$407,"Y") -> 0 | Q42: =SUMIFS(Q$135:Q$407,$C$135:$C$407,$C42,$S$135:$S$407,"Y") -> 0 | R42: =SUMIFS(R$135:R$407,$C$135:$C$407,$C42,$S$135:$S$407,"Y") -> 0 | T42: =SUMIFS(T$135:T$407,$C$135:$C$407,$C42,$V$135:$V$407,"Y") -> 0 | U42: =SUMIFS(U$135:U$407,$C$135:$C$407,$C42,$V$135:$V$407,"Y") -> 0
C43: =TRIM(合并试算平衡表!A65) -> △向中央银行借款 | E43: =SUMIFS(E$134:E$407,$C$134:$C$407,$C43,$G$134:$G$407,"Y") -> 0 | F43: =SUMIFS(F$134:F$407,$C$134:$C$407,$C43,$G$134:$G$407,"Y") -> 0 | H43: =SUMIFS(H$134:H$407,$C$134:$C$407,$C43,$J$134:$J$407,"Y") -> 0 | I43: =SUMIFS(I$134:I$407,$C$134:$C$407,$C43,$J$134:$J$407,"Y") -> 0 | K43: =SUMIFS(K$134:K$407,$C$134:$C$407,$C43,$M$134:$M$407,"Y") -> 0 | L43: =SUMIFS(L$134:L$407,$C$134:$C$407,$C43,$M$134:$M$407,"Y") -> 0 | N43: =SUMIFS(N$135:N$407,$C$135:$C$407,$C43,$P$135:$P$407,"Y") -> 0 | O43: =SUMIFS(O$135:O$407,$C$135:$C$407,$C43,$P$135:$P$407,"Y") -> 0 | Q43: =SUMIFS(Q$135:Q$407,$C$135:$C$407,$C43,$S$135:$S$407,"Y") -> 0 | R43: =SUMIFS(R$135:R$407,$C$135:$C$407,$C43,$S$135:$S$407,"Y") -> 0 | T43: =SUMIFS(T$135:T$407,$C$135:$C$407,$C43,$V$135:$V$407,"Y") -> 0 | U43: =SUMIFS(U$135:U$407,$C$135:$C$407,$C43,$V$135:$V$407,"Y") -> 0
C44: =TRIM(合并试算平衡表!A66) -> △吸收存款及同业存款 | E44: =SUMIFS(E$134:E$407,$C$134:$C$407,$C44,$G$134:$G$407,"Y") -> 0 | F44: =SUMIFS(F$134:F$407,$C$134:$C$407,$C44,$G$134:$G$407,"Y") -> 0 | H44: =SUMIFS(H$134:H$407,$C$134:$C$407,$C44,$J$134:$J$407,"Y") -> 0 | I44: =SUMIFS(I$134:I$407,$C$134:$C$407,$C44,$J$134:$J$407,"Y") -> 0 | K44: =SUMIFS(K$134:K$407,$C$134:$C$407,$C44,$M$134:$M$407,"Y") -> 0 | L44: =SUMIFS(L$134:L$407,$C$134:$C$407,$C44,$M$134:$M$407,"Y") -> 0 | N44: =SUMIFS(N$135:N$407,$C$135:$C$407,$C44,$P$135:$P$407,"Y") -> 0 | O44: =SUMIFS(O$135:O$407,$C$135:$C$407,$C44,$P$135:$P$407,"Y") -> 0 | Q44: =SUMIFS(Q$135:Q$407,$C$135:$C$407,$C44,$S$135:$S$407,"Y") -> 0 | R44: =SUMIFS(R$135:R$407,$C$135:$C$407,$C44,$S$135:$S$407,"Y") -> 0 | T44: =SUMIFS(T$135:T$407,$C$135:$C$407,$C44,$V$135:$V$407,"Y") -> 0 | U44: =SUMIFS(U$135:U$407,$C$135:$C$407,$C44,$V$135:$V$407,"Y") -> 0
C45: =TRIM(合并试算平衡表!A67) -> 交易性金融负债 | E45: =SUMIFS(E$134:E$407,$C$134:$C$407,$C45,$G$134:$G$407,"Y") -> 0 | F45: =SUMIFS(F$134:F$407,$C$134:$C$407,$C45,$G$134:$G$407,"Y") -> 0 | H45: =SUMIFS(H$134:H$407,$C$134:$C$407,$C45,$J$134:$J$407,"Y") -> 0 | I45: =SUMIFS(I$134:I$407,$C$134:$C$407,$C45,$J$134:$J$407,"Y") -> 0 | K45: =SUMIFS(K$134:K$407,$C$134:$C$407,$C45,$M$134:$M$407,"Y") -> 0 | L45: =SUMIFS(L$134:L$407,$C$134:$C$407,$C45,$M$134:$M$407,"Y") -> 0 | N45: =SUMIFS(N$135:N$407,$C$135:$C$407,$C45,$P$135:$P$407,"Y") -> 0 | O45: =SUMIFS(O$135:O$407,$C$135:$C$407,$C45,$P$135:$P$407,"Y") -> 0 | Q45: =SUMIFS(Q$135:Q$407,$C$135:$C$407,$C45,$S$135:$S$407,"Y") -> 0 | R45: =SUMIFS(R$135:R$407,$C$135:$C$407,$C45,$S$135:$S$407,"Y") -> 0 | T45: =SUMIFS(T$135:T$407,$C$135:$C$407,$C45,$V$135:$V$407,"Y") -> 0 | U45: =SUMIFS(U$135:U$407,$C$135:$C$407,$C45,$V$135:$V$407,"Y") -> 0
C46: =TRIM(合并试算平衡表!A68) -> 衍生金融负债 | E46: =SUMIFS(E$134:E$407,$C$134:$C$407,$C46,$G$134:$G$407,"Y") -> 0 | F46: =SUMIFS(F$134:F$407,$C$134:$C$407,$C46,$G$134:$G$407,"Y") -> 0 | H46: =SUMIFS(H$134:H$407,$C$134:$C$407,$C46,$J$134:$J$407,"Y") -> 0 | I46: =SUMIFS(I$134:I$407,$C$134:$C$407,$C46,$J$134:$J$407,"Y") -> 0 | K46: =SUMIFS(K$134:K$407,$C$134:$C$407,$C46,$M$134:$M$407,"Y") -> 0 | L46: =SUMIFS(L$134:L$407,$C$134:$C$407,$C46,$M$134:$M$407,"Y") -> 0 | N46: =SUMIFS(N$135:N$407,$C$135:$C$407,$C46,$P$135:$P$407,"Y") -> 0 | O46: =SUMIFS(O$135:O$407,$C$135:$C$407,$C46,$P$135:$P$407,"Y") -> 0 | Q46: =SUMIFS(Q$135:Q$407,$C$135:$C$407,$C46,$S$135:$S$407,"Y") -> 0 | R46: =SUMIFS(R$135:R$407,$C$135:$C$407,$C46,$S$135:$S$407,"Y") -> 0 | T46: =SUMIFS(T$135:T$407,$C$135:$C$407,$C46,$V$135:$V$407,"Y") -> 0 | U46: =SUMIFS(U$135:U$407,$C$135:$C$407,$C46,$V$135:$V$407,"Y") -> 0
C47: =TRIM(合并试算平衡表!A69) -> △拆入资金 | E47: =SUMIFS(E$134:E$407,$C$134:$C$407,$C47,$G$134:$G$407,"Y") -> 0 | F47: =SUMIFS(F$134:F$407,$C$134:$C$407,$C47,$G$134:$G$407,"Y") -> 0 | H47: =SUMIFS(H$134:H$407,$C$134:$C$407,$C47,$J$134:$J$407,"Y") -> 0 | I47: =SUMIFS(I$134:I$407,$C$134:$C$407,$C47,$J$134:$J$407,"Y") -> 0 | K47: =SUMIFS(K$134:K$407,$C$134:$C$407,$C47,$M$134:$M$407,"Y") -> 0 | L47: =SUMIFS(L$134:L$407,$C$134:$C$407,$C47,$M$134:$M$407,"Y") -> 0 | N47: =SUMIFS(N$135:N$407,$C$135:$C$407,$C47,$P$135:$P$407,"Y") -> 0 | O47: =SUMIFS(O$135:O$407,$C$135:$C$407,$C47,$P$135:$P$407,"Y") -> 0 | Q47: =SUMIFS(Q$135:Q$407,$C$135:$C$407,$C47,$S$135:$S$407,"Y") -> 0 | R47: =SUMIFS(R$135:R$407,$C$135:$C$407,$C47,$S$135:$S$407,"Y") -> 0 | T47: =SUMIFS(T$135:T$407,$C$135:$C$407,$C47,$V$135:$V$407,"Y") -> 0 | U47: =SUMIFS(U$135:U$407,$C$135:$C$407,$C47,$V$135:$V$407,"Y") -> 0
C48: =TRIM(合并试算平衡表!A70) -> 应付票据 | E48: =SUMIFS(E$134:E$407,$C$134:$C$407,$C48,$G$134:$G$407,"Y") -> 0 | F48: =SUMIFS(F$134:F$407,$C$134:$C$407,$C48,$G$134:$G$407,"Y") -> 0 | H48: =SUMIFS(H$134:H$407,$C$134:$C$407,$C48,$J$134:$J$407,"Y") -> 0 | I48: =SUMIFS(I$134:I$407,$C$134:$C$407,$C48,$J$134:$J$407,"Y") -> 0 | K48: =SUMIFS(K$134:K$407,$C$134:$C$407,$C48,$M$134:$M$407,"Y") -> 0 | L48: =SUMIFS(L$134:L$407,$C$134:$C$407,$C48,$M$134:$M$407,"Y") -> 0 | N48: =SUMIFS(N$135:N$407,$C$135:$C$407,$C48,$P$135:$P$407,"Y") -> 0 | O48: =SUMIFS(O$135:O$407,$C$135:$C$407,$C48,$P$135:$P$407,"Y") -> 0 | Q48: =SUMIFS(Q$135:Q$407,$C$135:$C$407,$C48,$S$135:$S$407,"Y") -> 0 | R48: =SUMIFS(R$135:R$407,$C$135:$C$407,$C48,$S$135:$S$407,"Y") -> 0 | T48: =SUMIFS(T$135:T$407,$C$135:$C$407,$C48,$V$135:$V$407,"Y") -> 0 | U48: =SUMIFS(U$135:U$407,$C$135:$C$407,$C48,$V$135:$V$407,"Y") -> 0
C49: =TRIM(合并试算平衡表!A71) -> 应付账款 | E49: =SUMIFS(E$134:E$407,$C$134:$C$407,$C49,$G$134:$G$407,"Y") -> 84166417 | F49: =SUMIFS(F$134:F$407,$C$134:$C$407,$C49,$G$134:$G$407,"Y") -> 0 | H49: =SUMIFS(H$134:H$407,$C$134:$C$407,$C49,$J$134:$J$407,"Y") -> 63078609 | I49: =SUMIFS(I$134:I$407,$C$134:$C$407,$C49,$J$134:$J$407,"Y") -> 0 | K49: =SUMIFS(K$134:K$407,$C$134:$C$407,$C49,$M$134:$M$407,"Y") -> 21170257 | L49: =SUMIFS(L$134:L$407,$C$134:$C$407,$C49,$M$134:$M$407,"Y") -> 0 | N49: =SUMIFS(N$135:N$407,$C$135:$C$407,$C49,$P$135:$P$407,"Y") -> 5028788.1 | O49: =SUMIFS(O$135:O$407,$C$135:$C$407,$C49,$P$135:$P$407,"Y") -> 0 | Q49: =SUMIFS(Q$135:Q$407,$C$135:$C$407,$C49,$S$135:$S$407,"Y") -> 0 | R49: =SUMIFS(R$135:R$407,$C$135:$C$407,$C49,$S$135:$S$407,"Y") -> 0 | T49: =SUMIFS(T$135:T$407,$C$135:$C$407,$C49,$V$135:$V$407,"Y") -> 0 | U49: =SUMIFS(U$135:U$407,$C$135:$C$407,$C49,$V$135:$V$407,"Y") -> 0
C50: =TRIM(合并试算平衡表!A72) -> 预收账款 | E50: =SUMIFS(E$134:E$407,$C$134:$C$407,$C50,$G$134:$G$407,"Y") -> 0 | F50: =SUMIFS(F$134:F$407,$C$134:$C$407,$C50,$G$134:$G$407,"Y") -> 0 | H50: =SUMIFS(H$134:H$407,$C$134:$C$407,$C50,$J$134:$J$407,"Y") -> 0 | I50: =SUMIFS(I$134:I$407,$C$134:$C$407,$C50,$J$134:$J$407,"Y") -> 0 | K50: =SUMIFS(K$134:K$407,$C$134:$C$407,$C50,$M$134:$M$407,"Y") -> 0 | L50: =SUMIFS(L$134:L$407,$C$134:$C$407,$C50,$M$134:$M$407,"Y") -> 0 | N50: =SUMIFS(N$135:N$407,$C$135:$C$407,$C50,$P$135:$P$407,"Y") -> 0 | O50: =SUMIFS(O$135:O$407,$C$135:$C$407,$C50,$P$135:$P$407,"Y") -> 0 | Q50: =SUMIFS(Q$135:Q$407,$C$135:$C$407,$C50,$S$135:$S$407,"Y") -> 0 | R50: =SUMIFS(R$135:R$407,$C$135:$C$407,$C50,$S$135:$S$407,"Y") -> 0 | T50: =SUMIFS(T$135:T$407,$C$135:$C$407,$C50,$V$135:$V$407,"Y") -> 0 | U50: =SUMIFS(U$135:U$407,$C$135:$C$407,$C50,$V$135:$V$407,"Y") -> 0
C51: =TRIM(合并试算平衡表!A74) -> △卖出回购金融资产款 | E51: =SUMIFS(E$134:E$407,$C$134:$C$407,$C51,$G$134:$G$407,"Y") -> 0 | F51: =SUMIFS(F$134:F$407,$C$134:$C$407,$C51,$G$134:$G$407,"Y") -> 0 | H51: =SUMIFS(H$134:H$407,$C$134:$C$407,$C51,$J$134:$J$407,"Y") -> 0 | I51: =SUMIFS(I$134:I$407,$C$134:$C$407,$C51,$J$134:$J$407,"Y") -> 0 | K51: =SUMIFS(K$134:K$407,$C$134:$C$407,$C51,$M$134:$M$407,"Y") -> 0 | L51: =SUMIFS(L$134:L$407,$C$134:$C$407,$C51,$M$134:$M$407,"Y") -> 0 | N51: =SUMIFS(N$135:N$407,$C$135:$C$407,$C51,$P$135:$P$407,"Y") -> 0 | O51: =SUMIFS(O$135:O$407,$C$135:$C$407,$C51,$P$135:$P$407,"Y") -> 0 | Q51: =SUMIFS(Q$135:Q$407,$C$135:$C$407,$C51,$S$135:$S$407,"Y") -> 0 | R51: =SUMIFS(R$135:R$407,$C$135:$C$407,$C51,$S$135:$S$407,"Y") -> 0 | T51: =SUMIFS(T$135:T$407,$C$135:$C$407,$C51,$V$135:$V$407,"Y") -> 0 | U51: =SUMIFS(U$135:U$407,$C$135:$C$407,$C51,$V$135:$V$407,"Y") -> 0
C52: =TRIM(合并试算平衡表!A75) -> △应付手续费及佣金 | E52: =SUMIFS(E$134:E$407,$C$134:$C$407,$C52,$G$134:$G$407,"Y") -> 0 | F52: =SUMIFS(F$134:F$407,$C$134:$C$407,$C52,$G$134:$G$407,"Y") -> 0 | H52: =SUMIFS(H$134:H$407,$C$134:$C$407,$C52,$J$134:$J$407,"Y") -> 0 | I52: =SUMIFS(I$134:I$407,$C$134:$C$407,$C52,$J$134:$J$407,"Y") -> 0 | K52: =SUMIFS(K$134:K$407,$C$134:$C$407,$C52,$M$134:$M$407,"Y") -> 0 | L52: =SUMIFS(L$134:L$407,$C$134:$C$407,$C52,$M$134:$M$407,"Y") -> 0 | N52: =SUMIFS(N$135:N$407,$C$135:$C$407,$C52,$P$135:$P$407,"Y") -> 0 | O52: =SUMIFS(O$135:O$407,$C$135:$C$407,$C52,$P$135:$P$407,"Y") -> 0 | Q52: =SUMIFS(Q$135:Q$407,$C$135:$C$407,$C52,$S$135:$S$407,"Y") -> 0 | R52: =SUMIFS(R$135:R$407,$C$135:$C$407,$C52,$S$135:$S$407,"Y") -> 0 | T52: =SUMIFS(T$135:T$407,$C$135:$C$407,$C52,$V$135:$V$407,"Y") -> 0 | U52: =SUMIFS(U$135:U$407,$C$135:$C$407,$C52,$V$135:$V$407,"Y") -> 0
C53: =TRIM(合并试算平衡表!A76) -> 应付职工薪酬 | E53: =SUMIFS(E$134:E$407,$C$134:$C$407,$C53,$G$134:$G$407,"Y") -> 0 | F53: =SUMIFS(F$134:F$407,$C$134:$C$407,$C53,$G$134:$G$407,"Y") -> 0 | H53: =SUMIFS(H$134:H$407,$C$134:$C$407,$C53,$J$134:$J$407,"Y") -> 0 | I53: =SUMIFS(I$134:I$407,$C$134:$C$407,$C53,$J$134:$J$407,"Y") -> 0 | K53: =SUMIFS(K$134:K$407,$C$134:$C$407,$C53,$M$134:$M$407,"Y") -> 0 | L53: =SUMIFS(L$134:L$407,$C$134:$C$407,$C53,$M$134:$M$407,"Y") -> 0 | N53: =SUMIFS(N$135:N$407,$C$135:$C$407,$C53,$P$135:$P$407,"Y") -> 0 | O53: =SUMIFS(O$135:O$407,$C$135:$C$407,$C53,$P$135:$P$407,"Y") -> 0 | Q53: =SUMIFS(Q$135:Q$407,$C$135:$C$407,$C53,$S$135:$S$407,"Y") -> 0 | R53: =SUMIFS(R$135:R$407,$C$135:$C$407,$C53,$S$135:$S$407,"Y") -> 0 | T53: =SUMIFS(T$135:T$407,$C$135:$C$407,$C53,$V$135:$V$407,"Y") -> 0 | U53: =SUMIFS(U$135:U$407,$C$135:$C$407,$C53,$V$135:$V$407,"Y") -> 0
C54: =TRIM(合并试算平衡表!A77) -> 应交税费 | E54: =SUMIFS(E$134:E$407,$C$134:$C$407,$C54,$G$134:$G$407,"Y") -> 0 | F54: =SUMIFS(F$134:F$407,$C$134:$C$407,$C54,$G$134:$G$407,"Y") -> 0 | H54: =SUMIFS(H$134:H$407,$C$134:$C$407,$C54,$J$134:$J$407,"Y") -> 0 | I54: =SUMIFS(I$134:I$407,$C$134:$C$407,$C54,$J$134:$J$407,"Y") -> 0 | K54: =SUMIFS(K$134:K$407,$C$134:$C$407,$C54,$M$134:$M$407,"Y") -> 0 | L54: =SUMIFS(L$134:L$407,$C$134:$C$407,$C54,$M$134:$M$407,"Y") -> 0 | N54: =SUMIFS(N$135:N$407,$C$135:$C$407,$C54,$P$135:$P$407,"Y") -> 0 | O54: =SUMIFS(O$135:O$407,$C$135:$C$407,$C54,$P$135:$P$407,"Y") -> 0 | Q54: =SUMIFS(Q$135:Q$407,$C$135:$C$407,$C54,$S$135:$S$407,"Y") -> 0 | R54: =SUMIFS(R$135:R$407,$C$135:$C$407,$C54,$S$135:$S$407,"Y") -> 0 | T54: =SUMIFS(T$135:T$407,$C$135:$C$407,$C54,$V$135:$V$407,"Y") -> 0 | U54: =SUMIFS(U$135:U$407,$C$135:$C$407,$C54,$V$135:$V$407,"Y") -> 0
C55: =TRIM(合并试算平衡表!A78) -> 应付利息 | E55: =SUMIFS(E$134:E$407,$C$134:$C$407,$C55,$G$134:$G$407,"Y") -> 0 | F55: =SUMIFS(F$134:F$407,$C$134:$C$407,$C55,$G$134:$G$407,"Y") -> 0 | H55: =SUMIFS(H$134:H$407,$C$134:$C$407,$C55,$J$134:$J$407,"Y") -> 0 | I55: =SUMIFS(I$134:I$407,$C$134:$C$407,$C55,$J$134:$J$407,"Y") -> 0 | K55: =SUMIFS(K$134:K$407,$C$134:$C$407,$C55,$M$134:$M$407,"Y") -> 0 | L55: =SUMIFS(L$134:L$407,$C$134:$C$407,$C55,$M$134:$M$407,"Y") -> 0 | N55: =SUMIFS(N$135:N$407,$C$135:$C$407,$C55,$P$135:$P$407,"Y") -> 0 | O55: =SUMIFS(O$135:O$407,$C$135:$C$407,$C55,$P$135:$P$407,"Y") -> 0 | Q55: =SUMIFS(Q$135:Q$407,$C$135:$C$407,$C55,$S$135:$S$407,"Y") -> 0 | R55: =SUMIFS(R$135:R$407,$C$135:$C$407,$C55,$S$135:$S$407,"Y") -> 0 | T55: =SUMIFS(T$135:T$407,$C$135:$C$407,$C55,$V$135:$V$407,"Y") -> 0 | U55: =SUMIFS(U$135:U$407,$C$135:$C$407,$C55,$V$135:$V$407,"Y") -> 0
C56: =TRIM(合并试算平衡表!A79) -> 应付股利 | E56: =SUMIFS(E$134:E$407,$C$134:$C$407,$C56,$G$134:$G$407,"Y") -> 0 | F56: =SUMIFS(F$134:F$407,$C$134:$C$407,$C56,$G$134:$G$407,"Y") -> 0 | H56: =SUMIFS(H$134:H$407,$C$134:$C$407,$C56,$J$134:$J$407,"Y") -> 0 | I56: =SUMIFS(I$134:I$407,$C$134:$C$407,$C56,$J$134:$J$407,"Y") -> 0 | K56: =SUMIFS(K$134:K$407,$C$134:$C$407,$C56,$M$134:$M$407,"Y") -> 0 | L56: =SUMIFS(L$134:L$407,$C$134:$C$407,$C56,$M$134:$M$407,"Y") -> 0 | N56: =SUMIFS(N$135:N$407,$C$135:$C$407,$C56,$P$135:$P$407,"Y") -> 0 | O56: =SUMIFS(O$135:O$407,$C$135:$C$407,$C56,$P$135:$P$407,"Y") -> 0 | Q56: =SUMIFS(Q$135:Q$407,$C$135:$C$407,$C56,$S$135:$S$407,"Y") -> 0 | R56: =SUMIFS(R$135:R$407,$C$135:$C$407,$C56,$S$135:$S$407,"Y") -> 0 | T56: =SUMIFS(T$135:T$407,$C$135:$C$407,$C56,$V$135:$V$407,"Y") -> 0 | U56: =SUMIFS(U$135:U$407,$C$135:$C$407,$C56,$V$135:$V$407,"Y") -> 0
C57: =TRIM(合并试算平衡表!A80) -> 其他应付款 | E57: =SUMIFS(E$134:E$407,$C$134:$C$407,$C57,$G$134:$G$407,"Y") -> 0 | F57: =SUMIFS(F$134:F$407,$C$134:$C$407,$C57,$G$134:$G$407,"Y") -> 0 | H57: =SUMIFS(H$134:H$407,$C$134:$C$407,$C57,$J$134:$J$407,"Y") -> 336853 | I57: =SUMIFS(I$134:I$407,$C$134:$C$407,$C57,$J$134:$J$407,"Y") -> 0 | K57: =SUMIFS(K$134:K$407,$C$134:$C$407,$C57,$M$134:$M$407,"Y") -> 1668414.2 | L57: =SUMIFS(L$134:L$407,$C$134:$C$407,$C57,$M$134:$M$407,"Y") -> 0 | N57: =SUMIFS(N$135:N$407,$C$135:$C$407,$C57,$P$135:$P$407,"Y") -> 0 | O57: =SUMIFS(O$135:O$407,$C$135:$C$407,$C57,$P$135:$P$407,"Y") -> 0 | Q57: =SUMIFS(Q$135:Q$407,$C$135:$C$407,$C57,$S$135:$S$407,"Y") -> 0 | R57: =SUMIFS(R$135:R$407,$C$135:$C$407,$C57,$S$135:$S$407,"Y") -> 0 | T57: =SUMIFS(T$135:T$407,$C$135:$C$407,$C57,$V$135:$V$407,"Y") -> 0 | U57: =SUMIFS(U$135:U$407,$C$135:$C$407,$C57,$V$135:$V$407,"Y") -> 0
C58: =TRIM(合并试算平衡表!A81) -> △应付分保账款 | E58: =SUMIFS(E$134:E$407,$C$134:$C$407,$C58,$G$134:$G$407,"Y") -> 0 | F58: =SUMIFS(F$134:F$407,$C$134:$C$407,$C58,$G$134:$G$407,"Y") -> 0 | H58: =SUMIFS(H$134:H$407,$C$134:$C$407,$C58,$J$134:$J$407,"Y") -> 0 | I58: =SUMIFS(I$134:I$407,$C$134:$C$407,$C58,$J$134:$J$407,"Y") -> 0 | K58: =SUMIFS(K$134:K$407,$C$134:$C$407,$C58,$M$134:$M$407,"Y") -> 0 | L58: =SUMIFS(L$134:L$407,$C$134:$C$407,$C58,$M$134:$M$407,"Y") -> 0 | N58: =SUMIFS(N$135:N$407,$C$135:$C$407,$C58,$P$135:$P$407,"Y") -> 0 | O58: =SUMIFS(O$135:O$407,$C$135:$C$407,$C58,$P$135:$P$407,"Y") -> 0 | Q58: =SUMIFS(Q$135:Q$407,$C$135:$C$407,$C58,$S$135:$S$407,"Y") -> 0 | R58: =SUMIFS(R$135:R$407,$C$135:$C$407,$C58,$S$135:$S$407,"Y") -> 0 | T58: =SUMIFS(T$135:T$407,$C$135:$C$407,$C58,$V$135:$V$407,"Y") -> 0 | U58: =SUMIFS(U$135:U$407,$C$135:$C$407,$C58,$V$135:$V$407,"Y") -> 0
